Workbook

Sheet Company Summary W Graphs
B2: Company Overview | C2: Our company is developing an AI-driven financial projection tool that helps founders quickly produce credible, data-backed five-year forecasts. By licensing Taft’s extensive repository of early-stage startup data, we are creating an Agentic AI-based model to ask founders a series of guided questions and generate robust, investor-ready projections. This reduces human error and bias, offering a level of rigor that most first-time founders struggle to achieve. With our platform, we plan to target startups, as well as accelerators, incubators, and venture capital firms, positioning ourselves as the go-to resource for reliable, real-time financial planning.
B3: Pricing Model | C3: Hybrid tiered pricing model Basic SaaS: A cost-effective subscription tier for early-stage founders, offering core financial projection features and limited customization. Fully Customizable Service: A premium tier that provides white-glove onboarding, extensive data integrations, advanced analytics, and dedicated support—ideal for larger startups, accelerators, or corporate clients looking for in-depth forecasting capabilities.
A6: Date | B6: =Rev!M3&" "&Rev!M4 -> Year 1 Jan | C6: =Rev!N3&" "&Rev!N4 -> Year 1 Feb | D6: =Rev!O3&" "&Rev!O4 -> Year 1 Mar | E6: =Rev!P3&" "&Rev!P4 -> Year 1 Apr | F6: =Rev!Q3&" "&Rev!Q4 -> Year 1 May | G6: =Rev!R3&" "&Rev!R4 -> Year 1 Jun | H6: =Rev!S3&" "&Rev!S4 -> Year 1 Jul | I6: =Rev!T3&" "&Rev!T4 -> Year 1 Aug | ... BI6: =Rev!BT3&" "&Rev!BT4 -> Year 5 Dec
A7: Ending Cash | B7: {='P&L'!M75:BT75} -> 617172.57 | C7: 512345.14 | D7: 407517.7 | E7: 288173.61 | F7: 168829.51 | G7: 33968.742 | H7: -97229.023 | I7: -227457.79 | J7: -361361.39 | K7: 2005361.5 | L7: 1873406.4 | M7: 1738833 | N7: 1552694.1 | O7: 1387343.6 | P7: 1207295.3 | Q7: 995125.28 | R7: 783243.08 | S7: 559631.57 | T7: 331237.69 | U7: 109072.91 | V7: -132139.9 | W7: 8630837.2 | X7: 8397789.5 | Y7: 8166599.6 | Z7: 7956205.9 | AA7: 7775902.1 | AB7: 7595158.2 | AC7: 7436229.9 | AD7: 7278614.8 | AE7: 7125230.6 | AF7: 6992147.4 | AG7: 6864273.2 | AH7: 6752650.7 | AI7: 6660548.1 | AJ7: 6588286.8 | AK7: 6554663.4 | AL7: 6530521.4 | AM7: 6573280.6 | AN7: 6664225.4 | AO7: 6788803.3 | AP7: 6957920.5 | AQ7: 7183643.3 | AR7: 7459521.4 | AS7: 7776336 | AT7: 8131156.2 | AU7: 8548310.6 | AV7: 9009812.8 | AW7: 9541652.7 | AX7: 10318233 | AY7: 11205780 | AZ7: 12197103 | BA7: 13299714 | BB7: 14517283 | BC7: 15850430 | BD7: 17309838 | BE7: 18904620 | BF7: 20631423 | BG7: 22510143 | BH7: 24541678 | BI7: 26735190
A8: Op Income | B8: {='P&L'!M36:BT36} -> -128508.33 | C8: -128508.33 | D8: -128508.33 | E8: -143025 | F8: -143025 | G8: -158541.67 | H8: -154683.67 | I8: -153825.67 | J8: -157535.5 | K8: -156917.5 | L8: -155559.5 | M8: -158190.33 | N8: -192831.25 | O8: -188381.25 | P8: -203251.25 | Q8: -235472.56 | R8: -235339 | S8: -247097.31 | T8: -251620.88 | U8: -245441.88 | V8: -235614.56 | W8: -231651.5 | X8: -227465.28 | Y8: -225674.75 | Z8: -176898.51 | AA8: -173601.01 | AB8: -174827.34 | AC8: -152571.67 | AD8: -151124.25 | AE8: -147001.21 | AF8: -126746.03 | AG8: -121570.54 | AH8: -105029.04 | AI8: -85211.115 | AJ8: -65864.569 | AK8: -26317.595 | AL8: 12872.627 | AM8: 64862.088 | AN8: 124041.99 | AO8: 165029.46 | AP8: 221556.53 | AQ8: 292406.49 | AR8: 356965.91 | AS8: 407289.02 | AT8: 454307.13 | AU8: 533275.64 | AV8: 588344.72 | AW8: 677405.54 | AX8: 1001238 | AY8: 1128610.1 | AZ8: 1255120 | BA8: 1395051.2 | BB8: 1539214.7 | BC8: 1683802.5 | BD8: 1842560.3 | BE8: 2012712.5 | BF8: 2177587.1 | BG8: 2369138.3 | BH8: 2560519 | BI8: 2763780.5
A9: Rev | B9: {=Rev!M77:BT77} -> 0 | C9: 0 | D9: 0 | E9: 0 | F9: 0 | G9: 0 | H9: 3900 | I9: 4800 | J9: 5600 | K9: 6250 | L9: 7650 | M9: 8650 | N9: 48220 | O9: 53310 | P9: 61850 | Q9: 67710 | R9: 71020 | S9: 74260 | T9: 82690 | U9: 89080 | V9: 98385 | W9: 102570 | X9: 112000 | Y9: 119035 | Z9: 206150 | AA9: 221400 | AB9: 235300 | AC9: 258270 | AD9: 282110 | AE9: 303620 | AF9: 324680 | AG9: 345160 | AH9: 371550 | AI9: 402720 | AJ9: 423040 | AK9: 463710 | AL9: 631850 | AM9: 688190 | AN9: 749940 | AO9: 793630 | AP9: 854460 | AQ9: 913230 | AR9: 1002140 | AS9: 1071340 | AT9: 1136540 | AU9: 1219230 | AV9: 1292450 | AW9: 1385660 | AX9: 1761250 | AY9: 1898870 | AZ9: 2032610 | BA9: 2180120 | BB9: 2332200 | BC9: 2485100 | BD9: 2652590 | BE9: 2832010 | BF9: 3006470 | BG9: 3208270 | BH9: 3410270 | BI9: 3624740
A10: {=A6:BI6} -> Date | B10: Year 1 Jan | C10: Year 1 Feb | D10: Year 1 Mar | E10: Year 1 Apr | F10: Year 1 May | G10: Year 1 Jun | H10: Year 1 Jul | I10: Year 1 Aug | J10: Year 1 Sep | K10: Year 1 Oct | L10: Year 1 Nov | M10: Year 1 Dec | N10: Year 2 Jan | O10: Year 2 Feb | P10: Year 2 Mar | Q10: Year 2 Apr | R10: Year 2 May | S10: Year 2 Jun | T10: Year 2 Jul | U10: Year 2 Aug | V10: Year 2 Sep | W10: Year 2 Oct | X10: Year 2 Nov | Y10: Year 2 Dec | Z10: Year 3 Jan | AA10: Year 3 Feb | AB10: Year 3 Mar | AC10: Year 3 Apr | AD10: Year 3 May | AE10: Year 3 Jun | AF10: Year 3 Jul | AG10: Year 3 Aug | AH10: Year 3 Sep | AI10: Year 3 Oct | AJ10: Year 3 Nov | AK10: Year 3 Dec | AL10: Year 4 Jan | AM10: Year 4 Feb | AN10: Year 4 Mar | AO10: Year 4 Apr | AP10: Year 4 May | AQ10: Year 4 Jun | AR10: Year 4 Jul | AS10: Year 4 Aug | AT10: Year 4 Sep | AU10: Year 4 Oct | AV10: Year 4 Nov | AW10: Year 4 Dec | AX10: Year 5 Jan | AY10: Year 5 Feb | AZ10: Year 5 Mar | BA10: Year 5 Apr | BB10: Year 5 May | BC10: Year 5 Jun | BD10: Year 5 Jul | BE10: Year 5 Aug | BF10: Year 5 Sep | BG10: Year 5 Oct | BH10: Year 5 Nov | BI10: Year 5 Dec
A12: {='P&L'!J28:J31} -> R&D | B12: {='P&L'!M28:BT31} -> 16516.667 | C12: 16516.667 | D12: 16516.667 | E12: 31033.333 | F12: 31033.333 | G12: 45550 | H12: 45550 | I12: 45550 | J12: 45550 | K12: 45550 | L12: 45550 | M12: 45550 | N12: 62049.167 | O12: 62049.167 | P12: 78090.833 | Q12: 92099.167 | R12: 92099.167 | S12: 106920.83 | T12: 119687.5 | U12: 119687.5 | V12: 119687.5 | W12: 119687.5 | X12: 119687.5 | Y12: 119687.5 | Z12: 124986.88 | AA12: 135436.88 | AB12: 149953.54 | AC12: 149953.54 | AD12: 166583.54 | AE12: 183133.54 | AF12: 183133.54 | AG12: 197650.21 | AH12: 206575.21 | AI12: 216945.21 | AJ12: 216945.21 | AK12: 216945.21 | AL12: 257719.14 | AM12: 257719.14 | AN12: 257719.14 | AO12: 257719.14 | AP12: 272235.8 | AQ12: 272235.8 | AR12: 288277.47 | AS12: 303810.8 | AT12: 318632.47 | AU12: 318632.47 | AV12: 333149.14 | AW12: 333149.14 | AX12: 348211.59 | AY12: 348211.59 | AZ12: 348211.59 | BA12: 348211.59 | BB12: 348211.59 | BC12: 348211.59 | BD12: 348211.59 | BE12: 348211.59 | BF12: 348211.59 | BG12: 348211.59 | BH12: 348211.59 | BI12: 348211.59
A13: Marketing | B13: 12750 | C13: 12750 | D13: 12750 | E13: 12750 | F13: 12750 | G13: 12750 | H13: 12750 | I13: 12750 | J13: 12750 | K13: 12750 | L13: 12750 | M13: 12750 | N13: 22525 | O13: 22525 | P13: 22525 | Q13: 22525 | R13: 22525 | S13: 22525 | T13: 22525 | U13: 22525 | V13: 22525 | W13: 22525 | X13: 22525 | Y13: 22525 | Z13: 28483.333 | AA13: 28483.333 | AB13: 28483.333 | AC13: 28483.333 | AD13: 28483.333 | AE13: 28483.333 | AF13: 28483.333 | AG13: 28483.333 | AH13: 28483.333 | AI13: 28483.333 | AJ13: 28483.333 | AK13: 28483.333 | AL13: 33775 | AM13: 33775 | AN13: 33775 | AO13: 33775 | AP13: 33775 | AQ13: 33775 | AR13: 33775 | AS13: 33775 | AT13: 33775 | AU13: 33775 | AV13: 33775 | AW13: 33775 | AX13: 38650 | AY13: 38650 | AZ13: 38650 | BA13: 38650 | BB13: 38650 | BC13: 38650 | BD13: 38650 | BE13: 38650 | BF13: 38650 | BG13: 38650 | BH13: 38650 | BI13: 38650
A14: G&A | B14: 98741.667 | C14: 98741.667 | D14: 98741.667 | E14: 98741.667 | F14: 98741.667 | G14: 98741.667 | H14: 98741.667 | I14: 98741.667 | J14: 103215 | K14: 103215 | L14: 103215 | M14: 106798.33 | N14: 131263.33 | O14: 131263.33 | P14: 138446.67 | Q14: 162338.33 | R14: 165338.33 | S14: 165338.33 | T14: 165338.33 | U14: 165338.33 | V14: 164588.33 | W14: 164588.33 | X14: 169588.33 | Y14: 174588.33 | Z14: 188720 | AA14: 188720 | AB14: 188720 | AC14: 188720 | AD14: 193720 | AE14: 193720 | AF14: 193720 | AG14: 193720 | AH14: 193720 | AI14: 193720 | AJ14: 193720 | AK14: 193720 | AL14: 250545 | AM14: 250545 | AN14: 250545 | AO14: 250545 | AP14: 237545 | AQ14: 222545 | AR14: 227545 | AS14: 227545 | AT14: 227545 | AU14: 227545 | AV14: 227545 | AW14: 227545 | AX14: 227545 | AY14: 227545 | AZ14: 227545 | BA14: 227545 | BB14: 227545 | BC14: 227545 | BD14: 227545 | BE14: 227545 | BF14: 227545 | BG14: 227545 | BH14: 227545 | BI14: 227545
A15: Sales | B15: 500 | C15: 500 | D15: 500 | E15: 500 | F15: 500 | G15: 500 | H15: 500 | I15: 500 | J15: 500 | K15: 500 | L15: 500 | M15: 500 | N15: 22312.5 | O15: 22837.5 | P15: 22863.75 | Q15: 22891.312 | R15: 22920.253 | S15: 22950.641 | T15: 22982.548 | U15: 23016.05 | V15: 23051.228 | W15: 23088.164 | X15: 23126.947 | Y15: 23167.67 | Z15: 32413.553 | AA15: 33328.927 | AB15: 33419.592 | AC15: 33514.791 | AD15: 33614.749 | AE15: 33719.705 | AF15: 33829.909 | AG15: 33945.624 | AH15: 34067.124 | AI15: 34194.698 | AJ15: 34328.652 | AK15: 34469.304 | AL15: 51713.862 | AM15: 53839.402 | AN15: 54100.747 | AO15: 54375.159 | AP15: 54663.292 | AQ15: 54965.832 | AR15: 55283.498 | AS15: 55617.048 | AT15: 55967.276 | AU15: 56335.014 | AV15: 56721.14 | AW15: 57126.572 | AX15: 66155.401 | AY15: 70168.266 | AZ15: 70815.898 | BA15: 71495.912 | BB15: 72209.926 | BC15: 72959.641 | BD15: 73746.842 | BE15: 74573.403 | BF15: 75441.292 | BG15: 76352.575 | BH15: 77309.423 | BI15: 78314.113

Sheet Investor Table
B2: Attribute | C2: Description
B3: Company Name | C3: Finsight - “Financial insight at your fingertips.”
B4: Industry | C4: Financial Technology / Artificial Intelligence
B5: Core Offering | C5: AI-driven financial forecasting tool that generates accurate, data-backed five-year projections
B6: Value Proposition | C6: Leverages proprietary early-stage data to eliminate bias and uncertainty, empowering startups and investors with objective, reliable forecasts
B7: Target Markets | C7: Early-stage startups, mid-cap companies, and large enterprises requiring scalable, tailored financial projections
B8: Revenue Model | C8: Tiered SaaS pricing: Basic self-service platform for startups and a premium, customizable solution for larger clients
B9: Growth Strategy | C9: Phased team expansion with targeted sales and marketing investments, continuous product enhancements heavy focus on RnD, and strategic market penetration

Sheet Rev
B3: Assumptions | M3: Year 1 | N3: Year 1 | O3: Year 1 | P3: Year 1 | Q3: Year 1 | R3: Year 1 | S3: Year 1 | T3: Year 1 | U3: Year 1 | V3: Year 1 | W3: Year 1 | X3: Year 1 | Y3: Year 2 | Z3: Year 2 | AA3: Year 2 | AB3: Year 2 | AC3: Year 2 | AD3: Year 2 | AE3: Year 2 | AF3: Year 2 | AG3: Year 2 | AH3: Year 2 | AI3: Year 2 | AJ3: Year 2 | AK3: Year 3 | AL3: Year 3 | AM3: Year 3 | AN3: Year 3 | AO3: Year 3 | AP3: Year 3 | AQ3: Year 3 | AR3: Year 3 | AS3: Year 3 | AT3: Year 3 | AU3: Year 3 | AV3: Year 3 | AW3: Year 4 | AX3: Year 4 | AY3: Year 4 | AZ3: Year 4 | BA3: Year 4 | BB3: Year 4 | BC3: Year 4 | BD3: Year 4 | BE3: Year 4 | BF3: Year 4 | BG3: Year 4 | BH3: Year 4 | BI3: Year 5 | BJ3: Year 5 | BK3: Year 5 | BL3: Year 5 | BM3: Year 5 | BN3: Year 5 | BO3: Year 5 | BP3: Year 5 | BQ3: Year 5 | BR3: Year 5 | BS3: Year 5 | BT3: Year 5
B4: Formulaic | M4: Jan | N4: Feb | O4: Mar | P4: Apr | Q4: May | R4: Jun | S4: Jul | T4: Aug | U4: Sep | V4: Oct | W4: Nov | X4: Dec | Y4: Jan | Z4: Feb | AA4: Mar | AB4: Apr | AC4: May | AD4: Jun | AE4: Jul | AF4: Aug | AG4: Sep | AH4: Oct | AI4: Nov | AJ4: Dec | AK4: Jan | AL4: Feb | AM4: Mar | AN4: Apr | AO4: May | AP4: Jun | AQ4: Jul | AR4: Aug | AS4: Sep | AT4: Oct | AU4: Nov | AV4: Dec | AW4: Jan | AX4: Feb | AY4: Mar | AZ4: Apr | BA4: May | BB4: Jun | BC4: Jul | BD4: Aug | BE4: Sep | BF4: Oct | BG4: Nov | BH4: Dec | BI4: Jan | BJ4: Feb | BK4: Mar | BL4: Apr | BM4: May | BN4: Jun | BO4: Jul | BP4: Aug | BQ4: Sep | BR4: Oct | BS4: Nov | BT4: Dec
C7: Year | D7: 1 | E7: 2 | F7: 3 | G7: 4 | H7: 5 | J7: Onetime Fee | L7: New customers | M7: =SUM(M12:M18) -> 0 | N7: =SUM(N12:N18) -> 0 | O7: =SUM(O12:O18) -> 0 | P7: =SUM(P12:P18) -> 0 | Q7: =SUM(Q12:Q18) -> 0 | R7: =SUM(R12:R18) -> 0 | S7: =SUM(S12:S18) -> 6 | T7: =SUM(T12:T18) -> 6 | ... BT7: =SUM(BT12:BT18) -> 287
B8: Onetime fee | L8: Total Onetime Fee Rev | M8: =_xlfn.XLOOKUP(_xlfn.NUMBERVALUE(RIGHT(M$3,1)),$D$7:$H$7,$D$9:$H$9)*M7 -> 0 | N8: =_xlfn.XLOOKUP(_xlfn.NUMBERVALUE(RIGHT(N$3,1)),$D$7:$H$7,$D$9:$H$9)*N7 -> 0 | O8: =_xlfn.XLOOKUP(_xlfn.NUMBERVALUE(RIGHT(O$3,1)),$D$7:$H$7,$D$9:$H$9)*O7 -> 0 | P8: =_xlfn.XLOOKUP(_xlfn.NUMBERVALUE(RIGHT(P$3,1)),$D$7:$H$7,$D$9:$H$9)*P7 -> 0 | Q8: =_xlfn.XLOOKUP(_xlfn.NUMBERVALUE(RIGHT(Q$3,1)),$D$7:$H$7,$D$9:$H$9)*Q7 -> 0 | R8: =_xlfn.XLOOKUP(_xlfn.NUMBERVALUE(RIGHT(R$3,1)),$D$7:$H$7,$D$9:$H$9)*R7 -> 0 | S8: =_xlfn.XLOOKUP(_xlfn.NUMBERVALUE(RIGHT(S$3,1)),$D$7:$H$7,$D$9:$H$9)*S7 -> 3000 | T8: =_xlfn.XLOOKUP(_xlfn.NUMBERVALUE(RIGHT(T$3,1)),$D$7:$H$7,$D$9:$H$9)*T7 -> 3000 | ... BT8: =_xlfn.XLOOKUP(_xlfn.NUMBERVALUE(RIGHT(BT$3,1)),$D$7:$H$7,$D$9:$H$9)*BT7 -> 1291500
B9: 1.5 | C9: All Tiers | D9: 500 | E9: 2500 | F9: 3500 | G9: 4000 | H9: 4500
B10: Monthly Base Subscription Price
C11: Small Cap | D11: 100 | E11: 120 | F11: 140 | G11: 160 | H11: 180 | J11: Monthly Units (Customers Rounded w/o attrition)
C12: Mid Cap | D12: 199 | E12: 230 | F12: 260 | G12: 290 | H12: 320 | K12: Basic | L12: Small Cap | M12: =ROUND(M21,0) -> 0 | N12: =ROUND(N21,0) -> 0 | O12: =ROUND(O21,0) -> 0 | P12: =ROUND(P21,0) -> 0 | Q12: =ROUND(Q21,0) -> 0 | R12: =ROUND(R21,0) -> 0 | S12: =ROUND(S21,0) -> 4 | T12: =ROUND(T21,0) -> 4 | ... BT12: =ROUND(BT21,0) -> 9
C13: Large Cap | D13: 500 | E13: 550 | F13: 600 | G13: 650 | H13: 700 | L13: Mid Cap | M13: =ROUND(M22,0) -> 0 | N13: =ROUND(N22,0) -> 0 | O13: =ROUND(O22,0) -> 0 | P13: =ROUND(P22,0) -> 0 | Q13: =ROUND(Q22,0) -> 0 | R13: =ROUND(R22,0) -> 0 | S13: =ROUND(S22,0) -> 0 | T13: =ROUND(T22,0) -> 0 | ... BT13: =ROUND(BT22,0) -> 49
B14: Monthly Base Premium Price | L14: Large Cap | M14: =ROUND(M23,0) -> 0 | N14: =ROUND(N23,0) -> 0 | O14: =ROUND(O23,0) -> 0 | P14: =ROUND(P23,0) -> 0 | Q14: =ROUND(Q23,0) -> 0 | R14: =ROUND(R23,0) -> 0 | S14: =ROUND(S23,0) -> 0 | T14: =ROUND(T23,0) -> 0 | ... BT14: =ROUND(BT23,0) -> 86
B15: 0.5 | C15: {=C11:C13} -> Small Cap | D15: 250 | E15: 300 | F15: 350 | G15: 400 | H15: 450
C16: Mid Cap | D16: 450 | E16: 525 | F16: 580 | G16: 650 | H16: 750 | K16: Premium | L16: Small Cap | M16: =ROUND(M25,0) -> 0 | N16: =ROUND(N25,0) -> 0 | O16: =ROUND(O25,0) -> 0 | P16: =ROUND(P25,0) -> 0 | Q16: =ROUND(Q25,0) -> 0 | R16: =ROUND(R25,0) -> 0 | S16: =ROUND(S25,0) -> 2 | T16: =ROUND(T25,0) -> 2 | ... BT16: =ROUND(BT25,0) -> 14
C17: Large Cap | D17: 850 | E17: 900 | F17: 1150 | G17: 1200 | H17: 1400 | L17: Mid Cap | M17: =ROUND(M26,0) -> 0 | N17: =ROUND(N26,0) -> 0 | O17: =ROUND(O26,0) -> 0 | P17: =ROUND(P26,0) -> 0 | Q17: =ROUND(Q26,0) -> 0 | R17: =ROUND(R26,0) -> 0 | S17: =ROUND(S26,0) -> 0 | T17: =ROUND(T26,0) -> 0 | ... BT17: =ROUND(BT26,0) -> 57
L18: Large Cap | M18: =ROUND(M27,0) -> 0 | N18: =ROUND(N27,0) -> 0 | O18: =ROUND(O27,0) -> 0 | P18: =ROUND(P27,0) -> 0 | Q18: =ROUND(Q27,0) -> 0 | R18: =ROUND(R27,0) -> 0 | S18: =ROUND(S27,0) -> 0 | T18: =ROUND(T27,0) -> 0 | ... BT18: =ROUND(BT27,0) -> 72
B19: Monthly Base Sales Mix
C20: Small Cap | D20: 0.7 | E20: 0.4 | F20: 0.2 | G20: 0.05 | H20: 0.03 | J20: Monthly Sales | M20: {='Sales Rev'!M13:BT13} -> 4 | N20: 4.2 | O20: 4.41 | P20: 4.6305 | Q20: 4.862025 | R20: 5.1051263 | S20: 5.3603826 | T20: 5.6284017 | U20: 5.9098218 | V20: 6.2053129 | W20: 6.5155785 | X20: 6.8413574 | Y20: 16.441357 | Z20: 17.263425 | AA20: 18.126597 | AB20: 19.032926 | AC20: 19.984573 | AD20: 20.983801 | AE20: 22.032991 | AF20: 23.134641 | AG20: 24.291373 | AH20: 25.505942 | AI20: 26.781239 | AJ20: 28.120301 | AK20: 38.320301 | AL20: 40.236316 | AM20: 42.248132 | AN20: 44.360538 | AO20: 46.578565 | AP20: 48.907493 | AQ20: 51.352868 | AR20: 53.920511 | AS20: 56.616537 | AT20: 59.447364 | AU20: 62.419732 | AV20: 65.540719 | AW20: 84.140719 | AX20: 88.347754 | AY20: 92.765142 | AZ20: 97.403399 | BA20: 102.27357 | BB20: 107.38725 | BC20: 112.75661 | BD20: 118.39444 | BE20: 124.31416 | BF20: 130.52987 | BG20: 137.05636 | BH20: 143.90918 | BI20: 167.30918 | BJ20: 175.67464 | BK20: 184.45837 | BL20: 193.68129 | BM20: 203.36536 | BN20: 213.53362 | BO20: 224.21031 | BP20: 235.42082 | BQ20: 247.19186 | BR20: 259.55146 | BS20: 272.52903 | BT20: 286.15548
C21: Mid Cap | E21: 0.2 | F21: 0.3 | G21: 0.3 | H21: 0.17 | K21: Basic | L21: Small Cap | M21: 0 | N21: 0 | O21: 0 | P21: 0 | Q21: 0 | R21: 0 | S21: =S$20*_xlfn.XLOOKUP(_xlfn.NUMBERVALUE(RIGHT(S$3,1)),$D$7:$H$7,$D20:$H20) -> 3.7522678 | T21: =T$20*_xlfn.XLOOKUP(_xlfn.NUMBERVALUE(RIGHT(T$3,1)),$D$7:$H$7,$D20:$H20) -> 3.9398812 | U21: =U$20*_xlfn.XLOOKUP(_xlfn.NUMBERVALUE(RIGHT(U$3,1)),$D$7:$H$7,$D20:$H20) -> 4.1368752 | V21: =V$20*_xlfn.XLOOKUP(_xlfn.NUMBERVALUE(RIGHT(V$3,1)),$D$7:$H$7,$D20:$H20) -> 4.343719 | W21: =W$20*_xlfn.XLOOKUP(_xlfn.NUMBERVALUE(RIGHT(W$3,1)),$D$7:$H$7,$D20:$H20) -> 4.560905 | X21: =X$20*_xlfn.XLOOKUP(_xlfn.NUMBERVALUE(RIGHT(X$3,1)),$D$7:$H$7,$D20:$H20) -> 4.7889502 | Y21: =Y$20*_xlfn.XLOOKUP(_xlfn.NUMBERVALUE(RIGHT(Y$3,1)),$D$7:$H$7,$D20:$H20) -> 6.576543 | Z21: =Z$20*_xlfn.XLOOKUP(_xlfn.NUMBERVALUE(RIGHT(Z$3,1)),$D$7:$H$7,$D20:$H20) -> 6.9053701 | ... BT21: =BT$20*_xlfn.XLOOKUP(_xlfn.NUMBERVALUE(RIGHT(BT$3,1)),$D$7:$H$7,$D20:$H20) -> 8.5846644
C22: Large Cap | F22: 0.1 | G22: 0.2 | H22: 0.3 | L22: Mid Cap | M22: =M$20*_xlfn.XLOOKUP(_xlfn.NUMBERVALUE(RIGHT(M$3,1)),$D$7:$H$7,$D21:$H21) -> 0 | N22: =N$20*_xlfn.XLOOKUP(_xlfn.NUMBERVALUE(RIGHT(N$3,1)),$D$7:$H$7,$D21:$H21) -> 0 | O22: =O$20*_xlfn.XLOOKUP(_xlfn.NUMBERVALUE(RIGHT(O$3,1)),$D$7:$H$7,$D21:$H21) -> 0 | P22: =P$20*_xlfn.XLOOKUP(_xlfn.NUMBERVALUE(RIGHT(P$3,1)),$D$7:$H$7,$D21:$H21) -> 0 | Q22: =Q$20*_xlfn.XLOOKUP(_xlfn.NUMBERVALUE(RIGHT(Q$3,1)),$D$7:$H$7,$D21:$H21) -> 0 | R22: =R$20*_xlfn.XLOOKUP(_xlfn.NUMBERVALUE(RIGHT(R$3,1)),$D$7:$H$7,$D21:$H21) -> 0 | S22: =S$20*_xlfn.XLOOKUP(_xlfn.NUMBERVALUE(RIGHT(S$3,1)),$D$7:$H$7,$D21:$H21) -> 0 | T22: =T$20*_xlfn.XLOOKUP(_xlfn.NUMBERVALUE(RIGHT(T$3,1)),$D$7:$H$7,$D21:$H21) -> 0 | ... BT22: =BT$20*_xlfn.XLOOKUP(_xlfn.NUMBERVALUE(RIGHT(BT$3,1)),$D$7:$H$7,$D21:$H21) -> 48.646432
B23: Monthly Base Premium Sales Mix | L23: Large Cap | M23: =M$20*_xlfn.XLOOKUP(_xlfn.NUMBERVALUE(RIGHT(M$3,1)),$D$7:$H$7,$D22:$H22) -> 0 | N23: =N$20*_xlfn.XLOOKUP(_xlfn.NUMBERVALUE(RIGHT(N$3,1)),$D$7:$H$7,$D22:$H22) -> 0 | O23: =O$20*_xlfn.XLOOKUP(_xlfn.NUMBERVALUE(RIGHT(O$3,1)),$D$7:$H$7,$D22:$H22) -> 0 | P23: =P$20*_xlfn.XLOOKUP(_xlfn.NUMBERVALUE(RIGHT(P$3,1)),$D$7:$H$7,$D22:$H22) -> 0 | Q23: =Q$20*_xlfn.XLOOKUP(_xlfn.NUMBERVALUE(RIGHT(Q$3,1)),$D$7:$H$7,$D22:$H22) -> 0 | R23: =R$20*_xlfn.XLOOKUP(_xlfn.NUMBERVALUE(RIGHT(R$3,1)),$D$7:$H$7,$D22:$H22) -> 0 | S23: =S$20*_xlfn.XLOOKUP(_xlfn.NUMBERVALUE(RIGHT(S$3,1)),$D$7:$H$7,$D22:$H22) -> 0 | T23: =T$20*_xlfn.XLOOKUP(_xlfn.NUMBERVALUE(RIGHT(T$3,1)),$D$7:$H$7,$D22:$H22) -> 0 | ... BT23: =BT$20*_xlfn.XLOOKUP(_xlfn.NUMBERVALUE(RIGHT(BT$3,1)),$D$7:$H$7,$D22:$H22) -> 85.846644
C24: {=C20:C22} -> Small Cap | D24: 0.3 | E24: 0.25 | F24: 0.15 | G24: 0.05 | H24: 0.05
C25: Mid Cap | E25: 0.15 | F25: 0.15 | G25: 0.2 | H25: 0.2 | K25: Premium | L25: Small Cap | M25: 0 | N25: 0 | O25: 0 | P25: 0 | Q25: 0 | R25: 0 | S25: =S$20*_xlfn.XLOOKUP(_xlfn.NUMBERVALUE(RIGHT(S$3,1)),$D$7:$H$7,$D24:$H24) -> 1.6081148 | T25: =T$20*_xlfn.XLOOKUP(_xlfn.NUMBERVALUE(RIGHT(T$3,1)),$D$7:$H$7,$D24:$H24) -> 1.6885205 | U25: =U$20*_xlfn.XLOOKUP(_xlfn.NUMBERVALUE(RIGHT(U$3,1)),$D$7:$H$7,$D24:$H24) -> 1.7729465 | V25: =V$20*_xlfn.XLOOKUP(_xlfn.NUMBERVALUE(RIGHT(V$3,1)),$D$7:$H$7,$D24:$H24) -> 1.8615939 | W25: =W$20*_xlfn.XLOOKUP(_xlfn.NUMBERVALUE(RIGHT(W$3,1)),$D$7:$H$7,$D24:$H24) -> 1.9546736 | X25: =X$20*_xlfn.XLOOKUP(_xlfn.NUMBERVALUE(RIGHT(X$3,1)),$D$7:$H$7,$D24:$H24) -> 2.0524072 | Y25: =Y$20*_xlfn.XLOOKUP(_xlfn.NUMBERVALUE(RIGHT(Y$3,1)),$D$7:$H$7,$D24:$H24) -> 4.1103394 | Z25: =Z$20*_xlfn.XLOOKUP(_xlfn.NUMBERVALUE(RIGHT(Z$3,1)),$D$7:$H$7,$D24:$H24) -> 4.3158563 | ... BT25: =BT$20*_xlfn.XLOOKUP(_xlfn.NUMBERVALUE(RIGHT(BT$3,1)),$D$7:$H$7,$D24:$H24) -> 14.307774
C26: Large Cap | F26: 0.1 | G26: 0.2 | H26: 0.25 | L26: Mid Cap | M26: =M$20*_xlfn.XLOOKUP(_xlfn.NUMBERVALUE(RIGHT(M$3,1)),$D$7:$H$7,$D25:$H25) -> 0 | N26: =N$20*_xlfn.XLOOKUP(_xlfn.NUMBERVALUE(RIGHT(N$3,1)),$D$7:$H$7,$D25:$H25) -> 0 | O26: =O$20*_xlfn.XLOOKUP(_xlfn.NUMBERVALUE(RIGHT(O$3,1)),$D$7:$H$7,$D25:$H25) -> 0 | P26: =P$20*_xlfn.XLOOKUP(_xlfn.NUMBERVALUE(RIGHT(P$3,1)),$D$7:$H$7,$D25:$H25) -> 0 | Q26: =Q$20*_xlfn.XLOOKUP(_xlfn.NUMBERVALUE(RIGHT(Q$3,1)),$D$7:$H$7,$D25:$H25) -> 0 | R26: =R$20*_xlfn.XLOOKUP(_xlfn.NUMBERVALUE(RIGHT(R$3,1)),$D$7:$H$7,$D25:$H25) -> 0 | S26: =S$20*_xlfn.XLOOKUP(_xlfn.NUMBERVALUE(RIGHT(S$3,1)),$D$7:$H$7,$D25:$H25) -> 0 | T26: =T$20*_xlfn.XLOOKUP(_xlfn.NUMBERVALUE(RIGHT(T$3,1)),$D$7:$H$7,$D25:$H25) -> 0 | ... BT26: =BT$20*_xlfn.XLOOKUP(_xlfn.NUMBERVALUE(RIGHT(BT$3,1)),$D$7:$H$7,$D25:$H25) -> 57.231096
L27: Large Cap | M27: =M$20*_xlfn.XLOOKUP(_xlfn.NUMBERVALUE(RIGHT(M$3,1)),$D$7:$H$7,$D26:$H26) -> 0 | N27: =N$20*_xlfn.XLOOKUP(_xlfn.NUMBERVALUE(RIGHT(N$3,1)),$D$7:$H$7,$D26:$H26) -> 0 | O27: =O$20*_xlfn.XLOOKUP(_xlfn.NUMBERVALUE(RIGHT(O$3,1)),$D$7:$H$7,$D26:$H26) -> 0 | P27: =P$20*_xlfn.XLOOKUP(_xlfn.NUMBERVALUE(RIGHT(P$3,1)),$D$7:$H$7,$D26:$H26) -> 0 | Q27: =Q$20*_xlfn.XLOOKUP(_xlfn.NUMBERVALUE(RIGHT(Q$3,1)),$D$7:$H$7,$D26:$H26) -> 0 | R27: =R$20*_xlfn.XLOOKUP(_xlfn.NUMBERVALUE(RIGHT(R$3,1)),$D$7:$H$7,$D26:$H26) -> 0 | S27: =S$20*_xlfn.XLOOKUP(_xlfn.NUMBERVALUE(RIGHT(S$3,1)),$D$7:$H$7,$D26:$H26) -> 0 | T27: =T$20*_xlfn.XLOOKUP(_xlfn.NUMBERVALUE(RIGHT(T$3,1)),$D$7:$H$7,$D26:$H26) -> 0 | ... BT27: =BT$20*_xlfn.XLOOKUP(_xlfn.NUMBERVALUE(RIGHT(BT$3,1)),$D$7:$H$7,$D26:$H26) -> 71.53887
J29: Total Customers w/o Attrition
K30: Basic | L30: Small Cap | M30: =M12 -> 0 | N30: =M30+N12 -> 0 | O30: =N30+O12 -> 0 | P30: =O30+P12 -> 0 | Q30: =P30+Q12 -> 0 | R30: =Q30+R12 -> 0 | S30: =R30+S12 -> 4 | T30: =S30+T12 -> 8 | U30: =T30+U12 -> 12 | ... BT30: =BS30+BT12 -> 399
B31: Cash Collections | C31: Month 1 | D31: 0.95 | L31: Mid Cap | M31: =M13 -> 0 | N31: =M31+N13 -> 0 | O31: =N31+O13 -> 0 | P31: =O31+P13 -> 0 | Q31: =P31+Q13 -> 0 | R31: =Q31+R13 -> 0 | S31: =R31+S13 -> 0 | T31: =S31+T13 -> 0 | U31: =T31+U13 -> 0 | ... BT31: =BS31+BT13 -> 1089
C32: Month 2 | D32: 0.04 | L32: Large Cap | M32: =M14 -> 0 | N32: =M32+N14 -> 0 | O32: =N32+O14 -> 0 | P32: =O32+P14 -> 0 | Q32: =P32+Q14 -> 0 | R32: =Q32+R14 -> 0 | S32: =R32+S14 -> 0 | T32: =S32+T14 -> 0 | U32: =T32+U14 -> 0 | ... BT32: =BS32+BT14 -> 1128
C33: Month 3 | D33: 0.01
K34: Premium | L34: Small Cap | M34: =M16 -> 0 | N34: =M34+N16 -> 0 | O34: =N34+O16 -> 0 | P34: =O34+P16 -> 0 | Q34: =P34+Q16 -> 0 | R34: =Q34+R16 -> 0 | S34: =R34+S16 -> 2 | T34: =S34+T16 -> 4 | U34: =T34+U16 -> 6 | ... BT34: =BS34+BT16 -> 369
D35: Year | L35: Mid Cap | M35: =M17 -> 0 | N35: =M35+N17 -> 0 | O35: =N35+O17 -> 0 | P35: =O35+P17 -> 0 | Q35: =P35+Q17 -> 0 | R35: =Q35+R17 -> 0 | S35: =R35+S17 -> 0 | T35: =S35+T17 -> 0 | U35: =T35+U17 -> 0 | ... BT35: =BS35+BT17 -> 931
B36: Users | C36: Percentage | D36: 0-1 | E36: 1-2 | F36: 2-3 | G36: 3-4 | H36: 4-5 | L36: Large Cap | M36: =M18 -> 0 | N36: =M36+N18 -> 0 | O36: =N36+O18 -> 0 | P36: =O36+P18 -> 0 | Q36: =P36+Q18 -> 0 | R36: =Q36+R18 -> 0 | S36: =R36+S18 -> 0 | T36: =S36+T18 -> 0 | U36: =T36+U18 -> 0 | ... BT36: =BS36+BT18 -> 995
B37: Abandon Rate | D37: 0.01 | E37: 0.15 | F37: 0.15 | G37: 0.15 | H37: 0.15
B38: Attrition rate | D38: 0.1 | E38: 0.2 | F38: 0.2 | G38: 0.2 | H38: 0.2
J39: Attrition Units
B40: Starting Customers | K40: Basic | L40: Small Cap | N40: =(M30*(_xlfn.XLOOKUP(_xlfn.NUMBERVALUE(RIGHT(N$3,1)),$D$7:$H$7,$D$38:$H$38))) -> 0 | O40: =(N30*(_xlfn.XLOOKUP(_xlfn.NUMBERVALUE(RIGHT(O$3,1)),$D$7:$H$7,$D$38:$H$38))) -> 0 | P40: =(O30*(_xlfn.XLOOKUP(_xlfn.NUMBERVALUE(RIGHT(P$3,1)),$D$7:$H$7,$D$38:$H$38))) -> 0 | Q40: =(P30*(_xlfn.XLOOKUP(_xlfn.NUMBERVALUE(RIGHT(Q$3,1)),$D$7:$H$7,$D$38:$H$38))) -> 0 | R40: =(Q30*(_xlfn.XLOOKUP(_xlfn.NUMBERVALUE(RIGHT(R$3,1)),$D$7:$H$7,$D$38:$H$38))) -> 0 | S40: =(R30*(_xlfn.XLOOKUP(_xlfn.NUMBERVALUE(RIGHT(S$3,1)),$D$7:$H$7,$D$38:$H$38))) -> 0 | T40: =(S30*(_xlfn.XLOOKUP(_xlfn.NUMBERVALUE(RIGHT(T$3,1)),$D$7:$H$7,$D$38:$H$38))) -> 0.4 | U40: =(T30*(_xlfn.XLOOKUP(_xlfn.NUMBERVALUE(RIGHT(U$3,1)),$D$7:$H$7,$D$38:$H$38))) -> 0.8 | ... BT40: =(BS30*(_xlfn.XLOOKUP(_xlfn.NUMBERVALUE(RIGHT(BT$3,1)),$D$7:$H$7,$D$38:$H$38))) -> 78
B41: Basic | C41: Small Cap | D41: 10 | L41: Mid Cap | N41: =(M31*(_xlfn.XLOOKUP(_xlfn.NUMBERVALUE(RIGHT(N$3,1)),$D$7:$H$7,$D$38:$H$38))) -> 0 | O41: =(N31*(_xlfn.XLOOKUP(_xlfn.NUMBERVALUE(RIGHT(O$3,1)),$D$7:$H$7,$D$38:$H$38))) -> 0 | P41: =(O31*(_xlfn.XLOOKUP(_xlfn.NUMBERVALUE(RIGHT(P$3,1)),$D$7:$H$7,$D$38:$H$38))) -> 0 | Q41: =(P31*(_xlfn.XLOOKUP(_xlfn.NUMBERVALUE(RIGHT(Q$3,1)),$D$7:$H$7,$D$38:$H$38))) -> 0 | R41: =(Q31*(_xlfn.XLOOKUP(_xlfn.NUMBERVALUE(RIGHT(R$3,1)),$D$7:$H$7,$D$38:$H$38))) -> 0 | S41: =(R31*(_xlfn.XLOOKUP(_xlfn.NUMBERVALUE(RIGHT(S$3,1)),$D$7:$H$7,$D$38:$H$38))) -> 0 | T41: =(S31*(_xlfn.XLOOKUP(_xlfn.NUMBERVALUE(RIGHT(T$3,1)),$D$7:$H$7,$D$38:$H$38))) -> 0 | U41: =(T31*(_xlfn.XLOOKUP(_xlfn.NUMBERVALUE(RIGHT(U$3,1)),$D$7:$H$7,$D$38:$H$38))) -> 0 | ... BT41: =(BS31*(_xlfn.XLOOKUP(_xlfn.NUMBERVALUE(RIGHT(BT$3,1)),$D$7:$H$7,$D$38:$H$38))) -> 208
C42: Mid Cap | D42: 10 | L42: Large Cap | N42: =(M32*(_xlfn.XLOOKUP(_xlfn.NUMBERVALUE(RIGHT(N$3,1)),$D$7:$H$7,$D$38:$H$38))) -> 0 | O42: =(N32*(_xlfn.XLOOKUP(_xlfn.NUMBERVALUE(RIGHT(O$3,1)),$D$7:$H$7,$D$38:$H$38))) -> 0 | P42: =(O32*(_xlfn.XLOOKUP(_xlfn.NUMBERVALUE(RIGHT(P$3,1)),$D$7:$H$7,$D$38:$H$38))) -> 0 | Q42: =(P32*(_xlfn.XLOOKUP(_xlfn.NUMBERVALUE(RIGHT(Q$3,1)),$D$7:$H$7,$D$38:$H$38))) -> 0 | R42: =(Q32*(_xlfn.XLOOKUP(_xlfn.NUMBERVALUE(RIGHT(R$3,1)),$D$7:$H$7,$D$38:$H$38))) -> 0 | S42: =(R32*(_xlfn.XLOOKUP(_xlfn.NUMBERVALUE(RIGHT(S$3,1)),$D$7:$H$7,$D$38:$H$38))) -> 0 | T42: =(S32*(_xlfn.XLOOKUP(_xlfn.NUMBERVALUE(RIGHT(T$3,1)),$D$7:$H$7,$D$38:$H$38))) -> 0 | U42: =(T32*(_xlfn.XLOOKUP(_xlfn.NUMBERVALUE(RIGHT(U$3,1)),$D$7:$H$7,$D$38:$H$38))) -> 0 | ... BT42: =(BS32*(_xlfn.XLOOKUP(_xlfn.NUMBERVALUE(RIGHT(BT$3,1)),$D$7:$H$7,$D$38:$H$38))) -> 208.4
C43: Large Cap | D43: 5
B44: Premium | K44: Premium | L44: Small Cap | N44: =(M34*(_xlfn.XLOOKUP(_xlfn.NUMBERVALUE(RIGHT(N$3,1)),$D$7:$H$7,$D$38:$H$38))) -> 0 | O44: =(N34*(_xlfn.XLOOKUP(_xlfn.NUMBERVALUE(RIGHT(O$3,1)),$D$7:$H$7,$D$38:$H$38))) -> 0 | P44: =(O34*(_xlfn.XLOOKUP(_xlfn.NUMBERVALUE(RIGHT(P$3,1)),$D$7:$H$7,$D$38:$H$38))) -> 0 | Q44: =(P34*(_xlfn.XLOOKUP(_xlfn.NUMBERVALUE(RIGHT(Q$3,1)),$D$7:$H$7,$D$38:$H$38))) -> 0 | R44: =(Q34*(_xlfn.XLOOKUP(_xlfn.NUMBERVALUE(RIGHT(R$3,1)),$D$7:$H$7,$D$38:$H$38))) -> 0 | S44: =(R34*(_xlfn.XLOOKUP(_xlfn.NUMBERVALUE(RIGHT(S$3,1)),$D$7:$H$7,$D$38:$H$38))) -> 0 | T44: =(S34*(_xlfn.XLOOKUP(_xlfn.NUMBERVALUE(RIGHT(T$3,1)),$D$7:$H$7,$D$38:$H$38))) -> 0.2 | U44: =(T34*(_xlfn.XLOOKUP(_xlfn.NUMBERVALUE(RIGHT(U$3,1)),$D$7:$H$7,$D$38:$H$38))) -> 0.4 | ... BT44: =(BS34*(_xlfn.XLOOKUP(_xlfn.NUMBERVALUE(RIGHT(BT$3,1)),$D$7:$H$7,$D$38:$H$38))) -> 71
C45: Small Cap | D45: 10 | L45: Mid Cap | N45: =(M35*(_xlfn.XLOOKUP(_xlfn.NUMBERVALUE(RIGHT(N$3,1)),$D$7:$H$7,$D$38:$H$38))) -> 0 | O45: =(N35*(_xlfn.XLOOKUP(_xlfn.NUMBERVALUE(RIGHT(O$3,1)),$D$7:$H$7,$D$38:$H$38))) -> 0 | P45: =(O35*(_xlfn.XLOOKUP(_xlfn.NUMBERVALUE(RIGHT(P$3,1)),$D$7:$H$7,$D$38:$H$38))) -> 0 | Q45: =(P35*(_xlfn.XLOOKUP(_xlfn.NUMBERVALUE(RIGHT(Q$3,1)),$D$7:$H$7,$D$38:$H$38))) -> 0 | R45: =(Q35*(_xlfn.XLOOKUP(_xlfn.NUMBERVALUE(RIGHT(R$3,1)),$D$7:$H$7,$D$38:$H$38))) -> 0 | S45: =(R35*(_xlfn.XLOOKUP(_xlfn.NUMBERVALUE(RIGHT(S$3,1)),$D$7:$H$7,$D$38:$H$38))) -> 0 | T45: =(S35*(_xlfn.XLOOKUP(_xlfn.NUMBERVALUE(RIGHT(T$3,1)),$D$7:$H$7,$D$38:$H$38))) -> 0 | U45: =(T35*(_xlfn.XLOOKUP(_xlfn.NUMBERVALUE(RIGHT(U$3,1)),$D$7:$H$7,$D$38:$H$38))) -> 0 | ... BT45: =(BS35*(_xlfn.XLOOKUP(_xlfn.NUMBERVALUE(RIGHT(BT$3,1)),$D$7:$H$7,$D$38:$H$38))) -> 174.8
C46: Mid Cap | D46: 10 | L46: Large Cap | N46: =(M36*(_xlfn.XLOOKUP(_xlfn.NUMBERVALUE(RIGHT(N$3,1)),$D$7:$H$7,$D$38:$H$38))) -> 0 | O46: =(N36*(_xlfn.XLOOKUP(_xlfn.NUMBERVALUE(RIGHT(O$3,1)),$D$7:$H$7,$D$38:$H$38))) -> 0 | P46: =(O36*(_xlfn.XLOOKUP(_xlfn.NUMBERVALUE(RIGHT(P$3,1)),$D$7:$H$7,$D$38:$H$38))) -> 0 | Q46: =(P36*(_xlfn.XLOOKUP(_xlfn.NUMBERVALUE(RIGHT(Q$3,1)),$D$7:$H$7,$D$38:$H$38))) -> 0 | R46: =(Q36*(_xlfn.XLOOKUP(_xlfn.NUMBERVALUE(RIGHT(R$3,1)),$D$7:$H$7,$D$38:$H$38))) -> 0 | S46: =(R36*(_xlfn.XLOOKUP(_xlfn.NUMBERVALUE(RIGHT(S$3,1)),$D$7:$H$7,$D$38:$H$38))) -> 0 | T46: =(S36*(_xlfn.XLOOKUP(_xlfn.NUMBERVALUE(RIGHT(T$3,1)),$D$7:$H$7,$D$38:$H$38))) -> 0 | U46: =(T36*(_xlfn.XLOOKUP(_xlfn.NUMBERVALUE(RIGHT(U$3,1)),$D$7:$H$7,$D$38:$H$38))) -> 0 | ... BT46: =(BS36*(_xlfn.XLOOKUP(_xlfn.NUMBERVALUE(RIGHT(BT$3,1)),$D$7:$H$7,$D$38:$H$38))) -> 184.6
C47: Large Cap | D47: 5 | J47: Abandon Units
K48: Basic | L48: Small Cap | N48: =(M30*(_xlfn.XLOOKUP(_xlfn.NUMBERVALUE(RIGHT(N$3,1)),$D$7:$H$7,$D$37:$H$37))) -> 0 | O48: =(N30*(_xlfn.XLOOKUP(_xlfn.NUMBERVALUE(RIGHT(O$3,1)),$D$7:$H$7,$D$37:$H$37))) -> 0 | P48: =(O30*(_xlfn.XLOOKUP(_xlfn.NUMBERVALUE(RIGHT(P$3,1)),$D$7:$H$7,$D$37:$H$37))) -> 0 | Q48: =(P30*(_xlfn.XLOOKUP(_xlfn.NUMBERVALUE(RIGHT(Q$3,1)),$D$7:$H$7,$D$37:$H$37))) -> 0 | R48: =(Q30*(_xlfn.XLOOKUP(_xlfn.NUMBERVALUE(RIGHT(R$3,1)),$D$7:$H$7,$D$37:$H$37))) -> 0 | S48: =(R30*(_xlfn.XLOOKUP(_xlfn.NUMBERVALUE(RIGHT(S$3,1)),$D$7:$H$7,$D$37:$H$37))) -> 0 | T48: =(S30*(_xlfn.XLOOKUP(_xlfn.NUMBERVALUE(RIGHT(T$3,1)),$D$7:$H$7,$D$37:$H$37))) -> 0.04 | U48: =(T30*(_xlfn.XLOOKUP(_xlfn.NUMBERVALUE(RIGHT(U$3,1)),$D$7:$H$7,$D$37:$H$37))) -> 0.08 | ... BT48: =(BS30*(_xlfn.XLOOKUP(_xlfn.NUMBERVALUE(RIGHT(BT$3,1)),$D$7:$H$7,$D$37:$H$37))) -> 58.5
L49: Mid Cap | N49: =(M31*(_xlfn.XLOOKUP(_xlfn.NUMBERVALUE(RIGHT(N$3,1)),$D$7:$H$7,$D$37:$H$37))) -> 0 | O49: =(N31*(_xlfn.XLOOKUP(_xlfn.NUMBERVALUE(RIGHT(O$3,1)),$D$7:$H$7,$D$37:$H$37))) -> 0 | P49: =(O31*(_xlfn.XLOOKUP(_xlfn.NUMBERVALUE(RIGHT(P$3,1)),$D$7:$H$7,$D$37:$H$37))) -> 0 | Q49: =(P31*(_xlfn.XLOOKUP(_xlfn.NUMBERVALUE(RIGHT(Q$3,1)),$D$7:$H$7,$D$37:$H$37))) -> 0 | R49: =(Q31*(_xlfn.XLOOKUP(_xlfn.NUMBERVALUE(RIGHT(R$3,1)),$D$7:$H$7,$D$37:$H$37))) -> 0 | S49: =(R31*(_xlfn.XLOOKUP(_xlfn.NUMBERVALUE(RIGHT(S$3,1)),$D$7:$H$7,$D$37:$H$37))) -> 0 | T49: =(S31*(_xlfn.XLOOKUP(_xlfn.NUMBERVALUE(RIGHT(T$3,1)),$D$7:$H$7,$D$37:$H$37))) -> 0 | U49: =(T31*(_xlfn.XLOOKUP(_xlfn.NUMBERVALUE(RIGHT(U$3,1)),$D$7:$H$7,$D$37:$H$37))) -> 0 | ... BT49: =(BS31*(_xlfn.XLOOKUP(_xlfn.NUMBERVALUE(RIGHT(BT$3,1)),$D$7:$H$7,$D$37:$H$37))) -> 156
L50: Large Cap | N50: =(M32*(_xlfn.XLOOKUP(_xlfn.NUMBERVALUE(RIGHT(N$3,1)),$D$7:$H$7,$D$37:$H$37))) -> 0 | O50: =(N32*(_xlfn.XLOOKUP(_xlfn.NUMBERVALUE(RIGHT(O$3,1)),$D$7:$H$7,$D$37:$H$37))) -> 0 | P50: =(O32*(_xlfn.XLOOKUP(_xlfn.NUMBERVALUE(RIGHT(P$3,1)),$D$7:$H$7,$D$37:$H$37))) -> 0 | Q50: =(P32*(_xlfn.XLOOKUP(_xlfn.NUMBERVALUE(RIGHT(Q$3,1)),$D$7:$H$7,$D$37:$H$37))) -> 0 | R50: =(Q32*(_xlfn.XLOOKUP(_xlfn.NUMBERVALUE(RIGHT(R$3,1)),$D$7:$H$7,$D$37:$H$37))) -> 0 | S50: =(R32*(_xlfn.XLOOKUP(_xlfn.NUMBERVALUE(RIGHT(S$3,1)),$D$7:$H$7,$D$37:$H$37))) -> 0 | T50: =(S32*(_xlfn.XLOOKUP(_xlfn.NUMBERVALUE(RIGHT(T$3,1)),$D$7:$H$7,$D$37:$H$37))) -> 0 | U50: =(T32*(_xlfn.XLOOKUP(_xlfn.NUMBERVALUE(RIGHT(U$3,1)),$D$7:$H$7,$D$37:$H$37))) -> 0 | ... BT50: =(BS32*(_xlfn.XLOOKUP(_xlfn.NUMBERVALUE(RIGHT(BT$3,1)),$D$7:$H$7,$D$37:$H$37))) -> 156.3
K52: Premium | L52: Small Cap | N52: =(M34*(_xlfn.XLOOKUP(_xlfn.NUMBERVALUE(RIGHT(N$3,1)),$D$7:$H$7,$D$37:$H$37))) -> 0 | O52: =(N34*(_xlfn.XLOOKUP(_xlfn.NUMBERVALUE(RIGHT(O$3,1)),$D$7:$H$7,$D$37:$H$37))) -> 0 | P52: =(O34*(_xlfn.XLOOKUP(_xlfn.NUMBERVALUE(RIGHT(P$3,1)),$D$7:$H$7,$D$37:$H$37))) -> 0 | Q52: =(P34*(_xlfn.XLOOKUP(_xlfn.NUMBERVALUE(RIGHT(Q$3,1)),$D$7:$H$7,$D$37:$H$37))) -> 0 | R52: =(Q34*(_xlfn.XLOOKUP(_xlfn.NUMBERVALUE(RIGHT(R$3,1)),$D$7:$H$7,$D$37:$H$37))) -> 0 | S52: =(R34*(_xlfn.XLOOKUP(_xlfn.NUMBERVALUE(RIGHT(S$3,1)),$D$7:$H$7,$D$37:$H$37))) -> 0 | T52: =(S34*(_xlfn.XLOOKUP(_xlfn.NUMBERVALUE(RIGHT(T$3,1)),$D$7:$H$7,$D$37:$H$37))) -> 0.02 | U52: =(T34*(_xlfn.XLOOKUP(_xlfn.NUMBERVALUE(RIGHT(U$3,1)),$D$7:$H$7,$D$37:$H$37))) -> 0.04 | ... BT52: =(BS34*(_xlfn.XLOOKUP(_xlfn.NUMBERVALUE(RIGHT(BT$3,1)),$D$7:$H$7,$D$37:$H$37))) -> 53.25
L53: Mid Cap | N53: =(M35*(_xlfn.XLOOKUP(_xlfn.NUMBERVALUE(RIGHT(N$3,1)),$D$7:$H$7,$D$37:$H$37))) -> 0 | O53: =(N35*(_xlfn.XLOOKUP(_xlfn.NUMBERVALUE(RIGHT(O$3,1)),$D$7:$H$7,$D$37:$H$37))) -> 0 | P53: =(O35*(_xlfn.XLOOKUP(_xlfn.NUMBERVALUE(RIGHT(P$3,1)),$D$7:$H$7,$D$37:$H$37))) -> 0 | Q53: =(P35*(_xlfn.XLOOKUP(_xlfn.NUMBERVALUE(RIGHT(Q$3,1)),$D$7:$H$7,$D$37:$H$37))) -> 0 | R53: =(Q35*(_xlfn.XLOOKUP(_xlfn.NUMBERVALUE(RIGHT(R$3,1)),$D$7:$H$7,$D$37:$H$37))) -> 0 | S53: =(R35*(_xlfn.XLOOKUP(_xlfn.NUMBERVALUE(RIGHT(S$3,1)),$D$7:$H$7,$D$37:$H$37))) -> 0 | T53: =(S35*(_xlfn.XLOOKUP(_xlfn.NUMBERVALUE(RIGHT(T$3,1)),$D$7:$H$7,$D$37:$H$37))) -> 0 | U53: =(T35*(_xlfn.XLOOKUP(_xlfn.NUMBERVALUE(RIGHT(U$3,1)),$D$7:$H$7,$D$37:$H$37))) -> 0 | ... BT53: =(BS35*(_xlfn.XLOOKUP(_xlfn.NUMBERVALUE(RIGHT(BT$3,1)),$D$7:$H$7,$D$37:$H$37))) -> 131.1
L54: Large Cap | N54: =(M36*(_xlfn.XLOOKUP(_xlfn.NUMBERVALUE(RIGHT(N$3,1)),$D$7:$H$7,$D$37:$H$37))) -> 0 | O54: =(N36*(_xlfn.XLOOKUP(_xlfn.NUMBERVALUE(RIGHT(O$3,1)),$D$7:$H$7,$D$37:$H$37))) -> 0 | P54: =(O36*(_xlfn.XLOOKUP(_xlfn.NUMBERVALUE(RIGHT(P$3,1)),$D$7:$H$7,$D$37:$H$37))) -> 0 | Q54: =(P36*(_xlfn.XLOOKUP(_xlfn.NUMBERVALUE(RIGHT(Q$3,1)),$D$7:$H$7,$D$37:$H$37))) -> 0 | R54: =(Q36*(_xlfn.XLOOKUP(_xlfn.NUMBERVALUE(RIGHT(R$3,1)),$D$7:$H$7,$D$37:$H$37))) -> 0 | S54: =(R36*(_xlfn.XLOOKUP(_xlfn.NUMBERVALUE(RIGHT(S$3,1)),$D$7:$H$7,$D$37:$H$37))) -> 0 | T54: =(S36*(_xlfn.XLOOKUP(_xlfn.NUMBERVALUE(RIGHT(T$3,1)),$D$7:$H$7,$D$37:$H$37))) -> 0 | U54: =(T36*(_xlfn.XLOOKUP(_xlfn.NUMBERVALUE(RIGHT(U$3,1)),$D$7:$H$7,$D$37:$H$37))) -> 0 | ... BT54: =(BS36*(_xlfn.XLOOKUP(_xlfn.NUMBERVALUE(RIGHT(BT$3,1)),$D$7:$H$7,$D$37:$H$37))) -> 138.45
J56: Units (Concurrent)
K57: Basic | M57: =ROUND(SUM(M30,-M40,-M48),0) -> 0 | N57: =ROUND(SUM(N30,-N40,-N48),0) -> 0 | O57: =ROUND(SUM(O30,-O40,-O48),0) -> 0 | P57: =ROUND(SUM(P30,-P40,-P48),0) -> 0 | Q57: =ROUND(SUM(Q30,-Q40,-Q48),0) -> 0 | R57: =ROUND(SUM(R30,-R40,-R48),0) -> 0 | S57: =ROUND(SUM(S30,-S40,-S48),0) -> 4 | T57: =ROUND(SUM(T30,-T40,-T48),0) -> 8 | ... BT57: =ROUND(SUM(BT30,-BT40,-BT48),0) -> 263
M58: =ROUND(SUM(M31,-M41,-M49),0) -> 0 | N58: =ROUND(SUM(N31,-N41,-N49),0) -> 0 | O58: =ROUND(SUM(O31,-O41,-O49),0) -> 0 | P58: =ROUND(SUM(P31,-P41,-P49),0) -> 0 | Q58: =ROUND(SUM(Q31,-Q41,-Q49),0) -> 0 | R58: =ROUND(SUM(R31,-R41,-R49),0) -> 0 | S58: =ROUND(SUM(S31,-S41,-S49),0) -> 0 | T58: =ROUND(SUM(T31,-T41,-T49),0) -> 0 | ... BT58: =ROUND(SUM(BT31,-BT41,-BT49),0) -> 725
M59: =ROUND(SUM(M32,-M42,-M50),0) -> 0 | N59: =ROUND(SUM(N32,-N42,-N50),0) -> 0 | O59: =ROUND(SUM(O32,-O42,-O50),0) -> 0 | P59: =ROUND(SUM(P32,-P42,-P50),0) -> 0 | Q59: =ROUND(SUM(Q32,-Q42,-Q50),0) -> 0 | R59: =ROUND(SUM(R32,-R42,-R50),0) -> 0 | S59: =ROUND(SUM(S32,-S42,-S50),0) -> 0 | T59: =ROUND(SUM(T32,-T42,-T50),0) -> 0 | ... BT59: =ROUND(SUM(BT32,-BT42,-BT50),0) -> 763
K61: Premium | M61: =ROUND(SUM(M34,-M44,-M52),0) -> 0 | N61: =ROUND(SUM(N34,-N44,-N52),0) -> 0 | O61: =ROUND(SUM(O34,-O44,-O52),0) -> 0 | P61: =ROUND(SUM(P34,-P44,-P52),0) -> 0 | Q61: =ROUND(SUM(Q34,-Q44,-Q52),0) -> 0 | R61: =ROUND(SUM(R34,-R44,-R52),0) -> 0 | S61: =ROUND(SUM(S34,-S44,-S52),0) -> 2 | T61: =ROUND(SUM(T34,-T44,-T52),0) -> 4 | ... BT61: =ROUND(SUM(BT34,-BT44,-BT52),0) -> 245
M62: =ROUND(SUM(M35,-M45,-M53),0) -> 0 | N62: =ROUND(SUM(N35,-N45,-N53),0) -> 0 | O62: =ROUND(SUM(O35,-O45,-O53),0) -> 0 | P62: =ROUND(SUM(P35,-P45,-P53),0) -> 0 | Q62: =ROUND(SUM(Q35,-Q45,-Q53),0) -> 0 | R62: =ROUND(SUM(R35,-R45,-R53),0) -> 0 | S62: =ROUND(SUM(S35,-S45,-S53),0) -> 0 | T62: =ROUND(SUM(T35,-T45,-T53),0) -> 0 | ... BT62: =ROUND(SUM(BT35,-BT45,-BT53),0) -> 625
M63: =ROUND(SUM(M36,-M46,-M54),0) -> 0 | N63: =ROUND(SUM(N36,-N46,-N54),0) -> 0 | O63: =ROUND(SUM(O36,-O46,-O54),0) -> 0 | P63: =ROUND(SUM(P36,-P46,-P54),0) -> 0 | Q63: =ROUND(SUM(Q36,-Q46,-Q54),0) -> 0 | R63: =ROUND(SUM(R36,-R46,-R54),0) -> 0 | S63: =ROUND(SUM(S36,-S46,-S54),0) -> 0 | T63: =ROUND(SUM(T36,-T46,-T54),0) -> 0 | ... BT63: =ROUND(SUM(BT36,-BT46,-BT54),0) -> 672
J64: Revenue
K65: Basic | M65: =M57*_xlfn.XLOOKUP(_xlfn.NUMBERVALUE(RIGHT(M$3,1)),$D$7:$H$7,$D11:$H11) -> 0 | N65: =N57*_xlfn.XLOOKUP(_xlfn.NUMBERVALUE(RIGHT(N$3,1)),$D$7:$H$7,$D11:$H11) -> 0 | O65: =O57*_xlfn.XLOOKUP(_xlfn.NUMBERVALUE(RIGHT(O$3,1)),$D$7:$H$7,$D11:$H11) -> 0 | P65: =P57*_xlfn.XLOOKUP(_xlfn.NUMBERVALUE(RIGHT(P$3,1)),$D$7:$H$7,$D11:$H11) -> 0 | Q65: =Q57*_xlfn.XLOOKUP(_xlfn.NUMBERVALUE(RIGHT(Q$3,1)),$D$7:$H$7,$D11:$H11) -> 0 | R65: =R57*_xlfn.XLOOKUP(_xlfn.NUMBERVALUE(RIGHT(R$3,1)),$D$7:$H$7,$D11:$H11) -> 0 | S65: =S57*_xlfn.XLOOKUP(_xlfn.NUMBERVALUE(RIGHT(S$3,1)),$D$7:$H$7,$D11:$H11) -> 400 | T65: =T57*_xlfn.XLOOKUP(_xlfn.NUMBERVALUE(RIGHT(T$3,1)),$D$7:$H$7,$D11:$H11) -> 800 | ... BT65: =BT57*_xlfn.XLOOKUP(_xlfn.NUMBERVALUE(RIGHT(BT$3,1)),$D$7:$H$7,$D11:$H11) -> 47340
M66: =M58*_xlfn.XLOOKUP(_xlfn.NUMBERVALUE(RIGHT(M$3,1)),$D$7:$H$7,$D12:$H12) -> 0 | N66: =N58*_xlfn.XLOOKUP(_xlfn.NUMBERVALUE(RIGHT(N$3,1)),$D$7:$H$7,$D12:$H12) -> 0 | O66: =O58*_xlfn.XLOOKUP(_xlfn.NUMBERVALUE(RIGHT(O$3,1)),$D$7:$H$7,$D12:$H12) -> 0 | P66: =P58*_xlfn.XLOOKUP(_xlfn.NUMBERVALUE(RIGHT(P$3,1)),$D$7:$H$7,$D12:$H12) -> 0 | Q66: =Q58*_xlfn.XLOOKUP(_xlfn.NUMBERVALUE(RIGHT(Q$3,1)),$D$7:$H$7,$D12:$H12) -> 0 | R66: =R58*_xlfn.XLOOKUP(_xlfn.NUMBERVALUE(RIGHT(R$3,1)),$D$7:$H$7,$D12:$H12) -> 0 | S66: =S58*_xlfn.XLOOKUP(_xlfn.NUMBERVALUE(RIGHT(S$3,1)),$D$7:$H$7,$D12:$H12) -> 0 | T66: =T58*_xlfn.XLOOKUP(_xlfn.NUMBERVALUE(RIGHT(T$3,1)),$D$7:$H$7,$D12:$H12) -> 0 | ... BT66: =BT58*_xlfn.XLOOKUP(_xlfn.NUMBERVALUE(RIGHT(BT$3,1)),$D$7:$H$7,$D12:$H12) -> 232000
M67: =M59*_xlfn.XLOOKUP(_xlfn.NUMBERVALUE(RIGHT(M$3,1)),$D$7:$H$7,$D13:$H13) -> 0 | N67: =N59*_xlfn.XLOOKUP(_xlfn.NUMBERVALUE(RIGHT(N$3,1)),$D$7:$H$7,$D13:$H13) -> 0 | O67: =O59*_xlfn.XLOOKUP(_xlfn.NUMBERVALUE(RIGHT(O$3,1)),$D$7:$H$7,$D13:$H13) -> 0 | P67: =P59*_xlfn.XLOOKUP(_xlfn.NUMBERVALUE(RIGHT(P$3,1)),$D$7:$H$7,$D13:$H13) -> 0 | Q67: =Q59*_xlfn.XLOOKUP(_xlfn.NUMBERVALUE(RIGHT(Q$3,1)),$D$7:$H$7,$D13:$H13) -> 0 | R67: =R59*_xlfn.XLOOKUP(_xlfn.NUMBERVALUE(RIGHT(R$3,1)),$D$7:$H$7,$D13:$H13) -> 0 | S67: =S59*_xlfn.XLOOKUP(_xlfn.NUMBERVALUE(RIGHT(S$3,1)),$D$7:$H$7,$D13:$H13) -> 0 | T67: =T59*_xlfn.XLOOKUP(_xlfn.NUMBERVALUE(RIGHT(T$3,1)),$D$7:$H$7,$D13:$H13) -> 0 | ... BT67: =BT59*_xlfn.XLOOKUP(_xlfn.NUMBERVALUE(RIGHT(BT$3,1)),$D$7:$H$7,$D13:$H13) -> 534100
K69: Premium | M69: =M61*_xlfn.XLOOKUP(_xlfn.NUMBERVALUE(RIGHT(M$3,1)),$D$7:$H$7,$D15:$H15) -> 0 | N69: =N61*_xlfn.XLOOKUP(_xlfn.NUMBERVALUE(RIGHT(N$3,1)),$D$7:$H$7,$D15:$H15) -> 0 | O69: =O61*_xlfn.XLOOKUP(_xlfn.NUMBERVALUE(RIGHT(O$3,1)),$D$7:$H$7,$D15:$H15) -> 0 | P69: =P61*_xlfn.XLOOKUP(_xlfn.NUMBERVALUE(RIGHT(P$3,1)),$D$7:$H$7,$D15:$H15) -> 0 | Q69: =Q61*_xlfn.XLOOKUP(_xlfn.NUMBERVALUE(RIGHT(Q$3,1)),$D$7:$H$7,$D15:$H15) -> 0 | R69: =R61*_xlfn.XLOOKUP(_xlfn.NUMBERVALUE(RIGHT(R$3,1)),$D$7:$H$7,$D15:$H15) -> 0 | S69: =S61*_xlfn.XLOOKUP(_xlfn.NUMBERVALUE(RIGHT(S$3,1)),$D$7:$H$7,$D15:$H15) -> 500 | T69: =T61*_xlfn.XLOOKUP(_xlfn.NUMBERVALUE(RIGHT(T$3,1)),$D$7:$H$7,$D15:$H15) -> 1000 | ... BT69: =BT61*_xlfn.XLOOKUP(_xlfn.NUMBERVALUE(RIGHT(BT$3,1)),$D$7:$H$7,$D15:$H15) -> 110250
M70: =M62*_xlfn.XLOOKUP(_xlfn.NUMBERVALUE(RIGHT(M$3,1)),$D$7:$H$7,$D16:$H16) -> 0 | N70: =N62*_xlfn.XLOOKUP(_xlfn.NUMBERVALUE(RIGHT(N$3,1)),$D$7:$H$7,$D16:$H16) -> 0 | O70: =O62*_xlfn.XLOOKUP(_xlfn.NUMBERVALUE(RIGHT(O$3,1)),$D$7:$H$7,$D16:$H16) -> 0 | P70: =P62*_xlfn.XLOOKUP(_xlfn.NUMBERVALUE(RIGHT(P$3,1)),$D$7:$H$7,$D16:$H16) -> 0 | Q70: =Q62*_xlfn.XLOOKUP(_xlfn.NUMBERVALUE(RIGHT(Q$3,1)),$D$7:$H$7,$D16:$H16) -> 0 | R70: =R62*_xlfn.XLOOKUP(_xlfn.NUMBERVALUE(RIGHT(R$3,1)),$D$7:$H$7,$D16:$H16) -> 0 | S70: =S62*_xlfn.XLOOKUP(_xlfn.NUMBERVALUE(RIGHT(S$3,1)),$D$7:$H$7,$D16:$H16) -> 0 | T70: =T62*_xlfn.XLOOKUP(_xlfn.NUMBERVALUE(RIGHT(T$3,1)),$D$7:$H$7,$D16:$H16) -> 0 | ... BT70: =BT62*_xlfn.XLOOKUP(_xlfn.NUMBERVALUE(RIGHT(BT$3,1)),$D$7:$H$7,$D16:$H16) -> 468750
M71: =M63*_xlfn.XLOOKUP(_xlfn.NUMBERVALUE(RIGHT(M$3,1)),$D$7:$H$7,$D17:$H17) -> 0 | N71: =N63*_xlfn.XLOOKUP(_xlfn.NUMBERVALUE(RIGHT(N$3,1)),$D$7:$H$7,$D17:$H17) -> 0 | O71: =O63*_xlfn.XLOOKUP(_xlfn.NUMBERVALUE(RIGHT(O$3,1)),$D$7:$H$7,$D17:$H17) -> 0 | P71: =P63*_xlfn.XLOOKUP(_xlfn.NUMBERVALUE(RIGHT(P$3,1)),$D$7:$H$7,$D17:$H17) -> 0 | Q71: =Q63*_xlfn.XLOOKUP(_xlfn.NUMBERVALUE(RIGHT(Q$3,1)),$D$7:$H$7,$D17:$H17) -> 0 | R71: =R63*_xlfn.XLOOKUP(_xlfn.NUMBERVALUE(RIGHT(R$3,1)),$D$7:$H$7,$D17:$H17) -> 0 | S71: =S63*_xlfn.XLOOKUP(_xlfn.NUMBERVALUE(RIGHT(S$3,1)),$D$7:$H$7,$D17:$H17) -> 0 | T71: =T63*_xlfn.XLOOKUP(_xlfn.NUMBERVALUE(RIGHT(T$3,1)),$D$7:$H$7,$D17:$H17) -> 0 | ... BT71: =BT63*_xlfn.XLOOKUP(_xlfn.NUMBERVALUE(RIGHT(BT$3,1)),$D$7:$H$7,$D17:$H17) -> 940800
K72: One Time Fee
L73: All Caps | M73: {=M8:BT8} -> 0 | N73: 0 | O73: 0 | P73: 0 | Q73: 0 | R73: 0 | S73: 3000 | T73: 3000 | U73: 3000 | V73: 3000 | W73: 3500 | X73: 3500 | Y73: 40000 | Z73: 42500 | AA73: 47500 | AB73: 50000 | AC73: 50000 | AD73: 50000 | AE73: 55000 | AF73: 57500 | AG73: 62500 | AH73: 62500 | AI73: 67500 | AJ73: 70000 | AK73: 136500 | AL73: 140000 | AM73: 143500 | AN73: 154000 | AO73: 164500 | AP73: 171500 | AQ73: 178500 | AR73: 185500 | AS73: 196000 | AT73: 210000 | AU73: 213500 | AV73: 234500 | AW73: 336000 | AX73: 356000 | AY73: 380000 | AZ73: 384000 | BA73: 404000 | BB73: 420000 | BC73: 460000 | BD73: 480000 | BE73: 496000 | BF73: 524000 | BG73: 544000 | BH73: 576000 | BI73: 747000 | BJ73: 792000 | BK73: 828000 | BL73: 873000 | BM73: 918000 | BN73: 958500 | BO73: 1008000 | BP73: 1062000 | BQ73: 1107000 | BR73: 1170000 | BS73: 1228500 | BT73: 1291500
J77: Total Revenue | M77: =SUM(M65:M73) -> 0 | N77: =SUM(N65:N73) -> 0 | O77: =SUM(O65:O73) -> 0 | P77: =SUM(P65:P73) -> 0 | Q77: =SUM(Q65:Q73) -> 0 | R77: =SUM(R65:R73) -> 0 | S77: =SUM(S65:S73) -> 3900 | T77: =SUM(T65:T73) -> 4800 | ... BT77: =SUM(BT65:BT73) -> 3624740
J79: Cumulative Revenue | M79: =M77 -> 0 | N79: =M79+N77 -> 0 | O79: =N79+O77 -> 0 | P79: =O79+P77 -> 0 | Q79: =P79+Q77 -> 0 | R79: =Q79+R77 -> 0 | S79: =R79+S77 -> 3900 | T79: =S79+T77 -> 8700 | U79: =T79+U77 -> 14300 | ... BT79: =BS79+BT77 -> 48017850
J81: Cash Collections | M81: =M77*$D$31+L77*$D$32+K77*$D$33 -> 0 | N81: =N77*$D$31+M77*$D$32+L77*$D$33 -> 0 | O81: =O77*$D$31+N77*$D$32+M77*$D$33 -> 0 | P81: =P77*$D$31+O77*$D$32+N77*$D$33 -> 0 | Q81: =Q77*$D$31+P77*$D$32+O77*$D$33 -> 0 | R81: =R77*$D$31+Q77*$D$32+P77*$D$33 -> 0 | S81: =S77*$D$31+R77*$D$32+Q77*$D$33 -> 3705 | T81: =T77*$D$31+S77*$D$32+R77*$D$33 -> 4716 | ... BT81: =BT77*$D$31+BS77*$D$32+BR77*$D$33 -> 3611996.5
J83: Cumalative Cash Collections | M83: =M81 -> 0 | N83: =M83+N81 -> 0 | O83: =N83+O81 -> 0 | P83: =O83+P81 -> 0 | Q83: =P83+Q81 -> 0 | R83: =Q83+R81 -> 0 | S83: =R83+S81 -> 3705 | T83: =S83+T81 -> 8421 | U83: =T83+U81 -> 13972 | ... BT83: =BS83+BT81 -> 47802510
J85: Accounts Receivable | M85: =M79-M83 -> 0 | N85: =N79-N83 -> 0 | O85: =O79-O83 -> 0 | P85: =P79-P83 -> 0 | Q85: =Q79-Q83 -> 0 | R85: =R79-R83 -> 0 | S85: =S79-S83 -> 195 | T85: =T79-T83 -> 279 | ... BT85: =BT79-BT83 -> 215339.7
J87: Change in A/R | M87: =M85-L85 -> 0 | N87: =N85-M85 -> 0 | O87: =O85-N85 -> 0 | P87: =P85-O85 -> 0 | Q87: =Q85-P85 -> 0 | R87: =R85-Q85 -> 0 | S87: =S85-R85 -> 195 | T87: =T85-S85 -> 84 | ... BT87: =BT85-BS85 -> 12743.5
K97: Total user/units | M97: =SUM(M57:M63) -> 0 | N97: =SUM(N57:N63) -> 0 | O97: =SUM(O57:O63) -> 0 | P97: =SUM(P57:P63) -> 0 | Q97: =SUM(Q57:Q63) -> 0 | R97: =SUM(R57:R63) -> 0 | S97: =SUM(S57:S63) -> 6 | T97: =SUM(T57:T63) -> 12 | ... BT97: =SUM(BT57:BT63) -> 3293
M98: =M97-L97 -> 0 | N98: =N97-M97 -> 0 | O98: =O97-N97 -> 0 | P98: =P97-O97 -> 0 | Q98: =Q97-P97 -> 0 | R98: =R97-Q97 -> 0 | S98: =S97-R97 -> 6 | T98: =T97-S97 -> 6 | ... BT98: =BT97-BS97 -> 192
K100: Total user/units | L100: basic | M100: =SUM(M57:M59) -> 0 | N100: =SUM(N57:N59) -> 0 | O100: =SUM(O57:O59) -> 0 | P100: =SUM(P57:P59) -> 0 | Q100: =SUM(Q57:Q59) -> 0 | R100: =SUM(R57:R59) -> 0 | S100: =SUM(S57:S59) -> 4 | T100: =SUM(T57:T59) -> 8 | ... BT100: =SUM(BT57:BT59) -> 1751
L101: premium | M101: =SUM(M61:M63) -> 0 | N101: =SUM(N61:N63) -> 0 | O101: =SUM(O61:O63) -> 0 | P101: =SUM(P61:P63) -> 0 | Q101: =SUM(Q61:Q63) -> 0 | R101: =SUM(R61:R63) -> 0 | S101: =SUM(S61:S63) -> 2 | T101: =SUM(T61:T63) -> 4 | ... BT101: =SUM(BT61:BT63) -> 1542

Sheet Sales Rev
A1: Sales Per Person
B2: Role | C2: Year 1 | D2: Year 2 | E2: Year 3 | F2: Year 4 | G2: Year 5 | H2: Monthly Learning Curve | M2: Year 1 | N2: Year 1 | O2: Year 1 | P2: Year 1 | Q2: Year 1 | R2: Year 1 | S2: Year 1 | T2: Year 1 | U2: Year 1 | V2: Year 1 | W2: Year 1 | X2: Year 1 | Y2: Year 2 | Z2: Year 2 | AA2: Year 2 | AB2: Year 2 | AC2: Year 2 | AD2: Year 2 | AE2: Year 2 | AF2: Year 2 | AG2: Year 2 | AH2: Year 2 | AI2: Year 2 | AJ2: Year 2 | AK2: Year 3 | AL2: Year 3 | AM2: Year 3 | AN2: Year 3 | AO2: Year 3 | AP2: Year 3 | AQ2: Year 3 | AR2: Year 3 | AS2: Year 3 | AT2: Year 3 | AU2: Year 3 | AV2: Year 3 | AW2: Year 4 | AX2: Year 4 | AY2: Year 4 | AZ2: Year 4 | BA2: Year 4 | BB2: Year 4 | BC2: Year 4 | BD2: Year 4 | BE2: Year 4 | BF2: Year 4 | BG2: Year 4 | BH2: Year 4 | BI2: Year 5 | BJ2: Year 5 | BK2: Year 5 | BL2: Year 5 | BM2: Year 5 | BN2: Year 5 | BO2: Year 5 | BP2: Year 5 | BQ2: Year 5 | BR2: Year 5 | BS2: Year 5 | BT2: Year 5
B3: Customer Success Manager | F3: 1.2 | G3: 1.5 | H3: 1.05 | J3: Unrounded Sales | M3: Jan | N3: Feb | O3: Mar | P3: Apr | Q3: May | R3: Jun | S3: Jul | T3: Aug | U3: Sep | V3: Oct | W3: Nov | X3: Dec | Y3: Jan | Z3: Feb | AA3: Mar | AB3: Apr | AC3: May | AD3: Jun | AE3: Jul | AF3: Aug | AG3: Sep | AH3: Oct | AI3: Nov | AJ3: Dec | AK3: Jan | AL3: Feb | AM3: Mar | AN3: Apr | AO3: May | AP3: Jun | AQ3: Jul | AR3: Aug | AS3: Sep | AT3: Oct | AU3: Nov | AV3: Dec | AW3: Jan | AX3: Feb | AY3: Mar | AZ3: Apr | BA3: May | BB3: Jun | BC3: Jul | BD3: Aug | BE3: Sep | BF3: Oct | BG3: Nov | BH3: Dec | BI3: Jan | BJ3: Feb | BK3: Mar | BL3: Apr | BM3: May | BN3: Jun | BO3: Jul | BP3: Aug | BQ3: Sep | BR3: Oct | BS3: Nov | BT3: Dec
B4: Founder | C4: 4 | D4: 3.6 | E4: 2.8 | F4: 2 | G4: 1.2 | H4: 1.05 | K4: Customer Success Manager | M4: =IF(M$3=$M$3,_xlfn.XLOOKUP(M$2,$C$2:$G$2,$C3:$G3)+L4,L4*$H3) -> 0 | N4: =IF(N$3=$M$3,_xlfn.XLOOKUP(N$2,$C$2:$G$2,$C3:$G3)+M4,M4*$H3) -> 0 | O4: =IF(O$3=$M$3,_xlfn.XLOOKUP(O$2,$C$2:$G$2,$C3:$G3)+N4,N4*$H3) -> 0 | P4: =IF(P$3=$M$3,_xlfn.XLOOKUP(P$2,$C$2:$G$2,$C3:$G3)+O4,O4*$H3) -> 0 | Q4: =IF(Q$3=$M$3,_xlfn.XLOOKUP(Q$2,$C$2:$G$2,$C3:$G3)+P4,P4*$H3) -> 0 | R4: =IF(R$3=$M$3,_xlfn.XLOOKUP(R$2,$C$2:$G$2,$C3:$G3)+Q4,Q4*$H3) -> 0 | S4: =IF(S$3=$M$3,_xlfn.XLOOKUP(S$2,$C$2:$G$2,$C3:$G3)+R4,R4*$H3) -> 0 | T4: =IF(T$3=$M$3,_xlfn.XLOOKUP(T$2,$C$2:$G$2,$C3:$G3)+S4,S4*$H3) -> 0 | ... BT4: =IF(BT$3=$M$3,_xlfn.XLOOKUP(BT$2,$C$2:$G$2,$C3:$G3)+BS4,BS4*$H3) -> 6.0758219
B5: Regional Sales Manager | F5: 3 | G5: 3.2 | H5: 1.05 | K5: Founder | M5: =IF(M$3=$M$3,_xlfn.XLOOKUP(M$2,$C$2:$G$2,$C4:$G4)+L5,L5*$H4) -> 4 | N5: =IF(N$3=$M$3,_xlfn.XLOOKUP(N$2,$C$2:$G$2,$C4:$G4)+M5,M5*$H4) -> 4.2 | O5: =IF(O$3=$M$3,_xlfn.XLOOKUP(O$2,$C$2:$G$2,$C4:$G4)+N5,N5*$H4) -> 4.41 | P5: =IF(P$3=$M$3,_xlfn.XLOOKUP(P$2,$C$2:$G$2,$C4:$G4)+O5,O5*$H4) -> 4.6305 | Q5: =IF(Q$3=$M$3,_xlfn.XLOOKUP(Q$2,$C$2:$G$2,$C4:$G4)+P5,P5*$H4) -> 4.862025 | R5: =IF(R$3=$M$3,_xlfn.XLOOKUP(R$2,$C$2:$G$2,$C4:$G4)+Q5,Q5*$H4) -> 5.1051263 | S5: =IF(S$3=$M$3,_xlfn.XLOOKUP(S$2,$C$2:$G$2,$C4:$G4)+R5,R5*$H4) -> 5.3603826 | T5: =IF(T$3=$M$3,_xlfn.XLOOKUP(T$2,$C$2:$G$2,$C4:$G4)+S5,S5*$H4) -> 5.6284017 | ... BT5: =IF(BT$3=$M$3,_xlfn.XLOOKUP(BT$2,$C$2:$G$2,$C4:$G4)+BS5,BS5*$H4) -> 111.26012
B6: Sales Rep | D6: 2 | E6: 2.6 | F6: 3 | G6: 3.2 | H6: 1.05 | K6: Regional Sales Manager | M6: =IF(M$3=$M$3,_xlfn.XLOOKUP(M$2,$C$2:$G$2,$C5:$G5)+L6,L6*$H5) -> 0 | N6: =IF(N$3=$M$3,_xlfn.XLOOKUP(N$2,$C$2:$G$2,$C5:$G5)+M6,M6*$H5) -> 0 | O6: =IF(O$3=$M$3,_xlfn.XLOOKUP(O$2,$C$2:$G$2,$C5:$G5)+N6,N6*$H5) -> 0 | P6: =IF(P$3=$M$3,_xlfn.XLOOKUP(P$2,$C$2:$G$2,$C5:$G5)+O6,O6*$H5) -> 0 | Q6: =IF(Q$3=$M$3,_xlfn.XLOOKUP(Q$2,$C$2:$G$2,$C5:$G5)+P6,P6*$H5) -> 0 | R6: =IF(R$3=$M$3,_xlfn.XLOOKUP(R$2,$C$2:$G$2,$C5:$G5)+Q6,Q6*$H5) -> 0 | S6: =IF(S$3=$M$3,_xlfn.XLOOKUP(S$2,$C$2:$G$2,$C5:$G5)+R6,R6*$H5) -> 0 | T6: =IF(T$3=$M$3,_xlfn.XLOOKUP(T$2,$C$2:$G$2,$C5:$G5)+S6,S6*$H5) -> 0 | ... BT6: =IF(BT$3=$M$3,_xlfn.XLOOKUP(BT$2,$C$2:$G$2,$C5:$G5)+BS6,BS6*$H5) -> 14.248868
B7: Additional Sales Rep | G7: 4 | H7: 1.05 | K7: Sales Rep | M7: =IF(M$3=$M$3,_xlfn.XLOOKUP(M$2,$C$2:$G$2,$C6:$G6)+L7,L7*$H6) -> 0 | N7: =IF(N$3=$M$3,_xlfn.XLOOKUP(N$2,$C$2:$G$2,$C6:$G6)+M7,M7*$H6) -> 0 | O7: =IF(O$3=$M$3,_xlfn.XLOOKUP(O$2,$C$2:$G$2,$C6:$G6)+N7,N7*$H6) -> 0 | P7: =IF(P$3=$M$3,_xlfn.XLOOKUP(P$2,$C$2:$G$2,$C6:$G6)+O7,O7*$H6) -> 0 | Q7: =IF(Q$3=$M$3,_xlfn.XLOOKUP(Q$2,$C$2:$G$2,$C6:$G6)+P7,P7*$H6) -> 0 | R7: =IF(R$3=$M$3,_xlfn.XLOOKUP(R$2,$C$2:$G$2,$C6:$G6)+Q7,Q7*$H6) -> 0 | S7: =IF(S$3=$M$3,_xlfn.XLOOKUP(S$2,$C$2:$G$2,$C6:$G6)+R7,R7*$H6) -> 0 | T7: =IF(T$3=$M$3,_xlfn.XLOOKUP(T$2,$C$2:$G$2,$C6:$G6)+S7,S7*$H6) -> 0 | ... BT7: =IF(BT$3=$M$3,_xlfn.XLOOKUP(BT$2,$C$2:$G$2,$C6:$G6)+BS7,BS7*$H6) -> 44.371459
B8: Sales Rep | D8: 2 | E8: 2.6 | F8: 3 | G8: 3.2 | H8: 1.05 | K8: Additional Sales Rep | M8: =IF(M$3=$M$3,_xlfn.XLOOKUP(M$2,$C$2:$G$2,$C7:$G7)+L8,L8*$H7) -> 0 | N8: =IF(N$3=$M$3,_xlfn.XLOOKUP(N$2,$C$2:$G$2,$C7:$G7)+M8,M8*$H7) -> 0 | O8: =IF(O$3=$M$3,_xlfn.XLOOKUP(O$2,$C$2:$G$2,$C7:$G7)+N8,N8*$H7) -> 0 | P8: =IF(P$3=$M$3,_xlfn.XLOOKUP(P$2,$C$2:$G$2,$C7:$G7)+O8,O8*$H7) -> 0 | Q8: =IF(Q$3=$M$3,_xlfn.XLOOKUP(Q$2,$C$2:$G$2,$C7:$G7)+P8,P8*$H7) -> 0 | R8: =IF(R$3=$M$3,_xlfn.XLOOKUP(R$2,$C$2:$G$2,$C7:$G7)+Q8,Q8*$H7) -> 0 | S8: =IF(S$3=$M$3,_xlfn.XLOOKUP(S$2,$C$2:$G$2,$C7:$G7)+R8,R8*$H7) -> 0 | T8: =IF(T$3=$M$3,_xlfn.XLOOKUP(T$2,$C$2:$G$2,$C7:$G7)+S8,S8*$H7) -> 0 | ... BT8: =IF(BT$3=$M$3,_xlfn.XLOOKUP(BT$2,$C$2:$G$2,$C7:$G7)+BS8,BS8*$H7) -> 6.8413574
B9: Sales VP | D9: 2 | E9: 2.2 | F9: 2.4 | G9: 2.6 | H9: 1.05 | K9: Sales Rep | M9: =IF(M$3=$M$3,_xlfn.XLOOKUP(M$2,$C$2:$G$2,$C8:$G8)+L9,L9*$H8) -> 0 | N9: =IF(N$3=$M$3,_xlfn.XLOOKUP(N$2,$C$2:$G$2,$C8:$G8)+M9,M9*$H8) -> 0 | O9: =IF(O$3=$M$3,_xlfn.XLOOKUP(O$2,$C$2:$G$2,$C8:$G8)+N9,N9*$H8) -> 0 | P9: =IF(P$3=$M$3,_xlfn.XLOOKUP(P$2,$C$2:$G$2,$C8:$G8)+O9,O9*$H8) -> 0 | Q9: =IF(Q$3=$M$3,_xlfn.XLOOKUP(Q$2,$C$2:$G$2,$C8:$G8)+P9,P9*$H8) -> 0 | R9: =IF(R$3=$M$3,_xlfn.XLOOKUP(R$2,$C$2:$G$2,$C8:$G8)+Q9,Q9*$H8) -> 0 | S9: =IF(S$3=$M$3,_xlfn.XLOOKUP(S$2,$C$2:$G$2,$C8:$G8)+R9,R9*$H8) -> 0 | T9: =IF(T$3=$M$3,_xlfn.XLOOKUP(T$2,$C$2:$G$2,$C8:$G8)+S9,S9*$H8) -> 0 | ... BT9: =IF(BT$3=$M$3,_xlfn.XLOOKUP(BT$2,$C$2:$G$2,$C8:$G8)+BS9,BS9*$H8) -> 44.371459
B10: Senior Sales Rep | F10: 4 | G10: 4.5 | H10: 1.05 | K10: Sales VP | M10: =IF(M$3=$M$3,_xlfn.XLOOKUP(M$2,$C$2:$G$2,$C9:$G9)+L10,L10*$H9) -> 0 | N10: =IF(N$3=$M$3,_xlfn.XLOOKUP(N$2,$C$2:$G$2,$C9:$G9)+M10,M10*$H9) -> 0 | O10: =IF(O$3=$M$3,_xlfn.XLOOKUP(O$2,$C$2:$G$2,$C9:$G9)+N10,N10*$H9) -> 0 | P10: =IF(P$3=$M$3,_xlfn.XLOOKUP(P$2,$C$2:$G$2,$C9:$G9)+O10,O10*$H9) -> 0 | Q10: =IF(Q$3=$M$3,_xlfn.XLOOKUP(Q$2,$C$2:$G$2,$C9:$G9)+P10,P10*$H9) -> 0 | R10: =IF(R$3=$M$3,_xlfn.XLOOKUP(R$2,$C$2:$G$2,$C9:$G9)+Q10,Q10*$H9) -> 0 | S10: =IF(S$3=$M$3,_xlfn.XLOOKUP(S$2,$C$2:$G$2,$C9:$G9)+R10,R10*$H9) -> 0 | T10: =IF(T$3=$M$3,_xlfn.XLOOKUP(T$2,$C$2:$G$2,$C9:$G9)+S10,S10*$H9) -> 0 | ... BT10: =IF(BT$3=$M$3,_xlfn.XLOOKUP(BT$2,$C$2:$G$2,$C9:$G9)+BS10,BS10*$H9) -> 39.588823
K11: Senior Sales Rep | M11: =IF(M$3=$M$3,_xlfn.XLOOKUP(M$2,$C$2:$G$2,$C10:$G10)+L11,L11*$H10) -> 0 | N11: =IF(N$3=$M$3,_xlfn.XLOOKUP(N$2,$C$2:$G$2,$C10:$G10)+M11,M11*$H10) -> 0 | O11: =IF(O$3=$M$3,_xlfn.XLOOKUP(O$2,$C$2:$G$2,$C10:$G10)+N11,N11*$H10) -> 0 | P11: =IF(P$3=$M$3,_xlfn.XLOOKUP(P$2,$C$2:$G$2,$C10:$G10)+O11,O11*$H10) -> 0 | Q11: =IF(Q$3=$M$3,_xlfn.XLOOKUP(Q$2,$C$2:$G$2,$C10:$G10)+P11,P11*$H10) -> 0 | R11: =IF(R$3=$M$3,_xlfn.XLOOKUP(R$2,$C$2:$G$2,$C10:$G10)+Q11,Q11*$H10) -> 0 | S11: =IF(S$3=$M$3,_xlfn.XLOOKUP(S$2,$C$2:$G$2,$C10:$G10)+R11,R11*$H10) -> 0 | T11: =IF(T$3=$M$3,_xlfn.XLOOKUP(T$2,$C$2:$G$2,$C10:$G10)+S11,S11*$H10) -> 0 | ... BT11: =IF(BT$3=$M$3,_xlfn.XLOOKUP(BT$2,$C$2:$G$2,$C10:$G10)+BS11,BS11*$H10) -> 19.39757
B12: Beginning Sales | C12: Starting Year | J12: Comissions
B13: Customer Success Manager | C13: ='Sales & Marketing'!D19 -> 4 | K13: Total Monthly Sales | M13: =SUM(M4:M11) -> 4 | N13: =SUM(N4:N11) -> 4.2 | O13: =SUM(O4:O11) -> 4.41 | P13: =SUM(P4:P11) -> 4.6305 | Q13: =SUM(Q4:Q11) -> 4.862025 | R13: =SUM(R4:R11) -> 5.1051263 | S13: =SUM(S4:S11) -> 5.3603826 | T13: =SUM(T4:T11) -> 5.6284017 | ... BT13: =SUM(BT4:BT11) -> 286.15548
B14: Founder | C14: 1
B15: Regional Sales Manager | C15: ='Sales & Marketing'!D18 -> 4 | K15: Customer Success Manager | M15: {=_xlfn.XLOOKUP(M$2,_xlfn.ANCHORARRAY($C$21),$C$24:$G$24)*M4*$C$23} -> 0 | N15: {=_xlfn.XLOOKUP(N$2,_xlfn.ANCHORARRAY($C$21),$C$24:$G$24)*N4*$C$23} -> 0 | O15: {=_xlfn.XLOOKUP(O$2,_xlfn.ANCHORARRAY($C$21),$C$24:$G$24)*O4*$C$23} -> 0 | P15: {=_xlfn.XLOOKUP(P$2,_xlfn.ANCHORARRAY($C$21),$C$24:$G$24)*P4*$C$23} -> 0 | Q15: {=_xlfn.XLOOKUP(Q$2,_xlfn.ANCHORARRAY($C$21),$C$24:$G$24)*Q4*$C$23} -> 0 | R15: {=_xlfn.XLOOKUP(R$2,_xlfn.ANCHORARRAY($C$21),$C$24:$G$24)*R4*$C$23} -> 0 | S15: {=_xlfn.XLOOKUP(S$2,_xlfn.ANCHORARRAY($C$21),$C$24:$G$24)*S4*$C$23} -> 0 | T15: {=_xlfn.XLOOKUP(T$2,_xlfn.ANCHORARRAY($C$21),$C$24:$G$24)*T4*$C$23} -> 0 | ... BT15: {=_xlfn.XLOOKUP(BT$2,_xlfn.ANCHORARRAY($C$21),$C$24:$G$24)*BT4*$C$23} -> 769.60411
B16: Sales Rep | C16: 2 | K16: Founder
B17: Additional Sales Rep | C17: 5 | K17: Regional Sales Manager | M17: {=_xlfn.XLOOKUP(M$2,_xlfn.ANCHORARRAY($C$21),$C$24:$G$24)*M6*$C$23} -> 0 | N17: {=_xlfn.XLOOKUP(N$2,_xlfn.ANCHORARRAY($C$21),$C$24:$G$24)*N6*$C$23} -> 0 | O17: {=_xlfn.XLOOKUP(O$2,_xlfn.ANCHORARRAY($C$21),$C$24:$G$24)*O6*$C$23} -> 0 | P17: {=_xlfn.XLOOKUP(P$2,_xlfn.ANCHORARRAY($C$21),$C$24:$G$24)*P6*$C$23} -> 0 | Q17: {=_xlfn.XLOOKUP(Q$2,_xlfn.ANCHORARRAY($C$21),$C$24:$G$24)*Q6*$C$23} -> 0 | R17: {=_xlfn.XLOOKUP(R$2,_xlfn.ANCHORARRAY($C$21),$C$24:$G$24)*R6*$C$23} -> 0 | S17: {=_xlfn.XLOOKUP(S$2,_xlfn.ANCHORARRAY($C$21),$C$24:$G$24)*S6*$C$23} -> 0 | T17: {=_xlfn.XLOOKUP(T$2,_xlfn.ANCHORARRAY($C$21),$C$24:$G$24)*T6*$C$23} -> 0 | ... BT17: {=_xlfn.XLOOKUP(BT$2,_xlfn.ANCHORARRAY($C$21),$C$24:$G$24)*BT6*$C$23} -> 1804.8566
B18: Sales Rep | C18: ='Sales & Marketing'!D14 -> 2 | K18: Sales Rep | M18: {=_xlfn.XLOOKUP(M$2,_xlfn.ANCHORARRAY($C$21),$C$24:$G$24)*M7*$C$23} -> 0 | N18: {=_xlfn.XLOOKUP(N$2,_xlfn.ANCHORARRAY($C$21),$C$24:$G$24)*N7*$C$23} -> 0 | O18: {=_xlfn.XLOOKUP(O$2,_xlfn.ANCHORARRAY($C$21),$C$24:$G$24)*O7*$C$23} -> 0 | P18: {=_xlfn.XLOOKUP(P$2,_xlfn.ANCHORARRAY($C$21),$C$24:$G$24)*P7*$C$23} -> 0 | Q18: {=_xlfn.XLOOKUP(Q$2,_xlfn.ANCHORARRAY($C$21),$C$24:$G$24)*Q7*$C$23} -> 0 | R18: {=_xlfn.XLOOKUP(R$2,_xlfn.ANCHORARRAY($C$21),$C$24:$G$24)*R7*$C$23} -> 0 | S18: {=_xlfn.XLOOKUP(S$2,_xlfn.ANCHORARRAY($C$21),$C$24:$G$24)*S7*$C$23} -> 0 | T18: {=_xlfn.XLOOKUP(T$2,_xlfn.ANCHORARRAY($C$21),$C$24:$G$24)*T7*$C$23} -> 0 | ... BT18: {=_xlfn.XLOOKUP(BT$2,_xlfn.ANCHORARRAY($C$21),$C$24:$G$24)*BT7*$C$23} -> 5620.3848
B19: Sales VP | C19: ='Sales & Marketing'!D13 -> 2 | K19: Additional Sales Rep | M19: {=_xlfn.XLOOKUP(M$2,_xlfn.ANCHORARRAY($C$21),$C$24:$G$24)*M8*$C$23} -> 0 | N19: {=_xlfn.XLOOKUP(N$2,_xlfn.ANCHORARRAY($C$21),$C$24:$G$24)*N8*$C$23} -> 0 | O19: {=_xlfn.XLOOKUP(O$2,_xlfn.ANCHORARRAY($C$21),$C$24:$G$24)*O8*$C$23} -> 0 | P19: {=_xlfn.XLOOKUP(P$2,_xlfn.ANCHORARRAY($C$21),$C$24:$G$24)*P8*$C$23} -> 0 | Q19: {=_xlfn.XLOOKUP(Q$2,_xlfn.ANCHORARRAY($C$21),$C$24:$G$24)*Q8*$C$23} -> 0 | R19: {=_xlfn.XLOOKUP(R$2,_xlfn.ANCHORARRAY($C$21),$C$24:$G$24)*R8*$C$23} -> 0 | S19: {=_xlfn.XLOOKUP(S$2,_xlfn.ANCHORARRAY($C$21),$C$24:$G$24)*S8*$C$23} -> 0 | T19: {=_xlfn.XLOOKUP(T$2,_xlfn.ANCHORARRAY($C$21),$C$24:$G$24)*T8*$C$23} -> 0 | ... BT19: {=_xlfn.XLOOKUP(BT$2,_xlfn.ANCHORARRAY($C$21),$C$24:$G$24)*BT8*$C$23} -> 866.57194
B20: Senior Sales Rep | C20: ='Sales & Marketing'!D16 -> 3 | K20: Sales Rep | M20: {=_xlfn.XLOOKUP(M$2,_xlfn.ANCHORARRAY($C$21),$C$24:$G$24)*M9*$C$23} -> 0 | N20: {=_xlfn.XLOOKUP(N$2,_xlfn.ANCHORARRAY($C$21),$C$24:$G$24)*N9*$C$23} -> 0 | O20: {=_xlfn.XLOOKUP(O$2,_xlfn.ANCHORARRAY($C$21),$C$24:$G$24)*O9*$C$23} -> 0 | P20: {=_xlfn.XLOOKUP(P$2,_xlfn.ANCHORARRAY($C$21),$C$24:$G$24)*P9*$C$23} -> 0 | Q20: {=_xlfn.XLOOKUP(Q$2,_xlfn.ANCHORARRAY($C$21),$C$24:$G$24)*Q9*$C$23} -> 0 | R20: {=_xlfn.XLOOKUP(R$2,_xlfn.ANCHORARRAY($C$21),$C$24:$G$24)*R9*$C$23} -> 0 | S20: {=_xlfn.XLOOKUP(S$2,_xlfn.ANCHORARRAY($C$21),$C$24:$G$24)*S9*$C$23} -> 0 | T20: {=_xlfn.XLOOKUP(T$2,_xlfn.ANCHORARRAY($C$21),$C$24:$G$24)*T9*$C$23} -> 0 | ... BT20: {=_xlfn.XLOOKUP(BT$2,_xlfn.ANCHORARRAY($C$21),$C$24:$G$24)*BT9*$C$23} -> 5620.3848
C21: {=C2:G2} -> Year 1 | D21: Year 2 | E21: Year 3 | F21: Year 4 | G21: Year 5 | K21: Sales VP | M21: {=_xlfn.XLOOKUP(M$2,_xlfn.ANCHORARRAY($C$21),$C$24:$G$24)*M10*$C$23} -> 0 | N21: {=_xlfn.XLOOKUP(N$2,_xlfn.ANCHORARRAY($C$21),$C$24:$G$24)*N10*$C$23} -> 0 | O21: {=_xlfn.XLOOKUP(O$2,_xlfn.ANCHORARRAY($C$21),$C$24:$G$24)*O10*$C$23} -> 0 | P21: {=_xlfn.XLOOKUP(P$2,_xlfn.ANCHORARRAY($C$21),$C$24:$G$24)*P10*$C$23} -> 0 | Q21: {=_xlfn.XLOOKUP(Q$2,_xlfn.ANCHORARRAY($C$21),$C$24:$G$24)*Q10*$C$23} -> 0 | R21: {=_xlfn.XLOOKUP(R$2,_xlfn.ANCHORARRAY($C$21),$C$24:$G$24)*R10*$C$23} -> 0 | S21: {=_xlfn.XLOOKUP(S$2,_xlfn.ANCHORARRAY($C$21),$C$24:$G$24)*S10*$C$23} -> 0 | T21: {=_xlfn.XLOOKUP(T$2,_xlfn.ANCHORARRAY($C$21),$C$24:$G$24)*T10*$C$23} -> 0 | ... BT21: {=_xlfn.XLOOKUP(BT$2,_xlfn.ANCHORARRAY($C$21),$C$24:$G$24)*BT10*$C$23} -> 5014.5843
B22: Commsions per Sale | K22: Senior Sales Rep | M22: {=_xlfn.XLOOKUP(M$2,_xlfn.ANCHORARRAY($C$21),$C$24:$G$24)*M11*$C$23} -> 0 | N22: {=_xlfn.XLOOKUP(N$2,_xlfn.ANCHORARRAY($C$21),$C$24:$G$24)*N11*$C$23} -> 0 | O22: {=_xlfn.XLOOKUP(O$2,_xlfn.ANCHORARRAY($C$21),$C$24:$G$24)*O11*$C$23} -> 0 | P22: {=_xlfn.XLOOKUP(P$2,_xlfn.ANCHORARRAY($C$21),$C$24:$G$24)*P11*$C$23} -> 0 | Q22: {=_xlfn.XLOOKUP(Q$2,_xlfn.ANCHORARRAY($C$21),$C$24:$G$24)*Q11*$C$23} -> 0 | R22: {=_xlfn.XLOOKUP(R$2,_xlfn.ANCHORARRAY($C$21),$C$24:$G$24)*R11*$C$23} -> 0 | S22: {=_xlfn.XLOOKUP(S$2,_xlfn.ANCHORARRAY($C$21),$C$24:$G$24)*S11*$C$23} -> 0 | T22: {=_xlfn.XLOOKUP(T$2,_xlfn.ANCHORARRAY($C$21),$C$24:$G$24)*T11*$C$23} -> 0 | ... BT22: {=_xlfn.XLOOKUP(BT$2,_xlfn.ANCHORARRAY($C$21),$C$24:$G$24)*BT11*$C$23} -> 2457.0255
B23: 20% of Average Sub Price | C23: 0.2
B24: Avg Sub Price | C24: =AVERAGE(Rev!D11:D17) -> 391.5 | D24: =AVERAGE(Rev!E11:E17) -> 437.5 | E24: =AVERAGE(Rev!F11:F17) -> 513.33333 | F24: =AVERAGE(Rev!G11:G17) -> 558.33333 | G24: =AVERAGE(Rev!H11:H17) -> 633.33333

Sheet Summary P&L
D1: Time | E1: =E3&" "&E4 -> Year 1 Q1 | F1: =F3&" "&F4 -> Year 1 Q2 | G1: =G3&" "&G4 -> Year 1 Q3 | H1: =H3&" "&H4 -> Year 1 Q4 | I1: =I3&" "&I4 -> Year 2 Q1 | J1: =J3&" "&J4 -> Year 2 Q2 | K1: =K3&" "&K4 -> Year 2 Q3 | L1: =L3&" "&L4 -> Year 2 Q4 | ... X1: =X3&" "&X4 -> Year 5 Q4
B2: Quarterly P & L
E3: Year 1 | F3: Year 1 | G3: Year 1 | H3: Year 1 | I3: Year 2 | J3: Year 2 | K3: Year 2 | L3: Year 2 | M3: Year 3 | N3: Year 3 | O3: Year 3 | P3: Year 3 | Q3: Year 4 | R3: Year 4 | S3: Year 4 | T3: Year 4 | U3: Year 5 | V3: Year 5 | W3: Year 5 | X3: Year 5
E4: Q1 | F4: Q2 | G4: Q3 | H4: Q4 | I4: Q1 | J4: Q2 | K4: Q3 | L4: Q4 | M4: Q1 | N4: Q2 | O4: Q3 | P4: Q4 | Q4: Q1 | R4: Q2 | S4: Q3 | T4: Q4 | U4: Q1 | V4: Q2 | W4: Q3 | X4: Q4
D5: Total Revenue | E5: =SUM('P&L'!M9:O9) -> 0 | F5: =SUM('P&L'!P9:R9) -> 0 | G5: =SUM('P&L'!S9:U9) -> 14300 | H5: =SUM('P&L'!V9:X9) -> 22550 | I5: =SUM('P&L'!Y9:AA9) -> 163380 | J5: =SUM('P&L'!AB9:AD9) -> 212990 | K5: =SUM('P&L'!AE9:AG9) -> 270155 | L5: =SUM('P&L'!AH9:AJ9) -> 333605 | M5: =SUM('P&L'!AK9:AM9) -> 662850 | N5: =SUM('P&L'!AN9:AP9) -> 844000 | O5: =SUM('P&L'!AQ9:AS9) -> 1041390 | P5: =SUM('P&L'!AT9:AV9) -> 1289470 | Q5: =SUM('P&L'!AW9:AY9) -> 2069980 | R5: =SUM('P&L'!AZ9:BB9) -> 2561320 | S5: =SUM('P&L'!BC9:BE9) -> 3210020 | T5: =SUM('P&L'!BF9:BH9) -> 3897340 | U5: =SUM('P&L'!BI9:BK9) -> 5692730 | V5: =SUM('P&L'!BL9:BN9) -> 6997420 | W5: =SUM('P&L'!BO9:BQ9) -> 8491070 | X5: =SUM('P&L'!BR9:BT9) -> 10243280
D6: COGS | E6: =SUM('P&L'!M23:O23) -> 0 | F6: =SUM('P&L'!P23:R23) -> 1000 | G6: =SUM('P&L'!S23:U23) -> 3246.5 | H6: =SUM('P&L'!V23:X23) -> 3589 | I6: =SUM('P&L'!Y23:AA23) -> 9092.5 | J6: =SUM('P&L'!AB23:AD23) -> 10427.5 | K6: =SUM('P&L'!AE23:AG23) -> 11880 | L6: =SUM('P&L'!AH23:AJ23) -> 13611.25 | M6: =SUM('P&L'!AK23:AM23) -> 27027.5 | N6: =SUM('P&L'!AN23:AP23) -> 32567.25 | O6: =SUM('P&L'!AQ23:AS23) -> 38924 | P6: =SUM('P&L'!AT23:AV23) -> 46425 | Q6: =SUM('P&L'!AW23:AY23) -> 82431.875 | R6: =SUM('P&L'!AZ23:BB23) -> 104172.5 | S6: =SUM('P&L'!BC23:BE23) -> 129909.38 | T6: =SUM('P&L'!BF23:BH23) -> 159240.62 | U6: =SUM('P&L'!BI23:BK23) -> 257402.5 | V6: =SUM('P&L'!BL23:BN23) -> 319466.25 | W6: =SUM('P&L'!BO23:BQ23) -> 391228.75 | X6: =SUM('P&L'!BR23:BT23) -> 474646.25
C7: Gross Profit | E7: =E5-E6 -> 0 | F7: =SUM('P&L'!P25:R25) -> -1000 | G7: =SUM('P&L'!S25:U25) -> 11053.5 | H7: =SUM('P&L'!V25:X25) -> 18961 | I7: =SUM('P&L'!Y25:AA25) -> 154287.5 | J7: =SUM('P&L'!AB25:AD25) -> 202562.5 | K7: =SUM('P&L'!AE25:AG25) -> 258275 | L7: =SUM('P&L'!AH25:AJ25) -> 319993.75 | M7: =SUM('P&L'!AK25:AM25) -> 635822.5 | N7: =SUM('P&L'!AN25:AP25) -> 811432.75 | O7: =SUM('P&L'!AQ25:AS25) -> 1002466 | P7: =SUM('P&L'!AT25:AV25) -> 1243045 | Q7: =SUM('P&L'!AW25:AY25) -> 1987548.1 | R7: =SUM('P&L'!AZ25:BB25) -> 2457147.5 | S7: =SUM('P&L'!BC25:BE25) -> 3080110.6 | T7: =SUM('P&L'!BF25:BH25) -> 3738099.4 | U7: =SUM('P&L'!BI25:BK25) -> 5435327.5 | V7: =SUM('P&L'!BL25:BN25) -> 6677953.8 | W7: =SUM('P&L'!BO25:BQ25) -> 8099841.2 | X7: =SUM('P&L'!BR25:BT25) -> 9768633.8
C8: Operating Expenses
D9: R&D | E9: =SUM('P&L'!M28:O28) -> 49550 | F9: =SUM('P&L'!P28:R28) -> 107616.67 | G9: =SUM('P&L'!S28:U28) -> 136650 | H9: =SUM('P&L'!V28:X28) -> 136650 | I9: =SUM('P&L'!Y28:AA28) -> 202189.17 | J9: =SUM('P&L'!AB28:AD28) -> 291119.17 | K9: =SUM('P&L'!AE28:AG28) -> 359062.5 | L9: =SUM('P&L'!AH28:AJ28) -> 359062.5 | M9: =SUM('P&L'!AK28:AM28) -> 410377.29 | N9: =SUM('P&L'!AN28:AP28) -> 499670.63 | O9: =SUM('P&L'!AQ28:AS28) -> 587358.96 | P9: =SUM('P&L'!AT28:AV28) -> 650835.63 | Q9: =SUM('P&L'!AW28:AY28) -> 773157.41 | R9: =SUM('P&L'!AZ28:BB28) -> 802190.74 | S9: =SUM('P&L'!BC28:BE28) -> 910720.74 | T9: =SUM('P&L'!BF28:BH28) -> 984930.74 | U9: =SUM('P&L'!BI28:BK28) -> 1044634.8 | V9: =SUM('P&L'!BL28:BN28) -> 1044634.8 | W9: =SUM('P&L'!BO28:BQ28) -> 1044634.8 | X9: =SUM('P&L'!BR28:BT28) -> 1044634.8
D10: Marketing | E10: =SUM('P&L'!M29:O29) -> 38250 | F10: =SUM('P&L'!P29:R29) -> 38250 | G10: =SUM('P&L'!S29:U29) -> 38250 | H10: =SUM('P&L'!V29:X29) -> 38250 | I10: =SUM('P&L'!Y29:AA29) -> 67575 | J10: =SUM('P&L'!AB29:AD29) -> 67575 | K10: =SUM('P&L'!AE29:AG29) -> 67575 | L10: =SUM('P&L'!AH29:AJ29) -> 67575 | M10: =SUM('P&L'!AK29:AM29) -> 85450 | N10: =SUM('P&L'!AN29:AP29) -> 85450 | O10: =SUM('P&L'!AQ29:AS29) -> 85450 | P10: =SUM('P&L'!AT29:AV29) -> 85450 | Q10: =SUM('P&L'!AW29:AY29) -> 101325 | R10: =SUM('P&L'!AZ29:BB29) -> 101325 | S10: =SUM('P&L'!BC29:BE29) -> 101325 | T10: =SUM('P&L'!BF29:BH29) -> 101325 | U10: =SUM('P&L'!BI29:BK29) -> 115950 | V10: =SUM('P&L'!BL29:BN29) -> 115950 | W10: =SUM('P&L'!BO29:BQ29) -> 115950 | X10: =SUM('P&L'!BR29:BT29) -> 115950
D11: G&A | E11: =SUM('P&L'!M30:O30) -> 296225 | F11: =SUM('P&L'!P30:R30) -> 296225 | G11: =SUM('P&L'!S30:U30) -> 300698.33 | H11: =SUM('P&L'!V30:X30) -> 313228.33 | I11: =SUM('P&L'!Y30:AA30) -> 400973.33 | J11: =SUM('P&L'!AB30:AD30) -> 493015 | K11: =SUM('P&L'!AE30:AG30) -> 495265 | L11: =SUM('P&L'!AH30:AJ30) -> 508765 | M11: =SUM('P&L'!AK30:AM30) -> 566160 | N11: =SUM('P&L'!AN30:AP30) -> 576160 | O11: =SUM('P&L'!AQ30:AS30) -> 581160 | P11: =SUM('P&L'!AT30:AV30) -> 581160 | Q11: =SUM('P&L'!AW30:AY30) -> 751635 | R11: =SUM('P&L'!AZ30:BB30) -> 710635 | S11: =SUM('P&L'!BC30:BE30) -> 682635 | T11: =SUM('P&L'!BF30:BH30) -> 682635 | U11: =SUM('P&L'!BI30:BK30) -> 682635 | V11: =SUM('P&L'!BL30:BN30) -> 682635 | W11: =SUM('P&L'!BO30:BQ30) -> 682635 | X11: =SUM('P&L'!BR30:BT30) -> 682635
D12: Sales | E12: =SUM('P&L'!M31:O31) -> 1500 | F12: =SUM('P&L'!P31:R31) -> 1500 | G12: =SUM('P&L'!S31:U31) -> 1500 | H12: =SUM('P&L'!V31:X31) -> 1500 | I12: =SUM('P&L'!Y31:AA31) -> 68013.75 | J12: =SUM('P&L'!AB31:AD31) -> 68762.206 | K12: =SUM('P&L'!AE31:AG31) -> 69049.826 | L12: =SUM('P&L'!AH31:AJ31) -> 69382.781 | M12: =SUM('P&L'!AK31:AM31) -> 99162.073 | N12: =SUM('P&L'!AN31:AP31) -> 100849.25 | O12: =SUM('P&L'!AQ31:AS31) -> 101842.66 | P12: =SUM('P&L'!AT31:AV31) -> 102992.65 | Q12: =SUM('P&L'!AW31:AY31) -> 159654.01 | R12: =SUM('P&L'!AZ31:BB31) -> 164004.28 | S12: =SUM('P&L'!BC31:BE31) -> 166867.82 | T12: =SUM('P&L'!BF31:BH31) -> 170182.73 | U12: =SUM('P&L'!BI31:BK31) -> 207139.57 | V12: =SUM('P&L'!BL31:BN31) -> 216665.48 | W12: =SUM('P&L'!BO31:BQ31) -> 223761.54 | X12: =SUM('P&L'!BR31:BT31) -> 231976.11
D13: Total Operating Expense | E13: =SUM(E9:E11) -> 384025 | F13: =SUM('P&L'!P33:R33) -> 443591.67 | G13: =SUM('P&L'!S33:U33) -> 477098.33 | H13: =SUM('P&L'!V33:X33) -> 489628.33 | I13: =SUM('P&L'!Y33:AA33) -> 738751.25 | J13: =SUM('P&L'!AB33:AD33) -> 920471.37 | K13: =SUM('P&L'!AE33:AG33) -> 990952.33 | L13: =SUM('P&L'!AH33:AJ33) -> 1004785.3 | M13: =SUM('P&L'!AK33:AM33) -> 1161149.4 | N13: =SUM('P&L'!AN33:AP33) -> 1262129.9 | O13: =SUM('P&L'!AQ33:AS33) -> 1355811.6 | P13: =SUM('P&L'!AT33:AV33) -> 1420438.3 | Q13: =SUM('P&L'!AW33:AY33) -> 1785771.4 | R13: =SUM('P&L'!AZ33:BB33) -> 1778155 | S13: =SUM('P&L'!BC33:BE33) -> 1861548.6 | T13: =SUM('P&L'!BF33:BH33) -> 1939073.5 | U13: =SUM('P&L'!BI33:BK33) -> 2050359.3 | V13: =SUM('P&L'!BL33:BN33) -> 2059885.3 | W13: =SUM('P&L'!BO33:BQ33) -> 2066981.3 | X13: =SUM('P&L'!BR33:BT33) -> 2075195.9
C14: Operating Income | E14: =E7-E13 -> -384025 | F14: =SUM('P&L'!P36:R36) -> -444591.67 | G14: =SUM('P&L'!S36:U36) -> -466044.83 | H14: =SUM('P&L'!V36:X36) -> -470667.33 | I14: =SUM('P&L'!Y36:AA36) -> -584463.75 | J14: =SUM('P&L'!AB36:AD36) -> -717908.87 | K14: =SUM('P&L'!AE36:AG36) -> -732677.33 | L14: =SUM('P&L'!AH36:AJ36) -> -684791.53 | M14: =SUM('P&L'!AK36:AM36) -> -525326.86 | N14: =SUM('P&L'!AN36:AP36) -> -450697.12 | O14: =SUM('P&L'!AQ36:AS36) -> -353345.61 | P14: =SUM('P&L'!AT36:AV36) -> -177393.28 | Q14: =SUM('P&L'!AW36:AY36) -> 201776.71 | R14: =SUM('P&L'!AZ36:BB36) -> 678992.48 | S14: =SUM('P&L'!BC36:BE36) -> 1218562.1 | T14: =SUM('P&L'!BF36:BH36) -> 1799025.9 | U14: =SUM('P&L'!BI36:BK36) -> 3384968.2 | V14: =SUM('P&L'!BL36:BN36) -> 4618068.5 | W14: =SUM('P&L'!BO36:BQ36) -> 6032859.9 | X14: =SUM('P&L'!BR36:BT36) -> 7693437.9
C16: Depreciation | E16: =SUM('P&L'!M38:O38) -> 1400 | F16: =SUM('P&L'!P38:R38) -> 1400 | G16: =SUM('P&L'!S38:U38) -> 1400 | H16: =SUM('P&L'!V38:X38) -> 1400 | I16: =SUM('P&L'!Y38:AA38) -> 2150 | J16: =SUM('P&L'!AB38:AD38) -> 2150 | K16: =SUM('P&L'!AE38:AG38) -> 2150 | L16: =SUM('P&L'!AH38:AJ38) -> 2150 | M16: =SUM('P&L'!AK38:AM38) -> 3350 | N16: =SUM('P&L'!AN38:AP38) -> 3350 | O16: =SUM('P&L'!AQ38:AS38) -> 3350 | P16: =SUM('P&L'!AT38:AV38) -> 3350 | Q16: =SUM('P&L'!AW38:AY38) -> 4400 | R16: =SUM('P&L'!AZ38:BB38) -> 4400 | S16: =SUM('P&L'!BC38:BE38) -> 4400 | T16: =SUM('P&L'!BF38:BH38) -> 4400 | U16: =SUM('P&L'!BI38:BK38) -> 4400 | V16: =SUM('P&L'!BL38:BN38) -> 4400 | W16: =SUM('P&L'!BO38:BQ38) -> 4400 | X16: =SUM('P&L'!BR38:BT38) -> 4400
C17: Interest Exp | E17: =SUM('P&L'!M39:O39) -> 4931.8001 | F17: =SUM('P&L'!P39:R39) -> 4724.9171 | G17: =SUM('P&L'!S39:U39) -> 4513.8688 | H17: =SUM('P&L'!V39:X39) -> 4298.5713 | I17: =SUM('P&L'!Y39:AA39) -> 4078.9391 | J17: =SUM('P&L'!AB39:AD39) -> 3854.8849 | K17: =SUM('P&L'!AE39:AG39) -> 3626.3196 | L17: =SUM('P&L'!AH39:AJ39) -> 3393.1525 | M17: =SUM('P&L'!AK39:AM39) -> 3155.291 | N17: =SUM('P&L'!AN39:AP39) -> 2912.6404 | O17: =SUM('P&L'!AQ39:AS39) -> 2665.1043 | P17: =SUM('P&L'!AT39:AV39) -> 2412.5845 | Q17: =SUM('P&L'!AW39:AY39) -> 2154.9805 | R17: =SUM('P&L'!AZ39:BB39) -> 1892.19 | S17: =SUM('P&L'!BC39:BE39) -> 1624.1086 | T17: =SUM('P&L'!BF39:BH39) -> 1350.6298 | U17: =SUM('P&L'!BI39:BK39) -> 1071.6448 | V17: =SUM('P&L'!BL39:BN39) -> 787.04283 | W17: =SUM('P&L'!BO39:BQ39) -> 496.7108 | X17: =SUM('P&L'!BR39:BT39) -> 200.53333
C18: Pre tax income | E18: =SUM('P&L'!M41:O41) -> -391856.8 | F18: =SUM('P&L'!P41:R41) -> -450716.58 | G18: =SUM('P&L'!S41:U41) -> -471958.7 | H18: =SUM('P&L'!V41:X41) -> -476365.9 | I18: =SUM('P&L'!Y41:AA41) -> -590692.69 | J18: =SUM('P&L'!AB41:AD41) -> -723913.76 | K18: =SUM('P&L'!AE41:AG41) -> -738453.65 | L18: =SUM('P&L'!AH41:AJ41) -> -690334.68 | M18: =SUM('P&L'!AK41:AM41) -> -531832.16 | N18: =SUM('P&L'!AN41:AP41) -> -456959.76 | O18: =SUM('P&L'!AQ41:AS41) -> -359360.72 | P18: =SUM('P&L'!AT41:AV41) -> -183155.86 | Q18: =SUM('P&L'!AW41:AY41) -> 195221.73 | R18: =SUM('P&L'!AZ41:BB41) -> 672700.29 | S18: =SUM('P&L'!BC41:BE41) -> 1212538 | T18: =SUM('P&L'!BF41:BH41) -> 1793275.3 | U18: =SUM('P&L'!BI41:BK41) -> 3379496.5 | V18: =SUM('P&L'!BL41:BN41) -> 4612881.5 | W18: =SUM('P&L'!BO41:BQ41) -> 6027963.2 | X18: =SUM('P&L'!BR41:BT41) -> 7688837.3
C19: Taxes @20% | E19: =SUM('P&L'!M42:O42) -> 0 | F19: =SUM('P&L'!P42:R42) -> 0 | G19: =SUM('P&L'!S42:U42) -> 0 | H19: =SUM('P&L'!V42:X42) -> 0 | I19: =SUM('P&L'!Y42:AA42) -> 0 | J19: =SUM('P&L'!AB42:AD42) -> 0 | K19: =SUM('P&L'!AE42:AG42) -> 0 | L19: =SUM('P&L'!AH42:AJ42) -> 0 | M19: =SUM('P&L'!AK42:AM42) -> 0 | N19: =SUM('P&L'!AN42:AP42) -> 0 | O19: =SUM('P&L'!AQ42:AS42) -> 0 | P19: =SUM('P&L'!AT42:AV42) -> 0 | Q19: =SUM('P&L'!AW42:AY42) -> 39044.345 | R19: =SUM('P&L'!AZ42:BB42) -> 134540.06 | S19: =SUM('P&L'!BC42:BE42) -> 242507.59 | T19: =SUM('P&L'!BF42:BH42) -> 358655.06 | U19: =SUM('P&L'!BI42:BK42) -> 675899.3 | V19: =SUM('P&L'!BL42:BN42) -> 922576.29 | W19: =SUM('P&L'!BO42:BQ42) -> 1205592.6 | X19: =SUM('P&L'!BR42:BT42) -> 1537767.5
C20: Net Income | E20: =SUM('P&L'!M44:O44) -> -391856.8 | F20: =SUM('P&L'!P44:R44) -> -450716.58 | G20: =SUM('P&L'!S44:U44) -> -471958.7 | H20: =SUM('P&L'!V44:X44) -> -476365.9 | I20: =SUM('P&L'!Y44:AA44) -> -590692.69 | J20: =SUM('P&L'!AB44:AD44) -> -723913.76 | K20: =SUM('P&L'!AE44:AG44) -> -738453.65 | L20: =SUM('P&L'!AH44:AJ44) -> -690334.68 | M20: =SUM('P&L'!AK44:AM44) -> -531832.16 | N20: =SUM('P&L'!AN44:AP44) -> -456959.76 | O20: =SUM('P&L'!AQ44:AS44) -> -359360.72 | P20: =SUM('P&L'!AT44:AV44) -> -183155.86 | Q20: =SUM('P&L'!AW44:AY44) -> 156177.38 | R20: =SUM('P&L'!AZ44:BB44) -> 538160.23 | S20: =SUM('P&L'!BC44:BE44) -> 970030.36 | T20: =SUM('P&L'!BF44:BH44) -> 1434620.2 | U20: =SUM('P&L'!BI44:BK44) -> 2703597.2 | V20: =SUM('P&L'!BL44:BN44) -> 3690305.2 | W20: =SUM('P&L'!BO44:BQ44) -> 4822370.6 | X20: =SUM('P&L'!BR44:BT44) -> 6151069.9
C21: Retained Earnings | E21: =D21+E20 -> -391856.8 | F21: =E21+F20 -> -842573.38 | G21: =F21+G20 -> -1314532.1 | H21: =G21+H20 -> -1790898 | I21: =H21+I20 -> -2381590.7 | J21: =I21+J20 -> -3105504.4 | K21: =J21+K20 -> -3843958.1 | L21: =K21+L20 -> -4534292.8 | ... X21: =W21+X20 -> 14400730
B23: Quarterly Cash Flow
B25: Net Income Method
C26: Beginning Cash | E26: 0 | F26: =E36 -> 407517.7 | G26: =F36 -> 33968.742 | H26: =G36 -> -361361.39 | I26: =H36 -> 1738833 | J26: =I36 -> 1207295.3 | K26: =J36 -> 559631.57 | L26: =K36 -> -132139.9 | M26: =L36 -> 8166599.6 | ... X26: =W36 -> 20631423
C27: Net Income | E27: =SUM('P&L'!M52:O52) -> -391856.8 | F27: =SUM('P&L'!P52:R52) -> -450716.58 | G27: =SUM('P&L'!S52:U52) -> -471958.7 | H27: =SUM('P&L'!V52:X52) -> -476365.9 | I27: =SUM('P&L'!Y52:AA52) -> -590692.69 | J27: =SUM('P&L'!AB52:AD52) -> -723913.76 | K27: =SUM('P&L'!AE52:AG52) -> -738453.65 | L27: =SUM('P&L'!AH52:AJ52) -> -690334.68 | M27: =SUM('P&L'!AK52:AM52) -> -531832.16 | N27: =SUM('P&L'!AN52:AP52) -> -456959.76 | O27: =SUM('P&L'!AQ52:AS52) -> -359360.72 | P27: =SUM('P&L'!AT52:AV52) -> -183155.86 | Q27: =SUM('P&L'!AW52:AY52) -> 156177.38 | R27: =SUM('P&L'!AZ52:BB52) -> 538160.23 | S27: =SUM('P&L'!BC52:BE52) -> 970030.36 | T27: =SUM('P&L'!BF52:BH52) -> 1434620.2 | U27: =SUM('P&L'!BI52:BK52) -> 2703597.2 | V27: =SUM('P&L'!BL52:BN52) -> 3690305.2 | W27: =SUM('P&L'!BO52:BQ52) -> 4822370.6 | X27: =SUM('P&L'!BR52:BT52) -> 6151069.9
C28: Equity Investment (+) | E28: =SUM('P&L'!M53:O53) -> 500000 | F28: =SUM('P&L'!P53:R53) -> 0 | G28: =SUM('P&L'!S53:U53) -> 0 | H28: =SUM('P&L'!V53:X53) -> 2500000 | I28: =SUM('P&L'!Y53:AA53) -> 0 | J28: =SUM('P&L'!AB53:AD53) -> 0 | K28: =SUM('P&L'!AE53:AG53) -> 0 | L28: =SUM('P&L'!AH53:AJ53) -> 9000000 | M28: =SUM('P&L'!AK53:AM53) -> 0 | N28: =SUM('P&L'!AN53:AP53) -> 0 | O28: =SUM('P&L'!AQ53:AS53) -> 0 | P28: =SUM('P&L'!AT53:AV53) -> 0 | Q28: =SUM('P&L'!AW53:AY53) -> 0 | R28: =SUM('P&L'!AZ53:BB53) -> 0 | S28: =SUM('P&L'!BC53:BE53) -> 0 | T28: =SUM('P&L'!BF53:BH53) -> 0 | U28: =SUM('P&L'!BI53:BK53) -> 0 | V28: =SUM('P&L'!BL53:BN53) -> 0 | W28: =SUM('P&L'!BO53:BQ53) -> 0 | X28: =SUM('P&L'!BR53:BT53) -> 0
C29: Change in A/R (+/-) | E29: =SUM('P&L'!M54:O54) -> 0 | F29: =SUM('P&L'!P54:R54) -> 0 | G29: =SUM('P&L'!S54:U54) -> -328 | H29: =SUM('P&L'!V54:X54) -> -181 | I29: =SUM('P&L'!Y54:AA54) -> -3116.6 | J29: =SUM('P&L'!AB54:AD54) -> -797.6 | K29: =SUM('P&L'!AE54:AG54) -> -1386.85 | L29: =SUM('P&L'!AH54:AJ54) -> -1261.7 | M29: =SUM('P&L'!AK54:AM54) -> -6907.25 | N29: =SUM('P&L'!AN54:AP54) -> -4023.1 | O29: =SUM('P&L'!AQ54:AS54) -> -4027 | P29: =SUM('P&L'!AT54:AV54) -> -5386.8 | Q29: =SUM('P&L'!AW54:AY54) -> -16963 | R29: =SUM('P&L'!AZ54:BB54) -> -9827.2 | S29: =SUM('P&L'!BC54:BE54) -> -13334.3 | T29: =SUM('P&L'!BF54:BH54) -> -14667.1 | U29: =SUM('P&L'!BI54:BK54) -> -38411.7 | V29: =SUM('P&L'!BL54:BN54) -> -26957.8 | W29: =SUM('P&L'!BO54:BQ54) -> -31066.6 | X29: =SUM('P&L'!BR54:BT54) -> -36696.1
C30: Capital Expenditures (-) | E30: =SUM('P&L'!M55:O55) -> -28000 | F30: =SUM('P&L'!P55:R55) -> 0 | G30: =SUM('P&L'!S55:U55) -> 0 | H30: =SUM('P&L'!V55:X55) -> 0 | I30: =SUM('P&L'!Y55:AA55) -> -15000 | J30: =SUM('P&L'!AB55:AD55) -> 0 | K30: =SUM('P&L'!AE55:AG55) -> 0 | L30: =SUM('P&L'!AH55:AJ55) -> 0 | M30: =SUM('P&L'!AK55:AM55) -> -24000 | N30: =SUM('P&L'!AN55:AP55) -> 0 | O30: =SUM('P&L'!AQ55:AS55) -> 0 | P30: =SUM('P&L'!AT55:AV55) -> 0 | Q30: =SUM('P&L'!AW55:AY55) -> -21000 | R30: =SUM('P&L'!AZ55:BB55) -> 0 | S30: =SUM('P&L'!BC55:BE55) -> 0 | T30: =SUM('P&L'!BF55:BH55) -> 0 | U30: =SUM('P&L'!BI55:BK55) -> 0 | V30: =SUM('P&L'!BL55:BN55) -> 0 | W30: =SUM('P&L'!BO55:BQ55) -> 0 | X30: =SUM('P&L'!BR55:BT55) -> 0
C31: Borrowings (+) | E31: =SUM('P&L'!M56:O56) -> 250000 | F31: =SUM('P&L'!P56:R56) -> 0 | G31: =SUM('P&L'!S56:U56) -> 0 | H31: =SUM('P&L'!V56:X56) -> 0 | I31: =SUM('P&L'!Y56:AA56) -> 0 | J31: =SUM('P&L'!AB56:AD56) -> 0 | K31: =SUM('P&L'!AE56:AG56) -> 0 | L31: =SUM('P&L'!AH56:AJ56) -> 0 | M31: =SUM('P&L'!AK56:AM56) -> 0 | N31: =SUM('P&L'!AN56:AP56) -> 0 | O31: =SUM('P&L'!AQ56:AS56) -> 0 | P31: =SUM('P&L'!AT56:AV56) -> 0 | Q31: =SUM('P&L'!AW56:AY56) -> 0 | R31: =SUM('P&L'!AZ56:BB56) -> 0 | S31: =SUM('P&L'!BC56:BE56) -> 0 | T31: =SUM('P&L'!BF56:BH56) -> 0 | U31: =SUM('P&L'!BI56:BK56) -> 0 | V31: =SUM('P&L'!BL56:BN56) -> 0 | W31: =SUM('P&L'!BO56:BQ56) -> 0 | X31: =SUM('P&L'!BR56:BT56) -> 0
C32: COGS (Related to Inventory) (+) | E32: =SUM('P&L'!M57:O57) -> 0 | F32: =SUM('P&L'!P57:R57) -> 0 | G32: =SUM('P&L'!S57:U57) -> 0 | H32: =SUM('P&L'!V57:X57) -> 0 | I32: =SUM('P&L'!Y57:AA57) -> 0 | J32: =SUM('P&L'!AB57:AD57) -> 0 | K32: =SUM('P&L'!AE57:AG57) -> 0 | L32: =SUM('P&L'!AH57:AJ57) -> 0 | M32: =SUM('P&L'!AK57:AM57) -> 0 | N32: =SUM('P&L'!AN57:AP57) -> 0 | O32: =SUM('P&L'!AQ57:AS57) -> 0 | P32: =SUM('P&L'!AT57:AV57) -> 0 | Q32: =SUM('P&L'!AW57:AY57) -> 0 | R32: =SUM('P&L'!AZ57:BB57) -> 0 | S32: =SUM('P&L'!BC57:BE57) -> 0 | T32: =SUM('P&L'!BF57:BH57) -> 0 | U32: =SUM('P&L'!BI57:BK57) -> 0 | V32: =SUM('P&L'!BL57:BN57) -> 0 | W32: =SUM('P&L'!BO57:BQ57) -> 0 | X32: =SUM('P&L'!BR57:BT57) -> 0
C33: Depreciation (+) | E33: =SUM('P&L'!M58:O58) -> 1400 | F33: =SUM('P&L'!P58:R58) -> 1400 | G33: =SUM('P&L'!S58:U58) -> 1400 | H33: =SUM('P&L'!V58:X58) -> 1400 | I33: =SUM('P&L'!Y58:AA58) -> 2150 | J33: =SUM('P&L'!AB58:AD58) -> 2150 | K33: =SUM('P&L'!AE58:AG58) -> 2150 | L33: =SUM('P&L'!AH58:AJ58) -> 2150 | M33: =SUM('P&L'!AK58:AM58) -> 3350 | N33: =SUM('P&L'!AN58:AP58) -> 3350 | O33: =SUM('P&L'!AQ58:AS58) -> 3350 | P33: =SUM('P&L'!AT58:AV58) -> 3350 | Q33: =SUM('P&L'!AW58:AY58) -> 4400 | R33: =SUM('P&L'!AZ58:BB58) -> 4400 | S33: =SUM('P&L'!BC58:BE58) -> 4400 | T33: =SUM('P&L'!BF58:BH58) -> 4400 | U33: =SUM('P&L'!BI58:BK58) -> 4400 | V33: =SUM('P&L'!BL58:BN58) -> 4400 | W33: =SUM('P&L'!BO58:BQ58) -> 4400 | X33: =SUM('P&L'!BR58:BT58) -> 4400
C34: Repayment of Principal (-) | E34: =SUM('P&L'!M59:O59) -> -10275.496 | F34: =SUM('P&L'!P59:R59) -> -10482.379 | G34: =SUM('P&L'!S59:U59) -> -10693.427 | H34: =SUM('P&L'!V59:X59) -> -10908.724 | I34: =SUM('P&L'!Y59:AA59) -> -11128.357 | J34: =SUM('P&L'!AB59:AD59) -> -11352.411 | K34: =SUM('P&L'!AE59:AG59) -> -11580.976 | L34: =SUM('P&L'!AH59:AJ59) -> -11814.143 | M34: =SUM('P&L'!AK59:AM59) -> -12052.005 | N34: =SUM('P&L'!AN59:AP59) -> -12294.655 | O34: =SUM('P&L'!AQ59:AS59) -> -12542.191 | P34: =SUM('P&L'!AT59:AV59) -> -12794.711 | Q34: =SUM('P&L'!AW59:AY59) -> -13052.315 | R34: =SUM('P&L'!AZ59:BB59) -> -13315.106 | S34: =SUM('P&L'!BC59:BE59) -> -13583.187 | T34: =SUM('P&L'!BF59:BH59) -> -13856.666 | U34: =SUM('P&L'!BI59:BK59) -> -14135.651 | V34: =SUM('P&L'!BL59:BN59) -> -14420.253 | W34: =SUM('P&L'!BO59:BQ59) -> -14710.585 | X34: =SUM('P&L'!BR59:BT59) -> -15006.762
C35: deffered exp | E35: =SUM('P&L'!M60:O60) -> 86250 | F35: =SUM('P&L'!P60:R60) -> 86250 | G35: =SUM('P&L'!S60:U60) -> 86250 | H35: =SUM('P&L'!V60:X60) -> 86250 | I35: =SUM('P&L'!Y60:AA60) -> 86250 | J35: =SUM('P&L'!AB60:AD60) -> 86250 | K35: =SUM('P&L'!AE60:AG60) -> 57500 | L35: =SUM('P&L'!AH60:AJ60) -> 0 | M35: =SUM('P&L'!AK60:AM60) -> 0 | N35: =SUM('P&L'!AN60:AP60) -> 0 | O35: =SUM('P&L'!AQ60:AS60) -> 0 | P35: =SUM('P&L'!AT60:AV60) -> 0 | Q35: =SUM('P&L'!AW60:AY60) -> 0 | R35: =SUM('P&L'!AZ60:BB60) -> 0 | S35: =SUM('P&L'!BC60:BE60) -> 0 | T35: =SUM('P&L'!BF60:BH60) -> 0 | U35: =SUM('P&L'!BI60:BK60) -> 0 | V35: =SUM('P&L'!BL60:BN60) -> 0 | W35: =SUM('P&L'!BO60:BQ60) -> 0 | X35: =SUM('P&L'!BR60:BT60) -> 0
C36: Ending Cash | E36: =SUM(E26:E35) -> 407517.7 | F36: =SUM(F26:F35) -> 33968.742 | G36: =SUM(G26:G35) -> -361361.39 | H36: =SUM(H26:H35) -> 1738833 | I36: =SUM(I26:I35) -> 1207295.3 | J36: =SUM(J26:J35) -> 559631.57 | K36: =SUM(K26:K35) -> -132139.9 | L36: =SUM(L26:L35) -> 8166599.6 | ... X36: =SUM(X26:X35) -> 26735190
B39: Cash Collections Method
C40: Beginning Cash | E40: 0 | F40: =E50 -> 407517.7 | G40: =F50 -> 33968.742 | H40: =G50 -> -361361.39 | I40: =H50 -> 1738833 | J40: =I50 -> 1207295.3 | K40: =J50 -> 559631.57 | L40: =K50 -> -132139.9 | M40: =L50 -> 8166599.6 | ... X40: =W50 -> 20631423
C41: Cash Collections | E41: =SUM('P&L'!M66:O66) -> 0 | F41: =SUM('P&L'!P66:R66) -> 0 | G41: =SUM('P&L'!S66:U66) -> 13972 | H41: =SUM('P&L'!V66:X66) -> 22369 | I41: =SUM('P&L'!Y66:AA66) -> 160263.4 | J41: =SUM('P&L'!AB66:AD66) -> 212192.4 | K41: =SUM('P&L'!AE66:AG66) -> 268768.15 | L41: =SUM('P&L'!AH66:AJ66) -> 332343.3 | M41: =SUM('P&L'!AK66:AM66) -> 655942.75 | N41: =SUM('P&L'!AN66:AP66) -> 839976.9 | O41: =SUM('P&L'!AQ66:AS66) -> 1037363 | P41: =SUM('P&L'!AT66:AV66) -> 1284083.2 | Q41: =SUM('P&L'!AW66:AY66) -> 2053017 | R41: =SUM('P&L'!AZ66:BB66) -> 2551492.8 | S41: =SUM('P&L'!BC66:BE66) -> 3196685.7 | T41: =SUM('P&L'!BF66:BH66) -> 3882672.9 | U41: =SUM('P&L'!BI66:BK66) -> 5654318.3 | V41: =SUM('P&L'!BL66:BN66) -> 6970462.2 | W41: =SUM('P&L'!BO66:BQ66) -> 8460003.4 | X41: =SUM('P&L'!BR66:BT66) -> 10206584
C42: Capital Expenditures (-) | E42: =SUM('P&L'!M67:O67) -> -28000 | F42: =SUM('P&L'!P67:R67) -> 0 | G42: =SUM('P&L'!S67:U67) -> 0 | H42: =SUM('P&L'!V67:X67) -> 0 | I42: =SUM('P&L'!Y67:AA67) -> -15000 | J42: =SUM('P&L'!AB67:AD67) -> 0 | K42: =SUM('P&L'!AE67:AG67) -> 0 | L42: =SUM('P&L'!AH67:AJ67) -> 0 | M42: =SUM('P&L'!AK67:AM67) -> -24000 | N42: =SUM('P&L'!AN67:AP67) -> 0 | O42: =SUM('P&L'!AQ67:AS67) -> 0 | P42: =SUM('P&L'!AT67:AV67) -> 0 | Q42: =SUM('P&L'!AW67:AY67) -> -21000 | R42: =SUM('P&L'!AZ67:BB67) -> 0 | S42: =SUM('P&L'!BC67:BE67) -> 0 | T42: =SUM('P&L'!BF67:BH67) -> 0 | U42: =SUM('P&L'!BI67:BK67) -> 0 | V42: =SUM('P&L'!BL67:BN67) -> 0 | W42: =SUM('P&L'!BO67:BQ67) -> 0 | X42: =SUM('P&L'!BR67:BT67) -> 0
C43: Equity Investments (+) | E43: =SUM('P&L'!M68:O68) -> 500000 | F43: =SUM('P&L'!P68:R68) -> 0 | G43: =SUM('P&L'!S68:U68) -> 0 | H43: =SUM('P&L'!V68:X68) -> 2500000 | I43: =SUM('P&L'!Y68:AA68) -> 0 | J43: =SUM('P&L'!AB68:AD68) -> 0 | K43: =SUM('P&L'!AE68:AG68) -> 0 | L43: =SUM('P&L'!AH68:AJ68) -> 9000000 | M43: =SUM('P&L'!AK68:AM68) -> 0 | N43: =SUM('P&L'!AN68:AP68) -> 0 | O43: =SUM('P&L'!AQ68:AS68) -> 0 | P43: =SUM('P&L'!AT68:AV68) -> 0 | Q43: =SUM('P&L'!AW68:AY68) -> 0 | R43: =SUM('P&L'!AZ68:BB68) -> 0 | S43: =SUM('P&L'!BC68:BE68) -> 0 | T43: =SUM('P&L'!BF68:BH68) -> 0 | U43: =SUM('P&L'!BI68:BK68) -> 0 | V43: =SUM('P&L'!BL68:BN68) -> 0 | W43: =SUM('P&L'!BO68:BQ68) -> 0 | X43: =SUM('P&L'!BR68:BT68) -> 0
C44: Borrowings (+) | E44: =SUM('P&L'!M69:O69) -> 250000 | F44: =SUM('P&L'!P69:R69) -> 0 | G44: =SUM('P&L'!S69:U69) -> 0 | H44: =SUM('P&L'!V69:X69) -> 0 | I44: =SUM('P&L'!Y69:AA69) -> 0 | J44: =SUM('P&L'!AB69:AD69) -> 0 | K44: =SUM('P&L'!AE69:AG69) -> 0 | L44: =SUM('P&L'!AH69:AJ69) -> 0 | M44: =SUM('P&L'!AK69:AM69) -> 0 | N44: =SUM('P&L'!AN69:AP69) -> 0 | O44: =SUM('P&L'!AQ69:AS69) -> 0 | P44: =SUM('P&L'!AT69:AV69) -> 0 | Q44: =SUM('P&L'!AW69:AY69) -> 0 | R44: =SUM('P&L'!AZ69:BB69) -> 0 | S44: =SUM('P&L'!BC69:BE69) -> 0 | T44: =SUM('P&L'!BF69:BH69) -> 0 | U44: =SUM('P&L'!BI69:BK69) -> 0 | V44: =SUM('P&L'!BL69:BN69) -> 0 | W44: =SUM('P&L'!BO69:BQ69) -> 0 | X44: =SUM('P&L'!BR69:BT69) -> 0
C45: Operating Expenses (-) | E45: =SUM('P&L'!M70:O70) -> -385525 | F45: =SUM('P&L'!P70:R70) -> -443591.67 | G45: =SUM('P&L'!S70:U70) -> -477098.33 | H45: =SUM('P&L'!V70:X70) -> -489628.33 | I45: =SUM('P&L'!Y70:AA70) -> -738751.25 | J45: =SUM('P&L'!AB70:AD70) -> -920471.37 | K45: =SUM('P&L'!AE70:AG70) -> -990952.33 | L45: =SUM('P&L'!AH70:AJ70) -> -1004785.3 | M45: =SUM('P&L'!AK70:AM70) -> -1161149.4 | N45: =SUM('P&L'!AN70:AP70) -> -1262129.9 | O45: =SUM('P&L'!AQ70:AS70) -> -1355811.6 | P45: =SUM('P&L'!AT70:AV70) -> -1420438.3 | Q45: =SUM('P&L'!AW70:AY70) -> -1785771.4 | R45: =SUM('P&L'!AZ70:BB70) -> -1778155 | S45: =SUM('P&L'!BC70:BE70) -> -1861548.6 | T45: =SUM('P&L'!BF70:BH70) -> -1939073.5 | U45: =SUM('P&L'!BI70:BK70) -> -2050359.3 | V45: =SUM('P&L'!BL70:BN70) -> -2059885.3 | W45: =SUM('P&L'!BO70:BQ70) -> -2066981.3 | X45: =SUM('P&L'!BR70:BT70) -> -2075195.9
C46: Cash COGS (-) | E46: =SUM('P&L'!M71:O71) -> 0 | F46: =SUM('P&L'!P71:R71) -> -1000 | G46: =SUM('P&L'!S71:U71) -> -3246.5 | H46: =SUM('P&L'!V71:X71) -> -3589 | I46: =SUM('P&L'!Y71:AA71) -> -9092.5 | J46: =SUM('P&L'!AB71:AD71) -> -10427.5 | K46: =SUM('P&L'!AE71:AG71) -> -11880 | L46: =SUM('P&L'!AH71:AJ71) -> -13611.25 | M46: =SUM('P&L'!AK71:AM71) -> -27027.5 | N46: =SUM('P&L'!AN71:AP71) -> -32567.25 | O46: =SUM('P&L'!AQ71:AS71) -> -38924 | P46: =SUM('P&L'!AT71:AV71) -> -46425 | Q46: =SUM('P&L'!AW71:AY71) -> -82431.875 | R46: =SUM('P&L'!AZ71:BB71) -> -104172.5 | S46: =SUM('P&L'!BC71:BE71) -> -129909.38 | T46: =SUM('P&L'!BF71:BH71) -> -159240.62 | U46: =SUM('P&L'!BI71:BK71) -> -257402.5 | V46: =SUM('P&L'!BL71:BN71) -> -319466.25 | W46: =SUM('P&L'!BO71:BQ71) -> -391228.75 | X46: =SUM('P&L'!BR71:BT71) -> -474646.25
C47: Debt Payments (-) | E47: =SUM('P&L'!M72:O72) -> -15207.296 | F47: =SUM('P&L'!P72:R72) -> -15207.296 | G47: =SUM('P&L'!S72:U72) -> -15207.296 | H47: =SUM('P&L'!V72:X72) -> -15207.296 | I47: =SUM('P&L'!Y72:AA72) -> -15207.296 | J47: =SUM('P&L'!AB72:AD72) -> -15207.296 | K47: =SUM('P&L'!AE72:AG72) -> -15207.296 | L47: =SUM('P&L'!AH72:AJ72) -> -15207.296 | M47: =SUM('P&L'!AK72:AM72) -> -15207.296 | N47: =SUM('P&L'!AN72:AP72) -> -15207.296 | O47: =SUM('P&L'!AQ72:AS72) -> -15207.296 | P47: =SUM('P&L'!AT72:AV72) -> -15207.296 | Q47: =SUM('P&L'!AW72:AY72) -> -15207.296 | R47: =SUM('P&L'!AZ72:BB72) -> -15207.296 | S47: =SUM('P&L'!BC72:BE72) -> -15207.296 | T47: =SUM('P&L'!BF72:BH72) -> -15207.296 | U47: =SUM('P&L'!BI72:BK72) -> -15207.296 | V47: =SUM('P&L'!BL72:BN72) -> -15207.296 | W47: =SUM('P&L'!BO72:BQ72) -> -15207.296 | X47: =SUM('P&L'!BR72:BT72) -> -15207.296
C48: Taxes (-) | E48: =SUM('P&L'!M73:O73) -> 0 | F48: =SUM('P&L'!P73:R73) -> 0 | G48: =SUM('P&L'!S73:U73) -> 0 | H48: =SUM('P&L'!V73:X73) -> 0 | I48: =SUM('P&L'!Y73:AA73) -> 0 | J48: =SUM('P&L'!AB73:AD73) -> 0 | K48: =SUM('P&L'!AE73:AG73) -> 0 | L48: =SUM('P&L'!AH73:AJ73) -> 0 | M48: =SUM('P&L'!AK73:AM73) -> 0 | N48: =SUM('P&L'!AN73:AP73) -> 0 | O48: =SUM('P&L'!AQ73:AS73) -> 0 | P48: =SUM('P&L'!AT73:AV73) -> 0 | Q48: =SUM('P&L'!AW73:AY73) -> -39044.345 | R48: =SUM('P&L'!AZ73:BB73) -> -134540.06 | S48: =SUM('P&L'!BC73:BE73) -> -242507.59 | T48: =SUM('P&L'!BF73:BH73) -> -358655.06 | U48: =SUM('P&L'!BI73:BK73) -> -675899.3 | V48: =SUM('P&L'!BL73:BN73) -> -922576.29 | W48: =SUM('P&L'!BO73:BQ73) -> -1205592.6 | X48: =SUM('P&L'!BR73:BT73) -> -1537767.5
C49: deffered exp | E49: =SUM('P&L'!M74:O74) -> 86250 | F49: =SUM('P&L'!P74:R74) -> 86250 | G49: =SUM('P&L'!S74:U74) -> 86250 | H49: =SUM('P&L'!V74:X74) -> 86250 | I49: =SUM('P&L'!Y74:AA74) -> 86250 | J49: =SUM('P&L'!AB74:AD74) -> 86250 | K49: =SUM('P&L'!AE74:AG74) -> 57500 | L49: =SUM('P&L'!AH74:AJ74) -> 0 | M49: =SUM('P&L'!AK74:AM74) -> 0 | N49: =SUM('P&L'!AN74:AP74) -> 0 | O49: =SUM('P&L'!AQ74:AS74) -> 0 | P49: =SUM('P&L'!AT74:AV74) -> 0 | Q49: =SUM('P&L'!AW74:AY74) -> 0 | R49: =SUM('P&L'!AZ74:BB74) -> 0 | S49: =SUM('P&L'!BC74:BE74) -> 0 | T49: =SUM('P&L'!BF74:BH74) -> 0 | U49: =SUM('P&L'!BI74:BK74) -> 0 | V49: =SUM('P&L'!BL74:BN74) -> 0 | W49: =SUM('P&L'!BO74:BQ74) -> 0 | X49: =SUM('P&L'!BR74:BT74) -> 0
C50: Ending Cash | E50: =SUM(E40:E49) -> 407517.7 | F50: =SUM(F40:F49) -> 33968.742 | G50: =SUM(G40:G49) -> -361361.39 | H50: =SUM(H40:H49) -> 1738833 | I50: =SUM(I40:I49) -> 1207295.3 | J50: =SUM(J40:J49) -> 559631.57 | K50: =SUM(K40:K49) -> -132139.9 | L50: =SUM(L40:L49) -> 8166599.6 | ... X50: =SUM(X40:X49) -> 26735190
D52: Check | E52: =E36-E50 -> 0 | F52: =F36-F50 -> 0 | G52: =G36-G50 -> 0 | H52: =H36-H50 -> 0 | I52: =I36-I50 -> 0 | J52: =J36-J50 -> 0 | K52: =K36-K50 -> 0 | L52: =L36-L50 -> 0 | ... X52: =X36-X50 -> 0
D53: Change in CF | E53: =E36-E26 -> 407517.7 | F53: =F36-F26 -> -373548.96 | G53: =G36-G26 -> -395330.13 | H53: =H36-H26 -> 2100194.4 | I53: =I36-I26 -> -531537.65 | J53: =J36-J26 -> -647663.77 | K53: =K36-K26 -> -691771.47 | L53: =L36-L26 -> 8298739.5 | ... X53: =X36-X26 -> 6103767
B55: Yearly P & L | D55: Year | E55: Year 1 | F55: Year 2 | G55: Year 3 | H55: Year 4 | I55: Year 5
D57: Total Revenue | E57: =SUM(E5:H5) -> 36850 | F57: =SUM(I5:L5) -> 980130 | G57: =SUM(M5:P5) -> 3837710 | H57: =SUM(Q5:T5) -> 11738660 | I57: =SUM(U5:X5) -> 31424500
D58: COGS | E58: =SUM(E6:H6) -> 7835.5 | F58: =SUM(I6:L6) -> 45011.25 | G58: =SUM(M6:P6) -> 144943.75 | H58: =SUM(Q6:T6) -> 475754.38 | I58: =SUM(U6:X6) -> 1442743.8
D59: Gross Profit | E59: =SUM(E7:H7) -> 29014.5 | F59: =SUM(I7:L7) -> 935118.75 | G59: =SUM(M7:P7) -> 3692766.2 | H59: =SUM(Q7:T7) -> 11262906 | I59: =SUM(U7:X7) -> 29981756
C60: Operating Expenses
D61: {=D9:D13} -> R&D | E61: =SUM(E9:H9) -> 430466.67 | F61: =SUM(I9:L9) -> 1211433.3 | G61: =SUM(M9:P9) -> 2148242.5 | H61: =SUM(Q9:T9) -> 3470999.6 | I61: =SUM(U9:X9) -> 4178539.1
D62: Marketing | E62: =SUM(E10:H10) -> 153000 | F62: =SUM(I10:L10) -> 270300 | G62: =SUM(M10:P10) -> 341800 | H62: =SUM(Q10:T10) -> 405300 | I62: =SUM(U10:X10) -> 463800
D63: G&A | E63: =SUM(E11:H11) -> 1206376.7 | F63: =SUM(I11:L11) -> 1898018.3 | G63: =SUM(M11:P11) -> 2304640 | H63: =SUM(Q11:T11) -> 2827540 | I63: =SUM(U11:X11) -> 2730540
D64: Sales | E64: =SUM(E12:H12) -> 6000 | F64: =SUM(I12:L12) -> 275208.56 | G64: =SUM(M12:P12) -> 404846.63 | H64: =SUM(Q12:T12) -> 660708.84 | I64: =SUM(U12:X12) -> 879542.69
D65: Total Operating Expense | E65: =SUM(E13:H13) -> 1794343.3 | F65: =SUM(I13:L13) -> 3654960.2 | G65: =SUM(M13:P13) -> 5199529.1 | H65: =SUM(Q13:T13) -> 7364548.5 | I65: =SUM(U13:X13) -> 8252421.8
C66: Operating Income | E66: =SUM(E14:H14) -> -1765328.8 | F66: =SUM(I14:L14) -> -2719841.5 | G66: =SUM(M14:P14) -> -1506762.9 | H66: =SUM(Q14:T14) -> 3898357.2 | I66: =SUM(U14:X14) -> 21729334
C68: Depreciation | E68: =SUM(E16:H16) -> 5600 | F68: =SUM(I16:L16) -> 8600 | G68: =SUM(M16:P16) -> 13400 | H68: =SUM(Q16:T16) -> 17600 | I68: =SUM(U16:X16) -> 17600
C69: Interest Exp | E69: =SUM(E17:H17) -> 18469.157 | F69: =SUM(I17:L17) -> 14953.296 | G69: =SUM(M17:P17) -> 11145.62 | H69: =SUM(Q17:T17) -> 7021.9089 | I69: =SUM(U17:X17) -> 2555.9318
C70: Pre tax income | E70: =SUM(E18:H18) -> -1790898 | F70: =SUM(I18:L18) -> -2743394.8 | G70: =SUM(M18:P18) -> -1531308.5 | H70: =SUM(Q18:T18) -> 3873735.2 | I70: =SUM(U18:X18) -> 21709179
C71: Taxes @20% | E71: =SUM(E19:H19) -> 0 | F71: =SUM(I19:L19) -> 0 | G71: =SUM(M19:P19) -> 0 | H71: =SUM(Q19:T19) -> 774747.05 | I71: =SUM(U19:X19) -> 4341835.7
C72: Net Income | E72: =SUM(E20:H20) -> -1790898 | F72: =SUM(I20:L20) -> -2743394.8 | G72: =SUM(M20:P20) -> -1531308.5 | H72: =SUM(Q20:T20) -> 3098988.2 | I72: =SUM(U20:X20) -> 17367343
C73: Retained Earnings | E73: =E72+D73 -> -1790898 | F73: =F72+E73 -> -4534292.8 | G73: =G72+F73 -> -6065601.3 | H73: =H72+G73 -> -2966613.1 | I73: =I72+H73 -> 14400730
B78: Yearly Cash Flow
B80: Net Income Method
C81: Beginning Cash | E81: 0 | F81: =E91 -> 1738833 | G81: =F91 -> 8166599.6 | H81: =G91 -> 6554663.4 | I81: =H91 -> 9541652.7
C82: Net Income | E82: =SUM(E27:H27) -> -1790898 | F82: =SUM(I27:L27) -> -2743394.8 | G82: =SUM(M27:P27) -> -1531308.5 | H82: =SUM(Q27:T27) -> 3098988.2 | I82: =SUM(U27:X27) -> 17367343
C83: Equity Investment (+) | E83: =SUM(E28:H28) -> 3000000 | F83: =SUM(I28:L28) -> 9000000 | G83: =SUM(M28:P28) -> 0 | H83: =SUM(Q28:T28) -> 0 | I83: =SUM(U28:X28) -> 0
C84: Change in A/R (+/-) | E84: =SUM(E29:H29) -> -509 | F84: =SUM(I29:L29) -> -6562.75 | G84: =SUM(M29:P29) -> -20344.15 | H84: =SUM(Q29:T29) -> -54791.6 | I84: =SUM(U29:X29) -> -133132.2
C85: Capital Expenditures (-) | E85: =SUM(E30:H30) -> -28000 | F85: =SUM(I30:L30) -> -15000 | G85: =SUM(M30:P30) -> -24000 | H85: =SUM(Q30:T30) -> -21000 | I85: =SUM(U30:X30) -> 0
C86: Borrowings (+) | E86: =SUM(E31:H31) -> 250000 | F86: =SUM(I31:L31) -> 0 | G86: =SUM(M31:P31) -> 0 | H86: =SUM(Q31:T31) -> 0 | I86: =SUM(U31:X31) -> 0
C87: COGS (Related to Inventory) (+) | E87: =SUM(E32:H32) -> 0 | F87: =SUM(I32:L32) -> 0 | G87: =SUM(M32:P32) -> 0 | H87: =SUM(Q32:T32) -> 0 | I87: =SUM(U32:X32) -> 0
C88: Depreciation (+) | E88: =SUM(E33:H33) -> 5600 | F88: =SUM(I33:L33) -> 8600 | G88: =SUM(M33:P33) -> 13400 | H88: =SUM(Q33:T33) -> 17600 | I88: =SUM(U33:X33) -> 17600
C89: Repayment of Principal (-) | E89: =SUM(E34:H34) -> -42360.026 | F89: =SUM(I34:L34) -> -45875.887 | G89: =SUM(M34:P34) -> -49683.563 | H89: =SUM(Q34:T34) -> -53807.274 | I89: =SUM(U34:X34) -> -58273.251
C90: deffered exp | E90: =SUM(E35:H35) -> 345000 | F90: =SUM(I35:L35) -> 230000 | G90: =SUM(M35:P35) -> 0 | H90: =SUM(Q35:T35) -> 0 | I90: =SUM(U35:X35) -> 0
C91: Ending Cash | E91: =SUM(E81:E90) -> 1738833 | F91: =SUM(F81:F90) -> 8166599.6 | G91: =SUM(G81:G90) -> 6554663.4 | H91: =SUM(H81:H90) -> 9541652.7 | I91: =SUM(I81:I90) -> 26735190
B94: Cash Collections Method
C95: Beginning Cash | E95: 0 | F95: =E105 -> 1738833 | G95: =F105 -> 8166599.6 | H95: =G105 -> 6554663.4 | I95: =H105 -> 9541652.7
C96: Cash Collections | E96: =SUM(E41:H41) -> 36341 | F96: =SUM(I41:L41) -> 973567.25 | G96: =SUM(M41:P41) -> 3817365.9 | H96: =SUM(Q41:T41) -> 11683868 | I96: =SUM(U41:X41) -> 31291368
C97: Capital Expenditures (-) | E97: =SUM(E42:H42) -> -28000 | F97: =SUM(I42:L42) -> -15000 | G97: =SUM(M42:P42) -> -24000 | H97: =SUM(Q42:T42) -> -21000 | I97: =SUM(U42:X42) -> 0
C98: Equity Investments (+) | E98: =SUM(E43:H43) -> 3000000 | F98: =SUM(I43:L43) -> 9000000 | G98: =SUM(M43:P43) -> 0 | H98: =SUM(Q43:T43) -> 0 | I98: =SUM(U43:X43) -> 0
C99: Borrowings (+) | E99: =SUM(E44:H44) -> 250000 | F99: =SUM(I44:L44) -> 0 | G99: =SUM(M44:P44) -> 0 | H99: =SUM(Q44:T44) -> 0 | I99: =SUM(U44:X44) -> 0
C100: Operating Expenses (-) | E100: =SUM(E45:H45) -> -1795843.3 | F100: =SUM(I45:L45) -> -3654960.2 | G100: =SUM(M45:P45) -> -5199529.1 | H100: =SUM(Q45:T45) -> -7364548.5 | I100: =SUM(U45:X45) -> -8252421.8
C101: Cash COGS (-) | E101: =SUM(E46:H46) -> -7835.5 | F101: =SUM(I46:L46) -> -45011.25 | G101: =SUM(M46:P46) -> -144943.75 | H101: =SUM(Q46:T46) -> -475754.38 | I101: =SUM(U46:X46) -> -1442743.8
C102: Debt Payments (-) | E102: =SUM(E47:H47) -> -60829.183 | F102: =SUM(I47:L47) -> -60829.183 | G102: =SUM(M47:P47) -> -60829.183 | H102: =SUM(Q47:T47) -> -60829.183 | I102: =SUM(U47:X47) -> -60829.183
C103: Taxes (-) | E103: =SUM(E48:H48) -> 0 | F103: =SUM(I48:L48) -> 0 | G103: =SUM(M48:P48) -> 0 | H103: =SUM(Q48:T48) -> -774747.05 | I103: =SUM(U48:X48) -> -4341835.7
C104: deffered exp | E104: =SUM(E49:H49) -> 345000 | F104: =SUM(I49:L49) -> 230000 | G104: =SUM(M49:P49) -> 0 | H104: =SUM(Q49:T49) -> 0 | I104: =SUM(U49:X49) -> 0
C105: Ending Cash | E105: =SUM(E95:E104) -> 1738833 | F105: =SUM(F95:F104) -> 8166599.6 | G105: =SUM(G95:G104) -> 6554663.4 | H105: =SUM(H95:H104) -> 9541652.7 | I105: =SUM(I95:I104) -> 26735190
D107: Check | E107: =E91-E105 -> 0 | F107: =F91-F105 -> 0 | G107: =G91-G105 -> 0 | H107: =H91-H105 -> 0 | I107: =I91-I105 -> 0
D108: Yearly Change in CF | E108: =E91-E81 -> 1738833 | F108: =F91-F81 -> 6427766.6 | G108: =G91-G81 -> -1611936.2 | H108: =H91-H81 -> 2986989.3 | I108: =I91-I81 -> 17193537

Sheet P&L
A1: P&L
D2: Cost per user | M2: Year 1 | N2: Year 1 | O2: Year 1 | P2: Year 1 | Q2: Year 1 | R2: Year 1 | S2: Year 1 | T2: Year 1 | U2: Year 1 | V2: Year 1 | W2: Year 1 | X2: Year 1 | Y2: Year 2 | Z2: Year 2 | AA2: Year 2 | AB2: Year 2 | AC2: Year 2 | AD2: Year 2 | AE2: Year 2 | AF2: Year 2 | AG2: Year 2 | AH2: Year 2 | AI2: Year 2 | AJ2: Year 2 | AK2: Year 3 | AL2: Year 3 | AM2: Year 3 | AN2: Year 3 | AO2: Year 3 | AP2: Year 3 | AQ2: Year 3 | AR2: Year 3 | AS2: Year 3 | AT2: Year 3 | AU2: Year 3 | AV2: Year 3 | AW2: Year 4 | AX2: Year 4 | AY2: Year 4 | AZ2: Year 4 | BA2: Year 4 | BB2: Year 4 | BC2: Year 4 | BD2: Year 4 | BE2: Year 4 | BF2: Year 4 | BG2: Year 4 | BH2: Year 4 | BI2: Year 5 | BJ2: Year 5 | BK2: Year 5 | BL2: Year 5 | BM2: Year 5 | BN2: Year 5 | BO2: Year 5 | BP2: Year 5 | BQ2: Year 5 | BR2: Year 5 | BS2: Year 5 | BT2: Year 5
C3: multiplier rate | D3: 1 | E3: 2 | F3: 3 | G3: 4 | H3: 5 | M3: Jan | N3: Feb | O3: Mar | P3: Apr | Q3: May | R3: Jun | S3: Jul | T3: Aug | U3: Sep | V3: Oct | W3: Nov | X3: Dec | Y3: Jan | Z3: Feb | AA3: Mar | AB3: Apr | AC3: May | AD3: Jun | AE3: Jul | AF3: Aug | AG3: Sep | AH3: Oct | AI3: Nov | AJ3: Dec | AK3: Jan | AL3: Feb | AM3: Mar | AN3: Apr | AO3: May | AP3: Jun | AQ3: Jul | AR3: Aug | AS3: Sep | AT3: Oct | AU3: Nov | AV3: Dec | AW3: Jan | AX3: Feb | AY3: Mar | AZ3: Apr | BA3: May | BB3: Jun | BC3: Jul | BD3: Aug | BE3: Sep | BF3: Oct | BG3: Nov | BH3: Dec | BI3: Jan | BJ3: Feb | BK3: Mar | BL3: Apr | BM3: May | BN3: Jun | BO3: Jul | BP3: Aug | BQ3: Sep | BR3: Oct | BS3: Nov | BT3: Dec
B6: Small Cap | C6: 1 | D6: 5.5 | E6: 7.5 | F6: 9.5 | G6: 12.5 | H6: 15
B7: Mid Cap | C7: 1.5 | D7: =$C7*D6 -> 8.25 | E7: =$C7*E6 -> 11.25 | F7: =$C7*F6 -> 14.25 | G7: =$C7*G6 -> 18.75 | H7: =$C7*H6 -> 22.5
B8: Large Cap | C8: 2.5 | D8: =$C8*D7 -> 20.625 | E8: =$C8*E7 -> 28.125 | F8: =$C8*F7 -> 35.625 | G8: =$C8*G7 -> 46.875 | H8: =$C8*H7 -> 56.25
J9: Total Revenue | M9: =Rev!M77 -> 0 | N9: =Rev!N77 -> 0 | O9: =Rev!O77 -> 0 | P9: =Rev!P77 -> 0 | Q9: =Rev!Q77 -> 0 | R9: =Rev!R77 -> 0 | S9: =Rev!S77 -> 3900 | T9: =Rev!T77 -> 4800 | ... BT9: =Rev!BT77 -> 3624740
B10: Small Cap | C10: 1 | D10: 10 | E10: 12.5 | F10: 15 | G10: 20 | H10: 25
B11: Mid Cap | C11: 1.5 | D11: =$C11*D10 -> 15 | E11: =$C11*E10 -> 18.75 | F11: =$C11*F10 -> 22.5 | G11: =$C11*G10 -> 30 | H11: =$C11*H10 -> 37.5 | I11: COGS
B12: Large Cap | C12: 2.5 | D12: =$C12*D11 -> 37.5 | E12: =$C12*E11 -> 46.875 | F12: =$C12*F11 -> 56.25 | G12: =$C12*G11 -> 75 | H12: =$C12*H11 -> 93.75
B14: Fixed compute cost | D14: 1000 | E14: 2500 | F14: 5000 | G14: 7500 | H14: =150000/12 -> 12500 | R14: =_xlfn.XLOOKUP(_xlfn.NUMBERVALUE(RIGHT(R$2,1)),$D$3:$H$3,$D$14:$H$14) -> 1000 | S14: =_xlfn.XLOOKUP(_xlfn.NUMBERVALUE(RIGHT(S$2,1)),$D$3:$H$3,$D$14:$H$14) -> 1000 | T14: =_xlfn.XLOOKUP(_xlfn.NUMBERVALUE(RIGHT(T$2,1)),$D$3:$H$3,$D$14:$H$14) -> 1000 | U14: =_xlfn.XLOOKUP(_xlfn.NUMBERVALUE(RIGHT(U$2,1)),$D$3:$H$3,$D$14:$H$14) -> 1000 | V14: =_xlfn.XLOOKUP(_xlfn.NUMBERVALUE(RIGHT(V$2,1)),$D$3:$H$3,$D$14:$H$14) -> 1000 | W14: =_xlfn.XLOOKUP(_xlfn.NUMBERVALUE(RIGHT(W$2,1)),$D$3:$H$3,$D$14:$H$14) -> 1000 | X14: =_xlfn.XLOOKUP(_xlfn.NUMBERVALUE(RIGHT(X$2,1)),$D$3:$H$3,$D$14:$H$14) -> 1000 | Y14: =_xlfn.XLOOKUP(_xlfn.NUMBERVALUE(RIGHT(Y$2,1)),$D$3:$H$3,$D$14:$H$14) -> 2500 | ... BT14: =_xlfn.XLOOKUP(_xlfn.NUMBERVALUE(RIGHT(BT$2,1)),$D$3:$H$3,$D$14:$H$14) -> 12500
I15: Cloud Hosting | J15: Basic | M15: =(Rev!M57*_xlfn.XLOOKUP(_xlfn.NUMBERVALUE(RIGHT(M$2,1)),$D$3:$H$3,$D$6:$H$6)) -> 0 | N15: =(Rev!N57*_xlfn.XLOOKUP(_xlfn.NUMBERVALUE(RIGHT(N$2,1)),$D$3:$H$3,$D$6:$H$6)) -> 0 | O15: =(Rev!O57*_xlfn.XLOOKUP(_xlfn.NUMBERVALUE(RIGHT(O$2,1)),$D$3:$H$3,$D$6:$H$6)) -> 0 | P15: =(Rev!P57*_xlfn.XLOOKUP(_xlfn.NUMBERVALUE(RIGHT(P$2,1)),$D$3:$H$3,$D$6:$H$6)) -> 0 | Q15: =(Rev!Q57*_xlfn.XLOOKUP(_xlfn.NUMBERVALUE(RIGHT(Q$2,1)),$D$3:$H$3,$D$6:$H$6)) -> 0 | R15: =(Rev!R57*_xlfn.XLOOKUP(_xlfn.NUMBERVALUE(RIGHT(R$2,1)),$D$3:$H$3,$D$6:$H$6)) -> 0 | S15: =(Rev!S57*_xlfn.XLOOKUP(_xlfn.NUMBERVALUE(RIGHT(S$2,1)),$D$3:$H$3,$D$6:$H$6)) -> 22 | T15: =(Rev!T57*_xlfn.XLOOKUP(_xlfn.NUMBERVALUE(RIGHT(T$2,1)),$D$3:$H$3,$D$6:$H$6)) -> 44 | ... BT15: =(Rev!BT57*_xlfn.XLOOKUP(_xlfn.NUMBERVALUE(RIGHT(BT$2,1)),$D$3:$H$3,$D$6:$H$6)) -> 3945
M16: =(Rev!M58*_xlfn.XLOOKUP(_xlfn.NUMBERVALUE(RIGHT(M$2,1)),$D$3:$H$3,$D$7:$H$7)) -> 0 | N16: =(Rev!N58*_xlfn.XLOOKUP(_xlfn.NUMBERVALUE(RIGHT(N$2,1)),$D$3:$H$3,$D$7:$H$7)) -> 0 | O16: =(Rev!O58*_xlfn.XLOOKUP(_xlfn.NUMBERVALUE(RIGHT(O$2,1)),$D$3:$H$3,$D$7:$H$7)) -> 0 | P16: =(Rev!P58*_xlfn.XLOOKUP(_xlfn.NUMBERVALUE(RIGHT(P$2,1)),$D$3:$H$3,$D$7:$H$7)) -> 0 | Q16: =(Rev!Q58*_xlfn.XLOOKUP(_xlfn.NUMBERVALUE(RIGHT(Q$2,1)),$D$3:$H$3,$D$7:$H$7)) -> 0 | R16: =(Rev!R58*_xlfn.XLOOKUP(_xlfn.NUMBERVALUE(RIGHT(R$2,1)),$D$3:$H$3,$D$7:$H$7)) -> 0 | S16: =(Rev!S58*_xlfn.XLOOKUP(_xlfn.NUMBERVALUE(RIGHT(S$2,1)),$D$3:$H$3,$D$7:$H$7)) -> 0 | T16: =(Rev!T58*_xlfn.XLOOKUP(_xlfn.NUMBERVALUE(RIGHT(T$2,1)),$D$3:$H$3,$D$7:$H$7)) -> 0 | ... BT16: =(Rev!BT58*_xlfn.XLOOKUP(_xlfn.NUMBERVALUE(RIGHT(BT$2,1)),$D$3:$H$3,$D$7:$H$7)) -> 16312.5
M17: =(Rev!M59*_xlfn.XLOOKUP(_xlfn.NUMBERVALUE(RIGHT(M$2,1)),$D$3:$H$3,$D$8:$H$8)) -> 0 | N17: =(Rev!N59*_xlfn.XLOOKUP(_xlfn.NUMBERVALUE(RIGHT(N$2,1)),$D$3:$H$3,$D$8:$H$8)) -> 0 | O17: =(Rev!O59*_xlfn.XLOOKUP(_xlfn.NUMBERVALUE(RIGHT(O$2,1)),$D$3:$H$3,$D$8:$H$8)) -> 0 | P17: =(Rev!P59*_xlfn.XLOOKUP(_xlfn.NUMBERVALUE(RIGHT(P$2,1)),$D$3:$H$3,$D$8:$H$8)) -> 0 | Q17: =(Rev!Q59*_xlfn.XLOOKUP(_xlfn.NUMBERVALUE(RIGHT(Q$2,1)),$D$3:$H$3,$D$8:$H$8)) -> 0 | R17: =(Rev!R59*_xlfn.XLOOKUP(_xlfn.NUMBERVALUE(RIGHT(R$2,1)),$D$3:$H$3,$D$8:$H$8)) -> 0 | S17: =(Rev!S59*_xlfn.XLOOKUP(_xlfn.NUMBERVALUE(RIGHT(S$2,1)),$D$3:$H$3,$D$8:$H$8)) -> 0 | T17: =(Rev!T59*_xlfn.XLOOKUP(_xlfn.NUMBERVALUE(RIGHT(T$2,1)),$D$3:$H$3,$D$8:$H$8)) -> 0 | ... BT17: =(Rev!BT59*_xlfn.XLOOKUP(_xlfn.NUMBERVALUE(RIGHT(BT$2,1)),$D$3:$H$3,$D$8:$H$8)) -> 42918.75
J19: Premium | M19: =(Rev!M61*_xlfn.XLOOKUP(_xlfn.NUMBERVALUE(RIGHT(M$2,1)),$D$3:$H$3,$D$10:$H$10)) -> 0 | N19: =(Rev!N61*_xlfn.XLOOKUP(_xlfn.NUMBERVALUE(RIGHT(N$2,1)),$D$3:$H$3,$D$10:$H$10)) -> 0 | O19: =(Rev!O61*_xlfn.XLOOKUP(_xlfn.NUMBERVALUE(RIGHT(O$2,1)),$D$3:$H$3,$D$10:$H$10)) -> 0 | P19: =(Rev!P61*_xlfn.XLOOKUP(_xlfn.NUMBERVALUE(RIGHT(P$2,1)),$D$3:$H$3,$D$10:$H$10)) -> 0 | Q19: =(Rev!Q61*_xlfn.XLOOKUP(_xlfn.NUMBERVALUE(RIGHT(Q$2,1)),$D$3:$H$3,$D$10:$H$10)) -> 0 | R19: =(Rev!R61*_xlfn.XLOOKUP(_xlfn.NUMBERVALUE(RIGHT(R$2,1)),$D$3:$H$3,$D$10:$H$10)) -> 0 | S19: =(Rev!S61*_xlfn.XLOOKUP(_xlfn.NUMBERVALUE(RIGHT(S$2,1)),$D$3:$H$3,$D$10:$H$10)) -> 20 | T19: =(Rev!T61*_xlfn.XLOOKUP(_xlfn.NUMBERVALUE(RIGHT(T$2,1)),$D$3:$H$3,$D$10:$H$10)) -> 40 | ... BT19: =(Rev!BT61*_xlfn.XLOOKUP(_xlfn.NUMBERVALUE(RIGHT(BT$2,1)),$D$3:$H$3,$D$10:$H$10)) -> 6125
M20: =(Rev!M62*_xlfn.XLOOKUP(_xlfn.NUMBERVALUE(RIGHT(M$2,1)),$D$3:$H$3,$D$11:$H$11)) -> 0 | N20: =(Rev!N62*_xlfn.XLOOKUP(_xlfn.NUMBERVALUE(RIGHT(N$2,1)),$D$3:$H$3,$D$11:$H$11)) -> 0 | O20: =(Rev!O62*_xlfn.XLOOKUP(_xlfn.NUMBERVALUE(RIGHT(O$2,1)),$D$3:$H$3,$D$11:$H$11)) -> 0 | P20: =(Rev!P62*_xlfn.XLOOKUP(_xlfn.NUMBERVALUE(RIGHT(P$2,1)),$D$3:$H$3,$D$11:$H$11)) -> 0 | Q20: =(Rev!Q62*_xlfn.XLOOKUP(_xlfn.NUMBERVALUE(RIGHT(Q$2,1)),$D$3:$H$3,$D$11:$H$11)) -> 0 | R20: =(Rev!R62*_xlfn.XLOOKUP(_xlfn.NUMBERVALUE(RIGHT(R$2,1)),$D$3:$H$3,$D$11:$H$11)) -> 0 | S20: =(Rev!S62*_xlfn.XLOOKUP(_xlfn.NUMBERVALUE(RIGHT(S$2,1)),$D$3:$H$3,$D$11:$H$11)) -> 0 | T20: =(Rev!T62*_xlfn.XLOOKUP(_xlfn.NUMBERVALUE(RIGHT(T$2,1)),$D$3:$H$3,$D$11:$H$11)) -> 0 | ... BT20: =(Rev!BT62*_xlfn.XLOOKUP(_xlfn.NUMBERVALUE(RIGHT(BT$2,1)),$D$3:$H$3,$D$11:$H$11)) -> 23437.5
M21: =(Rev!M63*_xlfn.XLOOKUP(_xlfn.NUMBERVALUE(RIGHT(M$2,1)),$D$3:$H$3,$D$12:$H$12)) -> 0 | N21: =(Rev!N63*_xlfn.XLOOKUP(_xlfn.NUMBERVALUE(RIGHT(N$2,1)),$D$3:$H$3,$D$12:$H$12)) -> 0 | O21: =(Rev!O63*_xlfn.XLOOKUP(_xlfn.NUMBERVALUE(RIGHT(O$2,1)),$D$3:$H$3,$D$12:$H$12)) -> 0 | P21: =(Rev!P63*_xlfn.XLOOKUP(_xlfn.NUMBERVALUE(RIGHT(P$2,1)),$D$3:$H$3,$D$12:$H$12)) -> 0 | Q21: =(Rev!Q63*_xlfn.XLOOKUP(_xlfn.NUMBERVALUE(RIGHT(Q$2,1)),$D$3:$H$3,$D$12:$H$12)) -> 0 | R21: =(Rev!R63*_xlfn.XLOOKUP(_xlfn.NUMBERVALUE(RIGHT(R$2,1)),$D$3:$H$3,$D$12:$H$12)) -> 0 | S21: =(Rev!S63*_xlfn.XLOOKUP(_xlfn.NUMBERVALUE(RIGHT(S$2,1)),$D$3:$H$3,$D$12:$H$12)) -> 0 | T21: =(Rev!T63*_xlfn.XLOOKUP(_xlfn.NUMBERVALUE(RIGHT(T$2,1)),$D$3:$H$3,$D$12:$H$12)) -> 0 | ... BT21: =(Rev!BT63*_xlfn.XLOOKUP(_xlfn.NUMBERVALUE(RIGHT(BT$2,1)),$D$3:$H$3,$D$12:$H$12)) -> 63000
J23: Total COGS | M23: =SUM(M15:M22) -> 0 | N23: =SUM(N15:N22) -> 0 | O23: =SUM(O15:O22) -> 0 | P23: =SUM(P15:P22) -> 0 | Q23: =SUM(Q15:Q22) -> 0 | R23: =SUM(R14:R22) -> 1000 | S23: =SUM(S14:S22) -> 1042 | T23: =SUM(T14:T22) -> 1084 | U23: =SUM(U14:U22) -> 1120.5 | V23: =SUM(V14:V22) -> 1152.5 | W23: =SUM(W14:W22) -> 1194.5 | X23: =SUM(X14:X22) -> 1242 | Y23: =SUM(Y14:Y22) -> 2901.25 | ... BT23: =SUM(BT14:BT22) -> 168238.75
I25: Gross Profit | M25: =M9-M23 -> 0 | N25: =N9-N23 -> 0 | O25: =O9-O23 -> 0 | P25: =P9-P23 -> 0 | Q25: =Q9-Q23 -> 0 | R25: =R9-R23 -> -1000 | S25: =S9-S23 -> 2858 | T25: =T9-T23 -> 3716 | ... BT25: =BT9-BT23 -> 3456501.2
I27: Operating Expenses
J28: R&D | M28: ='R&D'!M14 -> 16516.667 | N28: ='R&D'!N14 -> 16516.667 | O28: ='R&D'!O14 -> 16516.667 | P28: ='R&D'!P14 -> 31033.333 | Q28: ='R&D'!Q14 -> 31033.333 | R28: ='R&D'!R14 -> 45550 | S28: ='R&D'!S14 -> 45550 | T28: ='R&D'!T14 -> 45550 | ... BT28: ='R&D'!BT14 -> 348211.59
J29: Marketing | M29: {='Sales & Marketing'!M12:BT12} -> 12750 | N29: 12750 | O29: 12750 | P29: 12750 | Q29: 12750 | R29: 12750 | S29: 12750 | T29: 12750 | U29: 12750 | V29: 12750 | W29: 12750 | X29: 12750 | Y29: 22525 | Z29: 22525 | AA29: 22525 | AB29: 22525 | AC29: 22525 | AD29: 22525 | AE29: 22525 | AF29: 22525 | AG29: 22525 | AH29: 22525 | AI29: 22525 | AJ29: 22525 | AK29: 28483.333 | AL29: 28483.333 | AM29: 28483.333 | AN29: 28483.333 | AO29: 28483.333 | AP29: 28483.333 | AQ29: 28483.333 | AR29: 28483.333 | AS29: 28483.333 | AT29: 28483.333 | AU29: 28483.333 | AV29: 28483.333 | AW29: 33775 | AX29: 33775 | AY29: 33775 | AZ29: 33775 | BA29: 33775 | BB29: 33775 | BC29: 33775 | BD29: 33775 | BE29: 33775 | BF29: 33775 | BG29: 33775 | BH29: 33775 | BI29: 38650 | BJ29: 38650 | BK29: 38650 | BL29: 38650 | BM29: 38650 | BN29: 38650 | BO29: 38650 | BP29: 38650 | BQ29: 38650 | BR29: 38650 | BS29: 38650 | BT29: 38650
J30: G&A | M30: ='G&A'!M25 -> 98741.667 | N30: ='G&A'!N25 -> 98741.667 | O30: ='G&A'!O25 -> 98741.667 | P30: ='G&A'!P25 -> 98741.667 | Q30: ='G&A'!Q25 -> 98741.667 | R30: ='G&A'!R25 -> 98741.667 | S30: ='G&A'!S25 -> 98741.667 | T30: ='G&A'!T25 -> 98741.667 | ... BT30: ='G&A'!BT25 -> 227545
J31: Sales | M31: {='Sales & Marketing'!M37:BT37} -> 500 | N31: 500 | O31: 500 | P31: 500 | Q31: 500 | R31: 500 | S31: 500 | T31: 500 | U31: 500 | V31: 500 | W31: 500 | X31: 500 | Y31: 22312.5 | Z31: 22837.5 | AA31: 22863.75 | AB31: 22891.312 | AC31: 22920.253 | AD31: 22950.641 | AE31: 22982.548 | AF31: 23016.05 | AG31: 23051.228 | AH31: 23088.164 | AI31: 23126.947 | AJ31: 23167.67 | AK31: 32413.553 | AL31: 33328.927 | AM31: 33419.592 | AN31: 33514.791 | AO31: 33614.749 | AP31: 33719.705 | AQ31: 33829.909 | AR31: 33945.624 | AS31: 34067.124 | AT31: 34194.698 | AU31: 34328.652 | AV31: 34469.304 | AW31: 51713.862 | AX31: 53839.402 | AY31: 54100.747 | AZ31: 54375.159 | BA31: 54663.292 | BB31: 54965.832 | BC31: 55283.498 | BD31: 55617.048 | BE31: 55967.276 | BF31: 56335.014 | BG31: 56721.14 | BH31: 57126.572 | BI31: 66155.401 | BJ31: 70168.266 | BK31: 70815.898 | BL31: 71495.912 | BM31: 72209.926 | BN31: 72959.641 | BO31: 73746.842 | BP31: 74573.403 | BQ31: 75441.292 | BR31: 76352.575 | BS31: 77309.423 | BT31: 78314.113
J33: Total Operating Expense | M33: =SUM(M28:M32) -> 128508.33 | N33: =SUM(N28:N32) -> 128508.33 | O33: =SUM(O28:O32) -> 128508.33 | P33: =SUM(P28:P32) -> 143025 | Q33: =SUM(Q28:Q32) -> 143025 | R33: =SUM(R28:R32) -> 157541.67 | S33: =SUM(S28:S32) -> 157541.67 | T33: =SUM(T28:T32) -> 157541.67 | ... BT33: =SUM(BT28:BT32) -> 692720.7
I36: Operating Income | M36: =M25-M33 -> -128508.33 | N36: =N25-N33 -> -128508.33 | O36: =O25-O33 -> -128508.33 | P36: =P25-P33 -> -143025 | Q36: =Q25-Q33 -> -143025 | R36: =R25-R33 -> -158541.67 | S36: =S25-S33 -> -154683.67 | T36: =T25-T33 -> -153825.67 | ... BT36: =BT25-BT33 -> 2763780.5
H38: =M38 -> 466.66667 | I38: Depreciation | M38: =CapEx!M9 -> 466.66667 | N38: =CapEx!N9 -> 466.66667 | O38: =CapEx!O9 -> 466.66667 | P38: =CapEx!P9 -> 466.66667 | Q38: =CapEx!Q9 -> 466.66667 | R38: =CapEx!R9 -> 466.66667 | S38: =CapEx!S9 -> 466.66667 | T38: =CapEx!T9 -> 466.66667 | ... BT38: =CapEx!BT9 -> 1466.6667
H39: =M39 -> 1666.6667 | I39: Interest Exp | M39: =Loan!M7 -> 1666.6667 | N39: =Loan!N7 -> 1643.9838 | O39: =Loan!O7 -> 1621.1497 | P39: =Loan!P7 -> 1598.1634 | Q39: =Loan!Q7 -> 1575.0238 | R39: =Loan!R7 -> 1551.73 | S39: =Loan!S7 -> 1528.2808 | T39: =Loan!T7 -> 1504.6754 | ... BT39: =Loan!BT7 -> 33.570189
H40: =M40 -> 0
H41: =M41 -> -130641.67 | I41: Pre tax income | M41: =M36-M38-M39 -> -130641.67 | N41: =N36-N38-N39 -> -130618.98 | O41: =O36-O38-O39 -> -130596.15 | P41: =P36-P38-P39 -> -145089.83 | Q41: =Q36-Q38-Q39 -> -145066.69 | R41: =R36-R38-R39 -> -160560.06 | S41: =S36-S38-S39 -> -156678.61 | T41: =T36-T38-T39 -> -155797.01 | ... BT41: =BT36-BT38-BT39 -> 2762280.3
H42: =M42 -> 0 | I42: Taxes @20% | J42: 0.2 | M42: =IF(M41>0,$J42*M41,0) -> 0 | N42: =IF(N41>0,$J42*N41,0) -> 0 | O42: =IF(O41>0,$J42*O41,0) -> 0 | P42: =IF(P41>0,$J42*P41,0) -> 0 | Q42: =IF(Q41>0,$J42*Q41,0) -> 0 | R42: =IF(R41>0,$J42*R41,0) -> 0 | S42: =IF(S41>0,$J42*S41,0) -> 0 | T42: =IF(T41>0,$J42*T41,0) -> 0 | ... BT42: =IF(BT41>0,$J42*BT41,0) -> 552456.06
H43: =M43 -> 0
H44: =M44 -> -130641.67 | I44: Net Income | M44: =M41-M42 -> -130641.67 | N44: =N41-N42 -> -130618.98 | O44: =O41-O42 -> -130596.15 | P44: =P41-P42 -> -145089.83 | Q44: =Q41-Q42 -> -145066.69 | R44: =R41-R42 -> -160560.06 | S44: =S41-S42 -> -156678.61 | T44: =T41-T42 -> -155797.01 | ... BT44: =BT41-BT42 -> 2209824.2
I45: Retained Earnings | M45: =M44+L45 -> -130641.67 | N45: =N44+M45 -> -261260.65 | O45: =O44+N45 -> -391856.8 | P45: =P44+O45 -> -536946.63 | Q45: =Q44+P45 -> -682013.32 | R45: =R44+Q45 -> -842573.38 | S45: =S44+R45 -> -999252 | T45: =T44+S45 -> -1155049 | ... BT45: =BT44+BS45 -> 14400730
I48: Cash Flow
I50: Net Income Method
J51: Beginning Cash | M51: 0 | N51: =M61 -> 617172.57 | O51: =N61 -> 512345.14 | P51: =O61 -> 407517.7 | Q51: =P61 -> 288173.61 | R51: =Q61 -> 168829.51 | S51: =R61 -> 33968.742 | T51: =S61 -> -97229.023 | U51: =T61 -> -227457.79 | ... BT51: =BS61 -> 24541678
J52: Net Income | M52: =M44 -> -130641.67 | N52: =N44 -> -130618.98 | O52: =O44 -> -130596.15 | P52: =P44 -> -145089.83 | Q52: =Q44 -> -145066.69 | R52: =R44 -> -160560.06 | S52: =S44 -> -156678.61 | T52: =T44 -> -155797.01 | ... BT52: =BT44 -> 2209824.2
J53: Equity Investment (+) | M53: =M82 -> 500000 | N53: =N82 -> 0 | O53: =O82 -> 0 | P53: =P82 -> 0 | Q53: =Q82 -> 0 | R53: =R82 -> 0 | S53: =S82 -> 0 | T53: =T82 -> 0 | ... BT53: =BT82 -> 0
J54: Change in A/R (+/-) | M54: =-Rev!M87 -> 0 | N54: =-Rev!N87 -> 0 | O54: =-Rev!O87 -> 0 | P54: =-Rev!P87 -> 0 | Q54: =-Rev!Q87 -> 0 | R54: =-Rev!R87 -> 0 | S54: =-Rev!S87 -> -195 | T54: =-Rev!T87 -> -84 | ... BT54: =-Rev!BT87 -> -12743.5
J55: Capital Expenditures (-) | M55: =-CapEx!M20 -> -28000 | N55: =-CapEx!N20 -> 0 | O55: =CapEx!O20 -> 0 | P55: =-CapEx!P20 -> 0 | Q55: =-CapEx!Q20 -> 0 | R55: =-CapEx!R20 -> 0 | S55: =-CapEx!S20 -> 0 | T55: =-CapEx!T20 -> 0 | U55: =-CapEx!U20 -> 0 | V55: =-CapEx!V20 -> 0 | W55: =-CapEx!W20 -> 0 | ... BT55: =-CapEx!BT20 -> 0
J56: Borrowings (+) | M56: =Loan!M13 -> 250000 | N56: =Loan!N13 -> 0 | O56: =Loan!O13 -> 0 | P56: =Loan!P13 -> 0 | Q56: =Loan!Q13 -> 0 | R56: =Loan!R13 -> 0 | S56: =Loan!S13 -> 0 | T56: =Loan!T13 -> 0 | ... BT56: =Loan!BT13 -> 0
J57: COGS (Related to Inventory) (+)
J58: Depreciation (+) | M58: =CapEx!M9 -> 466.66667 | N58: =CapEx!N9 -> 466.66667 | O58: =CapEx!O9 -> 466.66667 | P58: =CapEx!P9 -> 466.66667 | Q58: =CapEx!Q9 -> 466.66667 | R58: =CapEx!R9 -> 466.66667 | S58: =CapEx!S9 -> 466.66667 | T58: =CapEx!T9 -> 466.66667 | ... BT58: =CapEx!BT9 -> 1466.6667
J59: Repayment of Principal (-) | M59: =-Loan!M8 -> -3402.4319 | N59: =-Loan!N8 -> -3425.1148 | O59: =-Loan!O8 -> -3447.9489 | P59: =-Loan!P8 -> -3470.9352 | Q59: =-Loan!Q8 -> -3494.0748 | R59: =-Loan!R8 -> -3517.3686 | S59: =-Loan!S8 -> -3540.8177 | T59: =-Loan!T8 -> -3564.4232 | ... BT59: =-Loan!BT8 -> -5035.5284
J60: Defered Compensation | M60: ='G&A'!M62 -> 28750 | N60: ='G&A'!N62 -> 28750 | O60: ='G&A'!O62 -> 28750 | P60: ='G&A'!P62 -> 28750 | Q60: ='G&A'!Q62 -> 28750 | R60: ='G&A'!R62 -> 28750 | S60: ='G&A'!S62 -> 28750 | T60: ='G&A'!T62 -> 28750 | ... BT60: ='G&A'!BT62 -> 0
J61: Ending Cash | M61: =SUM(M51:M60) -> 617172.57 | N61: =SUM(N51:N60) -> 512345.14 | O61: =SUM(O51:O60) -> 407517.7 | P61: =SUM(P51:P60) -> 288173.61 | Q61: =SUM(Q51:Q60) -> 168829.51 | R61: =SUM(R51:R60) -> 33968.742 | S61: =SUM(S51:S60) -> -97229.023 | T61: =SUM(T51:T60) -> -227457.79 | ... BT61: =SUM(BT51:BT60) -> 26735190
I64: Cash Collections Method
J65: Beginning Cash | M65: 0 | N65: =M75 -> 617172.57 | O65: =N75 -> 512345.14 | P65: =O75 -> 407517.7 | Q65: =P75 -> 288173.61 | R65: =Q75 -> 168829.51 | S65: =R75 -> 33968.742 | T65: =S75 -> -97229.023 | U65: =T75 -> -227457.79 | ... BT65: =BS75 -> 24541678
J66: Cash Collections | M66: =Rev!M81 -> 0 | N66: =Rev!N81 -> 0 | O66: =Rev!O81 -> 0 | P66: =Rev!P81 -> 0 | Q66: =Rev!Q81 -> 0 | R66: =Rev!R81 -> 0 | S66: =Rev!S81 -> 3705 | T66: =Rev!T81 -> 4716 | ... BT66: =Rev!BT81 -> 3611996.5
J67: Capital Expenditures (-) | M67: {=-CapEx!M20:BT20} -> -28000 | N67: 0 | O67: 0 | P67: 0 | Q67: 0 | R67: 0 | S67: 0 | T67: 0 | U67: 0 | V67: 0 | W67: 0 | X67: 0 | Y67: -15000 | Z67: 0 | AA67: 0 | AB67: 0 | AC67: 0 | AD67: 0 | AE67: 0 | AF67: 0 | AG67: 0 | AH67: 0 | AI67: 0 | AJ67: 0 | AK67: -24000 | AL67: 0 | AM67: 0 | AN67: 0 | AO67: 0 | AP67: 0 | AQ67: 0 | AR67: 0 | AS67: 0 | AT67: 0 | AU67: 0 | AV67: 0 | AW67: -21000 | AX67: 0 | AY67: 0 | AZ67: 0 | BA67: 0 | BB67: 0 | BC67: 0 | BD67: 0 | BE67: 0 | BF67: 0 | BG67: 0 | BH67: 0 | BI67: 0 | BJ67: 0 | BK67: 0 | BL67: 0 | BM67: 0 | BN67: 0 | BO67: 0 | BP67: 0 | BQ67: 0 | BR67: 0 | BS67: 0 | BT67: 0
J68: Equity Investments (+) | M68: =M82 -> 500000 | N68: =N82 -> 0 | O68: =O82 -> 0 | P68: =P82 -> 0 | Q68: =Q82 -> 0 | R68: =R82 -> 0 | S68: =S82 -> 0 | T68: =T82 -> 0 | ... BT68: =BT82 -> 0
J69: Borrowings (+) | M69: =Loan!M13 -> 250000 | N69: 0 | O69: 0 | P69: 0 | Q69: 0 | R69: 0 | S69: 0 | T69: 0 | U69: 0 | V69: 0 | W69: 0 | X69: 0 | Y69: 0 | Z69: 0 | AA69: 0 | AB69: 0 | AC69: 0 | AD69: 0 | AE69: 0 | AF69: 0 | AG69: 0 | AH69: 0 | AI69: 0 | AJ69: 0 | AK69: 0 | AL69: 0 | AM69: 0 | AN69: 0 | AO69: 0 | AP69: 0 | AQ69: 0 | AR69: 0 | AS69: 0 | AT69: 0 | AU69: 0 | AV69: 0 | AW69: 0 | AX69: 0 | AY69: 0 | AZ69: 0 | BA69: 0 | BB69: 0 | BC69: 0 | BD69: 0 | BE69: 0 | BF69: 0 | BG69: 0 | BH69: 0 | BI69: 0 | BJ69: 0 | BK69: 0 | BL69: 0 | BM69: 0 | BN69: 0 | BO69: 0 | BP69: 0 | BQ69: 0 | BR69: 0 | BS69: 0 | BT69: 0
J70: Operating Expenses (-) | M70: {=-'P&L'!M33:BT33} -> -128508.33 | N70: -128508.33 | O70: -128508.33 | P70: -143025 | Q70: -143025 | R70: -157541.67 | S70: -157541.67 | T70: -157541.67 | U70: -162015 | V70: -162015 | W70: -162015 | X70: -165598.33 | Y70: -238150 | Z70: -238675 | AA70: -261926.25 | AB70: -299853.81 | AC70: -302882.75 | AD70: -317734.81 | AE70: -330533.38 | AF70: -330566.88 | AG70: -329852.06 | AH70: -329889 | AI70: -334927.78 | AJ70: -339968.5 | AK70: -374603.76 | AL70: -385969.14 | AM70: -400576.47 | AN70: -400671.67 | AO70: -422401.62 | AP70: -439056.58 | AQ70: -439166.78 | AR70: -453799.17 | AS70: -462845.67 | AT70: -473343.24 | AU70: -473477.19 | AV70: -473617.85 | AW70: -593753 | AX70: -595878.54 | AY70: -596139.88 | AZ70: -596414.29 | BA70: -598219.09 | BB70: -583521.63 | BC70: -604880.97 | BD70: -620747.85 | BE70: -635919.74 | BF70: -636287.48 | BG70: -651190.28 | BH70: -651595.71 | BI70: -680561.99 | BJ70: -684574.86 | BK70: -685222.49 | BL70: -685902.5 | BM70: -686616.52 | BN70: -687366.23 | BO70: -688153.43 | BP70: -688980 | BQ70: -689847.88 | BR70: -690759.17 | BS70: -691716.01 | BT70: -692720.7
J71: Cash COGS (-) | M71: =-M23 -> 0 | N71: =-N23 -> 0 | O71: =-O23 -> 0 | P71: =-P23 -> 0 | Q71: =-Q23 -> 0 | R71: =-R23 -> -1000 | S71: =-S23 -> -1042 | T71: =-T23 -> -1084 | ... BT71: =-BT23 -> -168238.75
J72: Debt Payments (-) | M72: {=-Loan!M6:BT6} -> -5069.0986 | N72: -5069.0986 | O72: -5069.0986 | P72: -5069.0986 | Q72: -5069.0986 | R72: -5069.0986 | S72: -5069.0986 | T72: -5069.0986 | U72: -5069.0986 | V72: -5069.0986 | W72: -5069.0986 | X72: -5069.0986 | Y72: -5069.0986 | Z72: -5069.0986 | AA72: -5069.0986 | AB72: -5069.0986 | AC72: -5069.0986 | AD72: -5069.0986 | AE72: -5069.0986 | AF72: -5069.0986 | AG72: -5069.0986 | AH72: -5069.0986 | AI72: -5069.0986 | AJ72: -5069.0986 | AK72: -5069.0986 | AL72: -5069.0986 | AM72: -5069.0986 | AN72: -5069.0986 | AO72: -5069.0986 | AP72: -5069.0986 | AQ72: -5069.0986 | AR72: -5069.0986 | AS72: -5069.0986 | AT72: -5069.0986 | AU72: -5069.0986 | AV72: -5069.0986 | AW72: -5069.0986 | AX72: -5069.0986 | AY72: -5069.0986 | AZ72: -5069.0986 | BA72: -5069.0986 | BB72: -5069.0986 | BC72: -5069.0986 | BD72: -5069.0986 | BE72: -5069.0986 | BF72: -5069.0986 | BG72: -5069.0986 | BH72: -5069.0986 | BI72: -5069.0986 | BJ72: -5069.0986 | BK72: -5069.0986 | BL72: -5069.0986 | BM72: -5069.0986 | BN72: -5069.0986 | BO72: -5069.0986 | BP72: -5069.0986 | BQ72: -5069.0986 | BR72: -5069.0986 | BS72: -5069.0986 | BT72: -5069.0986
J73: Taxes (-) | M73: =-M42 -> 0 | N73: =-N42 -> 0 | O73: =-O42 -> 0 | P73: =-P42 -> 0 | Q73: =-Q42 -> 0 | R73: =-R42 -> 0 | S73: =-S42 -> 0 | T73: =-T42 -> 0 | ... BT73: =-BT42 -> -552456.06
I74: =M73 -> 0 | J74: Deferred Compensation | M74: ='G&A'!M62 -> 28750 | N74: ='G&A'!N62 -> 28750 | O74: ='G&A'!O62 -> 28750 | P74: ='G&A'!P62 -> 28750 | Q74: ='G&A'!Q62 -> 28750 | R74: ='G&A'!R62 -> 28750 | S74: ='G&A'!S62 -> 28750 | T74: ='G&A'!T62 -> 28750 | ... BT74: ='G&A'!BT62 -> 0
J75: Ending Cash | M75: =SUM(M65:M74) -> 617172.57 | N75: =SUM(N65:N74) -> 512345.14 | O75: =SUM(O65:O74) -> 407517.7 | P75: =SUM(P65:P74) -> 288173.61 | Q75: =SUM(Q65:Q74) -> 168829.51 | R75: =SUM(R65:R74) -> 33968.742 | S75: =SUM(S65:S74) -> -97229.023 | T75: =SUM(T65:T74) -> -227457.79 | ... BT75: =SUM(BT65:BT74) -> 26735190
J77: Check | M77: =M61-M75 -> 0 | N77: =+N61-N75 -> 0 | O77: =+O61-O75 -> 0 | P77: =+P61-P75 -> 0 | Q77: =+Q61-Q75 -> 0 | R77: =+R61-R75 -> -9.4587449e-11 | S77: =+S61-S75 -> 0 | T77: =+T61-T75 -> 0 | U77: =+U61-U75 -> 0 | ... BT77: =+BT61-BT75 -> 0
I78: Low Point | J78: =_xlfn.CONCAT(_xlfn.XLOOKUP(MIN(M75:BT75),M75:BT75,M2:BT3)) -> Year 1Sep
I79: High Point | J79: =_xlfn.CONCAT(_xlfn.XLOOKUP(MAX(M75:BT75),M75:BT75,M2:BT3)) -> Year 5Dec
I82: Equity | M82: 500000 | V82: 2500000 | AH82: 9000000
I83: cum equity | M83: =M82+L83 -> 500000 | N83: =N82+M83 -> 500000 | O83: =O82+N83 -> 500000 | P83: =P82+O83 -> 500000 | Q83: =Q82+P83 -> 500000 | R83: =R82+Q83 -> 500000 | S83: =S82+R83 -> 500000 | T83: =T82+S83 -> 500000 | ... BT83: =BT82+BS83 -> 12000000

Sheet Balance Sheet
A1: Balance Sheet
M3: Year 1 | N3: Year 1 | O3: Year 1 | P3: Year 1 | Q3: Year 1 | R3: Year 1 | S3: Year 1 | T3: Year 1 | U3: Year 1 | V3: Year 1 | W3: Year 1 | X3: Year 1 | Y3: Year 2 | Z3: Year 2 | AA3: Year 2 | AB3: Year 2 | AC3: Year 2 | AD3: Year 2 | AE3: Year 2 | AF3: Year 2 | AG3: Year 2 | AH3: Year 2 | AI3: Year 2 | AJ3: Year 2 | AK3: Year 3 | AL3: Year 3 | AM3: Year 3 | AN3: Year 3 | AO3: Year 3 | AP3: Year 3 | AQ3: Year 3 | AR3: Year 3 | AS3: Year 3 | AT3: Year 3 | AU3: Year 3 | AV3: Year 3 | AW3: Year 4 | AX3: Year 4 | AY3: Year 4 | AZ3: Year 4 | BA3: Year 4 | BB3: Year 4 | BC3: Year 4 | BD3: Year 4 | BE3: Year 4 | BF3: Year 4 | BG3: Year 4 | BH3: Year 4 | BI3: Year 5 | BJ3: Year 5 | BK3: Year 5 | BL3: Year 5 | BM3: Year 5 | BN3: Year 5 | BO3: Year 5 | BP3: Year 5 | BQ3: Year 5 | BR3: Year 5 | BS3: Year 5 | BT3: Year 5
M4: January | N4: February | O4: March | P4: April | Q4: May | R4: June | S4: July | T4: August | U4: September | V4: October | W4: November | X4: December | Y4: January | Z4: February | AA4: March | AB4: April | AC4: May | AD4: June | AE4: July | AF4: August | AG4: September | AH4: October | AI4: November | AJ4: December | AK4: January | AL4: February | AM4: March | AN4: April | AO4: May | AP4: June | AQ4: July | AR4: August | AS4: September | AT4: October | AU4: November | AV4: December | AW4: January | AX4: February | AY4: March | AZ4: April | BA4: May | BB4: June | BC4: July | BD4: August | BE4: September | BF4: October | BG4: November | BH4: December | BI4: January | BJ4: February | BK4: March | BL4: April | BM4: May | BN4: June | BO4: July | BP4: August | BQ4: September | BR4: October | BS4: November | BT4: December
A5: Assets:
B6: Cash | M6: ='P&L'!M75 -> 617172.57 | N6: ='P&L'!N75 -> 512345.14 | O6: ='P&L'!O75 -> 407517.7 | P6: ='P&L'!P75 -> 288173.61 | Q6: ='P&L'!Q75 -> 168829.51 | R6: ='P&L'!R75 -> 33968.742 | S6: ='P&L'!S75 -> -97229.023 | T6: ='P&L'!T75 -> -227457.79 | ... BT6: ='P&L'!BT75 -> 26735190
B7: Accounts Receivable | M7: =Rev!M85 -> 0 | N7: =Rev!N85 -> 0 | O7: =Rev!O85 -> 0 | P7: =Rev!P85 -> 0 | Q7: =Rev!Q85 -> 0 | R7: =Rev!R85 -> 0 | S7: =Rev!S85 -> 195 | T7: =Rev!T85 -> 279 | ... BT7: =Rev!BT85 -> 215339.7
B8: Repayment of deffered expenses | M8: ='G&A'!M29 -> 0 | N8: ='G&A'!N29 -> 0 | O8: ='G&A'!O29 -> 0 | P8: ='G&A'!P29 -> 0 | Q8: ='G&A'!Q29 -> 0 | R8: ='G&A'!R29 -> 0 | S8: ='G&A'!S29 -> 0 | T8: ='G&A'!T29 -> 0 | ... BT8: ='G&A'!BT29 -> 0
B9: Inventory | M9: 0 | N9: =+M9 -> 0 | O9: =+N9 -> 0 | P9: =+O9 -> 0 | Q9: =+P9 -> 0 | R9: =+Q9 -> 0 | S9: =+R9 -> 0 | T9: =+S9 -> 0 | U9: =+T9 -> 0 | ... BT9: =+BS9 -> 0
B10: PPE (Net) | M10: =CapEx!M17 -> 27533.333 | N10: =CapEx!N17 -> 27066.667 | O10: =CapEx!O17 -> 26600 | P10: =CapEx!P17 -> 26133.333 | Q10: =CapEx!Q17 -> 25666.667 | R10: =CapEx!R17 -> 25200 | S10: =CapEx!S17 -> 24733.333 | T10: =CapEx!T17 -> 24266.667 | ... BT10: =CapEx!BT17 -> 25200
B13: Total Assets: | M13: =SUM(M6:M10) -> 644705.9 | N13: =SUM(N6:N11) -> 539411.8 | O13: =SUM(O6:O11) -> 434117.7 | P13: =SUM(P6:P11) -> 314306.94 | Q13: =SUM(Q6:Q11) -> 194496.17 | R13: =SUM(R6:R11) -> 59168.742 | S13: =SUM(S6:S11) -> -72300.69 | T13: =SUM(T6:T11) -> -202912.12 | U13: =SUM(U6:U11) -> -337233.39 | ... BT13: =SUM(BT6:BT11) -> 26975730
A15: Liabilities:
B16: Defered Compensation Payable | M16: ='G&A'!M64 -> 28750 | N16: ='G&A'!N64 -> 57500 | O16: ='G&A'!O64 -> 86250 | P16: ='G&A'!P64 -> 115000 | Q16: ='G&A'!Q64 -> 143750 | R16: ='G&A'!R64 -> 172500 | S16: ='G&A'!S64 -> 201250 | T16: ='G&A'!T64 -> 230000 | ... BT16: ='G&A'!BT64 -> 0
B17: Loan | M17: =Loan!M11 -> 246597.57 | N17: =Loan!N11 -> 243172.45 | O17: =Loan!O11 -> 239724.5 | P17: =Loan!P11 -> 236253.57 | Q17: =Loan!Q11 -> 232759.49 | R17: =Loan!R11 -> 229242.13 | S17: =Loan!S11 -> 225701.31 | T17: =Loan!T11 -> 222136.88 | ... BT17: =Loan!BT11 -> -3.6379788e-11
B19: Total Liabilities: | M19: =SUM(M16:M17) -> 275347.57 | N19: =SUM(N16:N17) -> 300672.45 | O19: =SUM(O16:O17) -> 325974.5 | P19: =SUM(P16:P17) -> 351253.57 | Q19: =SUM(Q16:Q17) -> 376509.49 | R19: =SUM(R16:R17) -> 401742.13 | S19: =SUM(S16:S17) -> 426951.31 | T19: =SUM(T16:T17) -> 452136.88 | ... BT19: =SUM(BT16:BT17) -> -3.6379788e-11
A21: Equity:
B22: Retained Earnings | M22: ='P&L'!M45 -> -130641.67 | N22: ='P&L'!N45 -> -261260.65 | O22: ='P&L'!O45 -> -391856.8 | P22: ='P&L'!P45 -> -536946.63 | Q22: ='P&L'!Q45 -> -682013.32 | R22: ='P&L'!R45 -> -842573.38 | S22: ='P&L'!S45 -> -999252 | T22: ='P&L'!T45 -> -1155049 | ... BT22: ='P&L'!BT45 -> 14400730
B23: Paid in Capital | M23: ='P&L'!M83 -> 500000 | N23: ='P&L'!N83 -> 500000 | O23: ='P&L'!O83 -> 500000 | P23: ='P&L'!P83 -> 500000 | Q23: ='P&L'!Q83 -> 500000 | R23: ='P&L'!R83 -> 500000 | S23: ='P&L'!S83 -> 500000 | T23: ='P&L'!T83 -> 500000 | ... BT23: ='P&L'!BT83 -> 12000000
B25: Total Share Holder's Equity | M25: =SUM(M22:M23) -> 369358.33 | N25: =SUM(N22:N23) -> 238739.35 | O25: =SUM(O22:O23) -> 108143.2 | P25: =SUM(P22:P23) -> -36946.63 | Q25: =SUM(Q22:Q23) -> -182013.32 | R25: =SUM(R22:R23) -> -342573.38 | S25: =SUM(S22:S23) -> -499252 | T25: =SUM(T22:T23) -> -655049.01 | ... BT25: =SUM(BT22:BT23) -> 26400730
B27: Total L & SE | M27: =M19+M25 -> 644705.9 | N27: =N19+N25 -> 539411.8 | O27: =O19+O25 -> 434117.7 | P27: =P19+P25 -> 314306.94 | Q27: =Q19+Q25 -> 194496.17 | R27: =R19+R25 -> 59168.742 | S27: =S19+S25 -> -72300.69 | T27: =T19+T25 -> -202912.12 | ... BT27: =BT19+BT25 -> 26400730
B29: Check | M29: =M13-M27 -> 0 | N29: =N13-N27 -> 0 | O29: =O13-O27 -> 0 | P29: =P13-P27 -> 0 | Q29: =Q13-Q27 -> 0 | R29: =R13-R27 -> 0 | S29: =S13-S27 -> 0 | T29: =T13-T27 -> 0 | ... BT29: =BT13-BT27 -> 0

Sheet HeadCount
A1: Total Headcount Projections
A4: Year | B4: Year 1 | C4: Year 2 | D4: Year 3 | E4: Year 4 | F4: Year 5
A6: G&A | B6: 3 | C6: 8 | D6: 8 | E6: 11 | F6: 11
A7: Sales & Marketing | B7: {='Sales & Marketing'!C28:G28} -> 1 | C7: 5 | D7: 6 | E7: 8 | F7: 9
A8: R&D | B8: 3 | C8: 8 | D8: 16 | E8: 23 | F8: 23
A10: Total Employees | B10: =SUM(B6:B8) -> 7 | C10: =SUM(C6:C8) -> 21 | D10: =SUM(D6:D8) -> 30 | E10: =SUM(E6:E8) -> 42 | F10: =SUM(F6:F8) -> 43
A12: Hiring Projections
A14: Year | B14: Year 1 | C14: Year 2 | D14: Year 3 | E14: Year 4 | F14: Year 5
A16: G&A | B16: =B6 -> 3 | C16: =C6-B6 -> 5 | D16: =D6-C6 -> 0 | E16: =E6-D6 -> 3 | F16: =F6-E6 -> 0
A17: Sales & Marketing | B17: =B7 -> 1 | C17: =C7-B7 -> 4 | D17: =D7-C7 -> 1 | E17: =E7-D7 -> 2 | F17: =F7-E7 -> 1
A18: R&D | B18: =B8 -> 3 | C18: 4 | D18: =D8-C8 -> 8 | E18: =E8-D8 -> 7 | F18: =F8-E8 -> 0
A20: Total Hires | B20: =SUM(B16:B18) -> 7 | C20: =SUM(C16:C18) -> 13 | D20: =SUM(D16:D18) -> 9 | E20: =SUM(E16:E18) -> 12 | F20: =SUM(F16:F18) -> 1

Sheet R&D
A1: R&D
M3: Year 1 | N3: Year 1 | O3: Year 1 | P3: Year 1 | Q3: Year 1 | R3: Year 1 | S3: Year 1 | T3: Year 1 | U3: Year 1 | V3: Year 1 | W3: Year 1 | X3: Year 1 | Y3: Year 2 | Z3: Year 2 | AA3: Year 2 | AB3: Year 2 | AC3: Year 2 | AD3: Year 2 | AE3: Year 2 | AF3: Year 2 | AG3: Year 2 | AH3: Year 2 | AI3: Year 2 | AJ3: Year 2 | AK3: Year 3 | AL3: Year 3 | AM3: Year 3 | AN3: Year 3 | AO3: Year 3 | AP3: Year 3 | AQ3: Year 3 | AR3: Year 3 | AS3: Year 3 | AT3: Year 3 | AU3: Year 3 | AV3: Year 3 | AW3: Year 4 | AX3: Year 4 | AY3: Year 4 | AZ3: Year 4 | BA3: Year 4 | BB3: Year 4 | BC3: Year 4 | BD3: Year 4 | BE3: Year 4 | BF3: Year 4 | BG3: Year 4 | BH3: Year 4 | BI3: Year 5 | BJ3: Year 5 | BK3: Year 5 | BL3: Year 5 | BM3: Year 5 | BN3: Year 5 | BO3: Year 5 | BP3: Year 5 | BQ3: Year 5 | BR3: Year 5 | BS3: Year 5 | BT3: Year 5
M4: January | N4: February | O4: March | P4: April | Q4: May | R4: June | S4: July | T4: August | U4: September | V4: October | W4: November | X4: December | Y4: January | Z4: February | AA4: March | AB4: April | AC4: May | AD4: June | AE4: July | AF4: August | AG4: September | AH4: October | AI4: November | AJ4: December | AK4: January | AL4: February | AM4: March | AN4: April | AO4: May | AP4: June | AQ4: July | AR4: August | AS4: September | AT4: October | AU4: November | AV4: December | AW4: January | AX4: February | AY4: March | AZ4: April | BA4: May | BB4: June | BC4: July | BD4: August | BE4: September | BF4: October | BG4: November | BH4: December | BI4: January | BJ4: February | BK4: March | BL4: April | BM4: May | BN4: June | BO4: July | BP4: August | BQ4: September | BR4: October | BS4: November | BT4: December
A5: Salaries & Wages | M5: =M57 -> 10833.333 | N5: =N57 -> 10833.333 | O5: =O57 -> 10833.333 | P5: =P57 -> 21666.667 | Q5: =Q57 -> 21666.667 | R5: =R57 -> 32500 | S5: =S57 -> 32500 | T5: =T57 -> 32500 | ... BT5: =BT57 -> 259271.8
A6: Benefits @ | B6: 0.22 | M6: =M5*$B$6 -> 2383.3333 | N6: =N5*$B$6 -> 2383.3333 | O6: =O5*$B$6 -> 2383.3333 | P6: =P5*$B$6 -> 4766.6667 | Q6: =Q5*$B$6 -> 4766.6667 | R6: =R5*$B$6 -> 7150 | S6: =S5*$B$6 -> 7150 | T6: =T5*$B$6 -> 7150 | ... BT6: =BT5*$B$6 -> 57039.795
A8: T&E | B8: 2000 | C8: /month | M8: =2000 -> 2000 | N8: =+M8 -> 2000 | O8: =+N8 -> 2000 | P8: =+O8 -> 2000 | Q8: =+P8 -> 2000 | R8: =+Q8 -> 2000 | S8: =+R8 -> 2000 | T8: =+S8 -> 2000 | U8: =+T8 -> 2000 | ... BT8: =+BS8 -> 2000
A10: Training | B10: 500 | C10: /month | M10: =COUNTIF(M$31:M$54,">0")*$B$10 -> 500 | N10: =COUNTIF(N$31:N$54,">0")*$B$10 -> 500 | O10: =COUNTIF(O$31:O$54,">0")*$B$10 -> 500 | P10: =COUNTIF(P$31:P$54,">0")*$B$10 -> 1000 | Q10: =COUNTIF(Q$31:Q$54,">0")*$B$10 -> 1000 | R10: =COUNTIF(R$31:R$54,">0")*$B$10 -> 1500 | S10: =COUNTIF(S$31:S$54,">0")*$B$10 -> 1500 | T10: =COUNTIF(T$31:T$54,">0")*$B$10 -> 1500 | ... BT10: =COUNTIF(BT$31:BT$54,">0")*$B$10 -> 11500
A12: Dev SaaS Services | B12: 800 | C12: /month | M12: =COUNTIF(M$31:M$54,">0")*$B$12 -> 800 | N12: =COUNTIF(N$31:N$54,">0")*$B$12 -> 800 | O12: =COUNTIF(O$31:O$54,">0")*$B$12 -> 800 | P12: =COUNTIF(P$31:P$54,">0")*$B$12 -> 1600 | Q12: =COUNTIF(Q$31:Q$54,">0")*$B$12 -> 1600 | R12: =COUNTIF(R$31:R$54,">0")*$B$12 -> 2400 | S12: =COUNTIF(S$31:S$54,">0")*$B$12 -> 2400 | T12: =COUNTIF(T$31:T$54,">0")*$B$12 -> 2400 | ... BT12: =COUNTIF(BT$31:BT$54,">0")*$B$12 -> 18400
A14: Total R&D Expense | M14: =SUM(M5:M12) -> 16516.667 | N14: =SUM(N5:N12) -> 16516.667 | O14: =SUM(O5:O12) -> 16516.667 | P14: =SUM(P5:P12) -> 31033.333 | Q14: =SUM(Q5:Q12) -> 31033.333 | R14: =SUM(R5:R12) -> 45550 | S14: =SUM(S5:S12) -> 45550 | T14: =SUM(T5:T12) -> 45550 | ... BT14: =SUM(BT5:BT12) -> 348211.59
C29: Salaries | M29: Year 1 | Y29: Year 2 | AK29: Year 3 | AW29: Year 4 | BI29: Year 5
A30: Employees | M30: Q1 | P30: Q2 | S30: Q3 | V30: Q4 | Y30: Q1 | AB30: Q2 | AE30: Q3 | AH30: Q4 | AK30: Q1 | AN30: Q2 | AQ30: Q3 | AT30: Q4 | AW30: Q1 | AZ30: Q2 | BC30: Q3 | BF30: Q4 | BI30: Q1 | BL30: Q2 | BO30: Q3 | BR30: Q4
B31: VP of Engineering | C31: 165000 | M31: 0 | N31: =+M31 -> 0 | O31: =+N31 -> 0 | P31: =+O31 -> 0 | Q31: =+P31 -> 0 | R31: =+Q31 -> 0 | S31: =+R31 -> 0 | T31: =+S31 -> 0 | U31: =+T31 -> 0 | ... X31: =+W31 -> 0 | Y31: =X31*(1+C$59) -> 0 | Z31: =+Y31 -> 0 | AA31: =+Z31 -> 0 | AB31: =+AA31 -> 0 | AC31: =+AB31 -> 0 | AD31: =+AC31 -> 0 | AE31: =+AD31 -> 0 | AF31: =+AE31 -> 0 | AG31: =+AF31 -> 0 | ... AJ31: =+AI31 -> 0 | AK31: =AJ31*(1+C$59) -> 0 | AL31: =+AK31 -> 0 | AM31: =+AL31 -> 0 | AN31: =+AM31 -> 0 | AO31: =+AN31 -> 0 | AP31: =+AO31 -> 0 | AQ31: =+AP31 -> 0 | AR31: =+AQ31 -> 0 | AS31: =+AR31 -> 0 | ... AV31: =+AU31 -> 0 | AW31: =C31/12 -> 13750 | AX31: =+AW31 -> 13750 | AY31: =+AX31 -> 13750 | AZ31: =+AY31 -> 13750 | BA31: =+AZ31 -> 13750 | BB31: =+BA31 -> 13750 | BC31: =+BB31 -> 13750 | BD31: =+BC31 -> 13750 | BE31: =+BD31 -> 13750 | ... BH31: =+BG31 -> 13750 | BI31: =BH31*(1+C$59) -> 14437.5 | BJ31: =+BI31 -> 14437.5 | BK31: =+BJ31 -> 14437.5 | BL31: =+BK31 -> 14437.5 | BM31: =+BL31 -> 14437.5 | BN31: =+BM31 -> 14437.5 | BO31: =+BN31 -> 14437.5 | BP31: =+BO31 -> 14437.5 | BQ31: =+BP31 -> 14437.5 | ... BT31: =+BS31 -> 14437.5
B32: Machine Learning Engineers | C32: 130000 | M32: =C32/12 -> 10833.333 | N32: =+M32 -> 10833.333 | O32: =+N32 -> 10833.333 | P32: =+O32 -> 10833.333 | Q32: =+P32 -> 10833.333 | R32: =+Q32 -> 10833.333 | S32: =+R32 -> 10833.333 | T32: =+S32 -> 10833.333 | U32: =+T32 -> 10833.333 | ... X32: =+W32 -> 10833.333 | Y32: =X32*(1+C$59) -> 11375 | Z32: =+Y32 -> 11375 | AA32: =+Z32 -> 11375 | AB32: =+AA32 -> 11375 | AC32: =+AB32 -> 11375 | AD32: =+AC32 -> 11375 | AE32: =+AD32 -> 11375 | AF32: =+AE32 -> 11375 | AG32: =+AF32 -> 11375 | ... AJ32: =+AI32 -> 11375 | AK32: =AJ32*(1+C$59) -> 11943.75 | AL32: =+AK32 -> 11943.75 | AM32: =+AL32 -> 11943.75 | AN32: =+AM32 -> 11943.75 | AO32: =+AN32 -> 11943.75 | AP32: =+AO32 -> 11943.75 | AQ32: =+AP32 -> 11943.75 | AR32: =+AQ32 -> 11943.75 | AS32: =+AR32 -> 11943.75 | ... AV32: =+AU32 -> 11943.75 | AW32: =AV32*(1+C$59) -> 12540.938 | AX32: =+AW32 -> 12540.938 | AY32: =+AX32 -> 12540.938 | AZ32: =+AY32 -> 12540.938 | BA32: =+AZ32 -> 12540.938 | BB32: =+BA32 -> 12540.938 | BC32: =+BB32 -> 12540.938 | BD32: =+BC32 -> 12540.938 | BE32: =+BD32 -> 12540.938 | ... BH32: =+BG32 -> 12540.938 | BI32: =BH32*(1+C$59) -> 13167.984 | BJ32: =+BI32 -> 13167.984 | BK32: =+BJ32 -> 13167.984 | BL32: =+BK32 -> 13167.984 | BM32: =+BL32 -> 13167.984 | BN32: =+BM32 -> 13167.984 | BO32: =+BN32 -> 13167.984 | BP32: =+BO32 -> 13167.984 | BQ32: =+BP32 -> 13167.984 | ... BT32: =+BS32 -> 13167.984
B33: AI Engineer | C33: 130000 | M33: 0 | N33: 0 | O33: 0 | P33: 0 | Q33: =0 -> 0 | R33: =C33/12 -> 10833.333 | S33: =+R33 -> 10833.333 | T33: =+S33 -> 10833.333 | U33: =+T33 -> 10833.333 | V33: =+U33 -> 10833.333 | W33: =+V33 -> 10833.333 | X33: =+W33 -> 10833.333 | Y33: =X33*(1+C$59) -> 11375 | Z33: =+Y33 -> 11375 | AA33: =+Z33 -> 11375 | AB33: =+AA33 -> 11375 | AC33: =+AB33 -> 11375 | AD33: =+AC33 -> 11375 | AE33: =+AD33 -> 11375 | AF33: =+AE33 -> 11375 | AG33: =+AF33 -> 11375 | ... AJ33: =+AI33 -> 11375 | AK33: =AJ33*(1+C$59) -> 11943.75 | AL33: =+AK33 -> 11943.75 | AM33: =+AL33 -> 11943.75 | AN33: =+AM33 -> 11943.75 | AO33: =+AN33 -> 11943.75 | AP33: =+AO33 -> 11943.75 | AQ33: =+AP33 -> 11943.75 | AR33: =+AQ33 -> 11943.75 | AS33: =+AR33 -> 11943.75 | ... AV33: =+AU33 -> 11943.75 | AW33: =AV33*(1+C$59) -> 12540.938 | AX33: =+AW33 -> 12540.938 | AY33: =+AX33 -> 12540.938 | AZ33: =+AY33 -> 12540.938 | BA33: =+AZ33 -> 12540.938 | BB33: =+BA33 -> 12540.938 | BC33: =+BB33 -> 12540.938 | BD33: =+BC33 -> 12540.938 | BE33: =+BD33 -> 12540.938 | ... BH33: =+BG33 -> 12540.938 | BI33: =BH33*(1+C$59) -> 13167.984 | BJ33: =+BI33 -> 13167.984 | BK33: =+BJ33 -> 13167.984 | BL33: =+BK33 -> 13167.984 | BM33: =+BL33 -> 13167.984 | BN33: =+BM33 -> 13167.984 | BO33: =+BN33 -> 13167.984 | BP33: =+BO33 -> 13167.984 | BQ33: =+BP33 -> 13167.984 | ... BT33: =+BS33 -> 13167.984
B34: AI Engineer | C34: 130000 | M34: 0 | N34: 0 | O34: 0 | P34: 0 | Q34: 0 | R34: 0 | S34: 0 | T34: 0 | U34: 0 | V34: 0 | W34: 0 | X34: 0 | Y34: =C34/12 -> 10833.333 | Z34: =+Y34 -> 10833.333 | AA34: =+Z34 -> 10833.333 | AB34: =+AA34 -> 10833.333 | AC34: =+AB34 -> 10833.333 | AD34: =+AC34 -> 10833.333 | AE34: =+AD34 -> 10833.333 | AF34: =+AE34 -> 10833.333 | AG34: =+AF34 -> 10833.333 | ... AJ34: =+AI34 -> 10833.333 | AK34: =AJ34*(1+C$59) -> 11375 | AL34: =+AK34 -> 11375 | AM34: =+AL34 -> 11375 | AN34: =+AM34 -> 11375 | AO34: =+AN34 -> 11375 | AP34: =+AO34 -> 11375 | AQ34: =+AP34 -> 11375 | AR34: =+AQ34 -> 11375 | AS34: =+AR34 -> 11375 | ... AV34: =+AU34 -> 11375 | AW34: =AV34*(1+C$59) -> 11943.75 | AX34: =+AW34 -> 11943.75 | AY34: =+AX34 -> 11943.75 | AZ34: =+AY34 -> 11943.75 | BA34: =+AZ34 -> 11943.75 | BB34: =+BA34 -> 11943.75 | BC34: =+BB34 -> 11943.75 | BD34: =+BC34 -> 11943.75 | BE34: =+BD34 -> 11943.75 | ... BH34: =+BG34 -> 11943.75 | BI34: =BH34*(1+C$59) -> 12540.938 | BJ34: =+BI34 -> 12540.938 | BK34: =+BJ34 -> 12540.938 | BL34: =+BK34 -> 12540.938 | BM34: =+BL34 -> 12540.938 | BN34: =+BM34 -> 12540.938 | BO34: =+BN34 -> 12540.938 | BP34: =+BO34 -> 12540.938 | BQ34: =+BP34 -> 12540.938 | ... BT34: =+BS34 -> 12540.938
B35: AI Engineer | C35: 130000 | M35: 0 | N35: 0 | O35: 0 | P35: 0 | Q35: 0 | R35: 0 | S35: 0 | T35: 0 | U35: 0 | V35: 0 | W35: 0 | X35: 0 | Y35: 0 | Z35: 0 | AA35: 0 | AB35: 0 | AC35: 0 | AD35: 0 | AE35: 0 | AF35: 0 | AG35: 0 | AH35: 0 | AI35: 0 | AJ35: 0 | AK35: 0 | AL35: 0 | AM35: =C35/12 -> 10833.333 | AN35: =+AM35 -> 10833.333 | AO35: =+AN35 -> 10833.333 | AP35: =+AO35 -> 10833.333 | AQ35: =+AP35 -> 10833.333 | AR35: =+AQ35 -> 10833.333 | AS35: =+AR35 -> 10833.333 | AT35: =+AS35 -> 10833.333 | AU35: =+AT35 -> 10833.333 | AV35: =+AU35 -> 10833.333 | AW35: =AV35*(1+C$59) -> 11375 | AX35: =+AW35 -> 11375 | AY35: =+AX35 -> 11375 | AZ35: =+AY35 -> 11375 | BA35: =+AZ35 -> 11375 | BB35: =+BA35 -> 11375 | BC35: =+BB35 -> 11375 | BD35: =+BC35 -> 11375 | BE35: =+BD35 -> 11375 | ... BH35: =+BG35 -> 11375 | BI35: =BH35*(1+C$59) -> 11943.75 | BJ35: =+BI35 -> 11943.75 | BK35: =+BJ35 -> 11943.75 | BL35: =+BK35 -> 11943.75 | BM35: =+BL35 -> 11943.75 | BN35: =+BM35 -> 11943.75 | BO35: =+BN35 -> 11943.75 | BP35: =+BO35 -> 11943.75 | BQ35: =+BP35 -> 11943.75 | ... BT35: =+BS35 -> 11943.75
B36: AI Engineer | C36: 130000 | M36: 0 | N36: 0 | O36: 0 | P36: 0 | Q36: 0 | R36: 0 | S36: 0 | T36: 0 | U36: 0 | V36: 0 | W36: 0 | X36: 0 | Y36: 0 | Z36: 0 | AA36: 0 | AB36: 0 | AC36: 0 | AD36: 0 | AE36: 0 | AF36: 0 | AG36: 0 | AH36: 0 | AI36: 0 | AJ36: 0 | AK36: 0 | AL36: 0 | AM36: 0 | AN36: 0 | AO36: 0 | AP36: 0 | AQ36: 0 | AR36: =C36/12 -> 10833.333 | AS36: =+AR36 -> 10833.333 | AT36: =+AS36 -> 10833.333 | AU36: =+AT36 -> 10833.333 | AV36: =+AU36 -> 10833.333 | AW36: =AV36*(1+C$59) -> 11375 | AX36: =+AW36 -> 11375 | AY36: =+AX36 -> 11375 | AZ36: =+AY36 -> 11375 | BA36: =+AZ36 -> 11375 | BB36: =+BA36 -> 11375 | BC36: =+BB36 -> 11375 | BD36: =+BC36 -> 11375 | BE36: =+BD36 -> 11375 | ... BH36: =+BG36 -> 11375 | BI36: =BH36*(1+C$59) -> 11943.75 | BJ36: =+BI36 -> 11943.75 | BK36: =+BJ36 -> 11943.75 | BL36: =+BK36 -> 11943.75 | BM36: =+BL36 -> 11943.75 | BN36: =+BM36 -> 11943.75 | BO36: =+BN36 -> 11943.75 | BP36: =+BO36 -> 11943.75 | BQ36: =+BP36 -> 11943.75 | ... BT36: =+BS36 -> 11943.75
B37: AI Engineer | C37: 130000 | M37: 0 | N37: 0 | O37: 0 | P37: 0 | Q37: 0 | R37: 0 | S37: 0 | T37: 0 | U37: 0 | V37: 0 | W37: 0 | X37: 0 | Y37: 0 | Z37: 0 | AA37: 0 | AB37: 0 | AC37: 0 | AD37: 0 | AE37: 0 | AF37: 0 | AG37: 0 | AH37: 0 | AI37: 0 | AJ37: 0 | AK37: 0 | AL37: 0 | AM37: 0 | AN37: 0 | AO37: 0 | AP37: 0 | AQ37: 0 | AR37: 0 | AS37: 0 | AT37: 0 | AU37: 0 | AV37: 0 | AW37: 0 | AX37: =+AW37 -> 0 | AY37: =+AX37 -> 0 | AZ37: =+AY37 -> 0 | BA37: =+AZ37 -> 0 | BB37: =+BA37 -> 0 | BC37: =+BB37 -> 0 | BD37: =+BC37 -> 0 | BE37: =+BD37 -> 0 | BF37: =+BE37 -> 0 | BG37: =C37/12 -> 10833.333 | BH37: =+BG37 -> 10833.333 | BI37: =BH37*(1+C$59) -> 11375 | BJ37: =+BI37 -> 11375 | BK37: =+BJ37 -> 11375 | BL37: =+BK37 -> 11375 | BM37: =+BL37 -> 11375 | BN37: =+BM37 -> 11375 | BO37: =+BN37 -> 11375 | BP37: =+BO37 -> 11375 | BQ37: =+BP37 -> 11375 | ... BT37: =+BS37 -> 11375
B38: Full Stack Engineer | C38: 130000 | M38: 0 | N38: 0 | O38: 0 | P38: =C38/12 -> 10833.333 | Q38: =+P38 -> 10833.333 | R38: =+Q38 -> 10833.333 | S38: =+R38 -> 10833.333 | T38: =+S38 -> 10833.333 | U38: =+T38 -> 10833.333 | V38: =+U38 -> 10833.333 | W38: =+V38 -> 10833.333 | X38: =+W38 -> 10833.333 | Y38: =X38*(1+C$59) -> 11375 | Z38: =+Y38 -> 11375 | AA38: =+Z38 -> 11375 | AB38: =+AA38 -> 11375 | AC38: =+AB38 -> 11375 | AD38: =+AC38 -> 11375 | AE38: =+AD38 -> 11375 | AF38: =+AE38 -> 11375 | AG38: =+AF38 -> 11375 | ... AJ38: =+AI38 -> 11375 | AK38: =AJ38*(1+$C$59) -> 11943.75 | AL38: =+AK38 -> 11943.75 | AM38: =+AL38 -> 11943.75 | AN38: =+AM38 -> 11943.75 | AO38: =+AN38 -> 11943.75 | AP38: =+AO38 -> 11943.75 | AQ38: =+AP38 -> 11943.75 | AR38: =+AQ38 -> 11943.75 | AS38: =+AR38 -> 11943.75 | ... AV38: =+AU38 -> 11943.75 | AW38: =AV38*(1+C$59) -> 12540.938 | AX38: =+AW38 -> 12540.938 | AY38: =+AX38 -> 12540.938 | AZ38: =+AY38 -> 12540.938 | BA38: =+AZ38 -> 12540.938 | BB38: =+BA38 -> 12540.938 | BC38: =+BB38 -> 12540.938 | BD38: =+BC38 -> 12540.938 | BE38: =+BD38 -> 12540.938 | ... BH38: =+BG38 -> 12540.938 | BI38: =BH38*(1+C$59) -> 13167.984 | BJ38: =+BI38 -> 13167.984 | BK38: =+BJ38 -> 13167.984 | BL38: =+BK38 -> 13167.984 | BM38: =+BL38 -> 13167.984 | BN38: =+BM38 -> 13167.984 | BO38: =+BN38 -> 13167.984 | BP38: =+BO38 -> 13167.984 | BQ38: =+BP38 -> 13167.984 | ... BT38: =+BS38 -> 13167.984
B39: Front End Engineer | C39: 133000 | M39: 0 | N39: 0 | O39: 0 | P39: 0 | Q39: 0 | R39: 0 | S39: 0 | T39: 0 | U39: 0 | V39: 0 | W39: 0 | X39: 0 | Y39: 0 | Z39: 0 | AA39: 0 | AB39: 0 | AC39: 0 | AD39: =C39/12 -> 11083.333 | AE39: =+AD39 -> 11083.333 | AF39: =+AE39 -> 11083.333 | AG39: =+AF39 -> 11083.333 | AH39: =+AG39 -> 11083.333 | AI39: =+AH39 -> 11083.333 | AJ39: =+AI39 -> 11083.333 | AK39: =AJ39*(1+C$59) -> 11637.5 | AL39: =+AK39 -> 11637.5 | AM39: =+AL39 -> 11637.5 | AN39: =+AM39 -> 11637.5 | AO39: =+AN39 -> 11637.5 | AP39: =+AO39 -> 11637.5 | AQ39: =+AP39 -> 11637.5 | AR39: =+AQ39 -> 11637.5 | AS39: =+AR39 -> 11637.5 | ... AV39: =+AU39 -> 11637.5 | AW39: =AV39*(1+$C$59) -> 12219.375 | AX39: =+AW39 -> 12219.375 | AY39: =+AX39 -> 12219.375 | AZ39: =+AY39 -> 12219.375 | BA39: =+AZ39 -> 12219.375 | BB39: =+BA39 -> 12219.375 | BC39: =+BB39 -> 12219.375 | BD39: =+BC39 -> 12219.375 | BE39: =+BD39 -> 12219.375 | ... BH39: =+BG39 -> 12219.375 | BI39: =BH39*(1+$C$59) -> 12830.344 | BJ39: =+BI39 -> 12830.344 | BK39: =+BJ39 -> 12830.344 | BL39: =+BK39 -> 12830.344 | BM39: =+BL39 -> 12830.344 | BN39: =+BM39 -> 12830.344 | BO39: =+BN39 -> 12830.344 | BP39: =+BO39 -> 12830.344 | BQ39: =+BP39 -> 12830.344 | ... BT39: =+BS39 -> 12830.344
B40: Front End Engineer | C40: 133000 | M40: 0 | N40: 0 | O40: 0 | P40: 0 | Q40: 0 | R40: 0 | S40: 0 | T40: 0 | U40: 0 | V40: 0 | W40: 0 | X40: 0 | Y40: 0 | Z40: 0 | AA40: 0 | AB40: 0 | AC40: 0 | AD40: 0 | AE40: 0 | AF40: 0 | AG40: 0 | AH40: 0 | AI40: 0 | AJ40: 0 | AK40: 0 | AL40: 0 | AM40: 0 | AN40: 0 | AO40: 0 | AP40: 0 | AQ40: 0 | AR40: 0 | AS40: 0 | AT40: 0 | AU40: 0 | AV40: 0 | AW40: 0 | AX40: =+AW40 -> 0 | AY40: =+AX40 -> 0 | AZ40: =+AY40 -> 0 | BA40: =+AZ40 -> 0 | BB40: =+BA40 -> 0 | BC40: =+BB40 -> 0 | BD40: =+BC40 -> 0 | BE40: =C40/12 -> 11083.333 | BF40: =+BE40 -> 11083.333 | BG40: =+BF40 -> 11083.333 | BH40: =+BG40 -> 11083.333 | BI40: =BH40*(1+$C$59) -> 11637.5 | BJ40: =+BI40 -> 11637.5 | BK40: =+BJ40 -> 11637.5 | BL40: =+BK40 -> 11637.5 | BM40: =+BL40 -> 11637.5 | BN40: =+BM40 -> 11637.5 | BO40: =+BN40 -> 11637.5 | BP40: =+BO40 -> 11637.5 | BQ40: =+BP40 -> 11637.5 | ... BT40: =+BS40 -> 11637.5
B41: Back End Engineer | C41: 145000 | M41: 0 | N41: 0 | O41: 0 | P41: 0 | Q41: 0 | R41: 0 | S41: 0 | T41: 0 | U41: 0 | V41: 0 | W41: 0 | X41: 0 | Y41: 0 | Z41: =+Y41 -> 0 | AA41: =C41/12 -> 12083.333 | AB41: =+AA41 -> 12083.333 | AC41: =+AB41 -> 12083.333 | AD41: =+AC41 -> 12083.333 | AE41: =+AD41 -> 12083.333 | AF41: =+AE41 -> 12083.333 | AG41: =+AF41 -> 12083.333 | AH41: =+AG41 -> 12083.333 | AI41: =+AH41 -> 12083.333 | AJ41: =+AI41 -> 12083.333 | AK41: =AJ41*(1+$C$59) -> 12687.5 | AL41: =+AK41 -> 12687.5 | AM41: =+AL41 -> 12687.5 | AN41: =+AM41 -> 12687.5 | AO41: =+AN41 -> 12687.5 | AP41: =+AO41 -> 12687.5 | AQ41: =+AP41 -> 12687.5 | AR41: =+AQ41 -> 12687.5 | AS41: =+AR41 -> 12687.5 | ... AV41: =+AU41 -> 12687.5 | AW41: =AV41*(1+C59) -> 13321.875 | AX41: =+AW41 -> 13321.875 | AY41: =+AX41 -> 13321.875 | AZ41: =+AY41 -> 13321.875 | BA41: =+AZ41 -> 13321.875 | BB41: =+BA41 -> 13321.875 | BC41: =+BB41 -> 13321.875 | BD41: =+BC41 -> 13321.875 | BE41: =+BD41 -> 13321.875 | ... BH41: =+BG41 -> 13321.875 | BI41: =BH41*(1+$C$59) -> 13987.969 | BJ41: =+BI41 -> 13987.969 | BK41: =+BJ41 -> 13987.969 | BL41: =+BK41 -> 13987.969 | BM41: =+BL41 -> 13987.969 | BN41: =+BM41 -> 13987.969 | BO41: =+BN41 -> 13987.969 | BP41: =+BO41 -> 13987.969 | BQ41: =+BP41 -> 13987.969 | ... BT41: =+BS41 -> 13987.969
B42: Back End Engineer | C42: 145000 | M42: 0 | N42: 0 | O42: 0 | P42: 0 | Q42: 0 | R42: 0 | S42: 0 | T42: 0 | U42: 0 | V42: 0 | W42: 0 | X42: 0 | Y42: 0 | Z42: 0 | AA42: 0 | AB42: 0 | AC42: 0 | AD42: 0 | AE42: 0 | AF42: 0 | AG42: 0 | AH42: 0 | AI42: 0 | AJ42: 0 | AK42: 0 | AL42: 0 | AM42: 0 | AN42: 0 | AO42: 0 | AP42: 0 | AQ42: 0 | AR42: 0 | AS42: 0 | AT42: 0 | AU42: 0 | AV42: 0 | AW42: 0 | AX42: =+AW42 -> 0 | AY42: =+AX42 -> 0 | AZ42: =+AY42 -> 0 | BA42: =+AZ42 -> 0 | BB42: =+BA42 -> 0 | BC42: =C42/12 -> 12083.333 | BD42: =+BC42 -> 12083.333 | BE42: =+BD42 -> 12083.333 | BF42: =+BE42 -> 12083.333 | BG42: =+BF42 -> 12083.333 | BH42: =+BG42 -> 12083.333 | BI42: =BH42*(1+$C$59) -> 12687.5 | BJ42: =+BI42 -> 12687.5 | BK42: =+BJ42 -> 12687.5 | BL42: =+BK42 -> 12687.5 | BM42: =+BL42 -> 12687.5 | BN42: =+BM42 -> 12687.5 | BO42: =+BN42 -> 12687.5 | BP42: =+BO42 -> 12687.5 | BQ42: =+BP42 -> 12687.5 | ... BT42: =+BS42 -> 12687.5
B43: Quality Engineer | C43: 90000 | M43: 0 | N43: 0 | O43: 0 | P43: 0 | Q43: 0 | R43: 0 | S43: 0 | T43: 0 | U43: 0 | V43: 0 | W43: 0 | X43: 0 | Y43: 0 | Z43: 0 | AA43: 0 | AB43: 0 | AC43: 0 | AD43: 0 | AE43: 0 | AF43: 0 | AG43: 0 | AH43: 0 | AI43: 0 | AJ43: 0 | AK43: 0 | AL43: =C43/12 -> 7500 | AM43: =+AL43 -> 7500 | AN43: =+AM43 -> 7500 | AO43: =+AN43 -> 7500 | AP43: =+AO43 -> 7500 | AQ43: =+AP43 -> 7500 | AR43: =+AQ43 -> 7500 | AS43: =+AR43 -> 7500 | AT43: =+AS43 -> 7500 | ... AV43: =+AU43 -> 7500 | AW43: =AV43*(1+$C$59) -> 7875 | AX43: =+AW43 -> 7875 | AY43: =+AX43 -> 7875 | AZ43: =+AY43 -> 7875 | BA43: =+AZ43 -> 7875 | BB43: =+BA43 -> 7875 | BC43: =+BB43 -> 7875 | BD43: =+BC43 -> 7875 | BE43: =+BD43 -> 7875 | ... BH43: =+BG43 -> 7875 | BI43: =BH43*(1+$C$59) -> 8268.75 | BJ43: =+BI43 -> 8268.75 | BK43: =+BJ43 -> 8268.75 | BL43: =+BK43 -> 8268.75 | BM43: =+BL43 -> 8268.75 | BN43: =+BM43 -> 8268.75 | BO43: =+BN43 -> 8268.75 | BP43: =+BO43 -> 8268.75 | BQ43: =+BP43 -> 8268.75 | ... BT43: =+BS43 -> 8268.75
B44: Security | C44: 90000 | M44: 0 | N44: 0 | O44: 0 | P44: 0 | Q44: 0 | R44: 0 | S44: 0 | T44: 0 | U44: 0 | V44: 0 | W44: 0 | X44: 0 | Y44: 0 | Z44: 0 | AA44: 0 | AB44: 0 | AC44: 0 | AD44: 0 | AE44: 0 | AF44: 0 | AG44: 0 | AH44: 0 | AI44: 0 | AJ44: 0 | AK44: 0 | AL44: 0 | AM44: 0 | AN44: 0 | AO44: =C44/12 -> 7500 | AP44: =+AO44 -> 7500 | AQ44: =+AP44 -> 7500 | AR44: =+AQ44 -> 7500 | AS44: =+AR44 -> 7500 | AT44: =+AS44 -> 7500 | AU44: =+AT44 -> 7500 | AV44: =+AU44 -> 7500 | AW44: =AV44*(1+$C$59) -> 7875 | AX44: =+AW44 -> 7875 | AY44: =+AX44 -> 7875 | AZ44: =+AY44 -> 7875 | BA44: =+AZ44 -> 7875 | BB44: =+BA44 -> 7875 | BC44: =+BB44 -> 7875 | BD44: =+BC44 -> 7875 | BE44: =+BD44 -> 7875 | ... BH44: =+BG44 -> 7875 | BI44: =BH44*(1+$C$59) -> 8268.75 | BJ44: =+BI44 -> 8268.75 | BK44: =+BJ44 -> 8268.75 | BL44: =+BK44 -> 8268.75 | BM44: =+BL44 -> 8268.75 | BN44: =+BM44 -> 8268.75 | BO44: =+BN44 -> 8268.75 | BP44: =+BO44 -> 8268.75 | BQ44: =+BP44 -> 8268.75 | ... BT44: =+BS44 -> 8268.75
B45: Dev Ops Engineer | C45: 125000 | M45: 0 | N45: 0 | O45: 0 | P45: 0 | Q45: 0 | R45: 0 | S45: 0 | T45: 0 | U45: 0 | V45: 0 | W45: 0 | X45: 0 | Y45: 0 | Z45: 0 | AA45: 0 | AB45: =C45/12 -> 10416.667 | AC45: =+AB45 -> 10416.667 | AD45: =+AC45 -> 10416.667 | AE45: =+AD45 -> 10416.667 | AF45: =+AE45 -> 10416.667 | AG45: =+AF45 -> 10416.667 | AH45: =+AG45 -> 10416.667 | AI45: =+AH45 -> 10416.667 | AJ45: =+AI45 -> 10416.667 | AK45: =AJ45*(1+$C$59) -> 10937.5 | AL45: =+AK45 -> 10937.5 | AM45: =+AL45 -> 10937.5 | AN45: =+AM45 -> 10937.5 | AO45: =+AN45 -> 10937.5 | AP45: =+AO45 -> 10937.5 | AQ45: =+AP45 -> 10937.5 | AR45: =+AQ45 -> 10937.5 | AS45: =+AR45 -> 10937.5 | ... AV45: =+AU45 -> 10937.5 | AW45: =AV45*(1+$C$59) -> 11484.375 | AX45: =+AW45 -> 11484.375 | AY45: =+AX45 -> 11484.375 | AZ45: =+AY45 -> 11484.375 | BA45: =+AZ45 -> 11484.375 | BB45: =+BA45 -> 11484.375 | BC45: =+BB45 -> 11484.375 | BD45: =+BC45 -> 11484.375 | BE45: =+BD45 -> 11484.375 | ... BH45: =+BG45 -> 11484.375 | BI45: =BH45*(1+$C$59) -> 12058.594 | BJ45: =+BI45 -> 12058.594 | BK45: =+BJ45 -> 12058.594 | BL45: =+BK45 -> 12058.594 | BM45: =+BL45 -> 12058.594 | BN45: =+BM45 -> 12058.594 | BO45: =+BN45 -> 12058.594 | BP45: =+BO45 -> 12058.594 | BQ45: =+BP45 -> 12058.594 | ... BT45: =+BS45 -> 12058.594
B46: UX/UI Designer | C46: 115000 | M46: 0 | N46: 0 | O46: 0 | P46: 0 | Q46: 0 | R46: 0 | S46: 0 | T46: 0 | U46: 0 | V46: 0 | W46: 0 | X46: 0 | Y46: 0 | Z46: 0 | AA46: 0 | AB46: 0 | AC46: 0 | AD46: 0 | AE46: 0 | AF46: 0 | AG46: 0 | AH46: 0 | AI46: 0 | AJ46: 0 | AK46: 0 | AL46: =+AK46 -> 0 | AM46: =+AL46 -> 0 | AN46: =+AM46 -> 0 | AO46: =+AN46 -> 0 | AP46: =+AO46 -> 0 | AQ46: =+AP46 -> 0 | AR46: =+AQ46 -> 0 | AS46: =+AR46 -> 0 | ... AV46: =+AU46 -> 0 | AW46: =C46/12 -> 9583.3333 | AX46: =+AW46 -> 9583.3333 | AY46: =+AX46 -> 9583.3333 | AZ46: =+AY46 -> 9583.3333 | BA46: =+AZ46 -> 9583.3333 | BB46: =+BA46 -> 9583.3333 | BC46: =+BB46 -> 9583.3333 | BD46: =+BC46 -> 9583.3333 | BE46: =+BD46 -> 9583.3333 | ... BH46: =+BG46 -> 9583.3333 | BI46: =BH46*(1+C$59) -> 10062.5 | BJ46: =+BI46 -> 10062.5 | BK46: =+BJ46 -> 10062.5 | BL46: =+BK46 -> 10062.5 | BM46: =+BL46 -> 10062.5 | BN46: =+BM46 -> 10062.5 | BO46: =+BN46 -> 10062.5 | BP46: =+BO46 -> 10062.5 | BQ46: =+BP46 -> 10062.5 | ... BT46: =+BS46 -> 10062.5
B47: Front End Engineer Intern | C47: 50000 | M47: 0 | N47: 0 | O47: 0 | P47: 0 | Q47: 0 | R47: 0 | S47: 0 | T47: 0 | U47: 0 | V47: 0 | W47: 0 | X47: 0 | Y47: 0 | Z47: 0 | AA47: 0 | AB47: 0 | AC47: 0 | AD47: 0 | AE47: =C47/12 -> 4166.6667 | AF47: =+AE47 -> 4166.6667 | AG47: =+AF47 -> 4166.6667 | AH47: =+AG47 -> 4166.6667 | AI47: =+AH47 -> 4166.6667 | AJ47: =+AI47 -> 4166.6667 | AK47: =AJ47*(1+$C$59) -> 4375 | AL47: =+AK47 -> 4375 | AM47: =+AL47 -> 4375 | AN47: =+AM47 -> 4375 | AO47: =+AN47 -> 4375 | AP47: =+AO47 -> 4375 | AQ47: =+AP47 -> 4375 | AR47: =+AQ47 -> 4375 | AS47: =+AR47 -> 4375 | ... AV47: =+AU47 -> 4375 | AW47: =AV47*(1+$C$59) -> 4593.75 | AX47: =+AW47 -> 4593.75 | AY47: =+AX47 -> 4593.75 | AZ47: =+AY47 -> 4593.75 | BA47: =+AZ47 -> 4593.75 | BB47: =+BA47 -> 4593.75 | BC47: =+BB47 -> 4593.75 | BD47: =+BC47 -> 4593.75 | BE47: =+BD47 -> 4593.75 | ... BH47: =+BG47 -> 4593.75 | BI47: =BH47*(1+C$59) -> 4823.4375 | BJ47: =+BI47 -> 4823.4375 | BK47: =+BJ47 -> 4823.4375 | BL47: =+BK47 -> 4823.4375 | BM47: =+BL47 -> 4823.4375 | BN47: =+BM47 -> 4823.4375 | BO47: =+BN47 -> 4823.4375 | BP47: =+BO47 -> 4823.4375 | BQ47: =+BP47 -> 4823.4375 | ... BT47: =+BS47 -> 4823.4375
B48: Back End Engineer Intern | C48: 50000 | M48: 0 | N48: 0 | O48: 0 | P48: 0 | Q48: 0 | R48: 0 | S48: 0 | T48: 0 | U48: 0 | V48: 0 | W48: 0 | X48: 0 | Y48: 0 | Z48: 0 | AA48: 0 | AB48: 0 | AC48: 0 | AD48: 0 | AE48: =C48/12 -> 4166.6667 | AF48: =+AE48 -> 4166.6667 | AG48: =+AF48 -> 4166.6667 | AH48: =+AG48 -> 4166.6667 | AI48: =+AH48 -> 4166.6667 | AJ48: =+AI48 -> 4166.6667 | AK48: =AJ48*(1+$C$59) -> 4375 | AL48: =+AK48 -> 4375 | AM48: =+AL48 -> 4375 | AN48: =+AM48 -> 4375 | AO48: =+AN48 -> 4375 | AP48: =+AO48 -> 4375 | AQ48: =+AP48 -> 4375 | AR48: =+AQ48 -> 4375 | AS48: =+AR48 -> 4375 | ... AV48: =+AU48 -> 4375 | AW48: =AV48*(1+$C$59) -> 4593.75 | AX48: =+AW48 -> 4593.75 | AY48: =+AX48 -> 4593.75 | AZ48: =+AY48 -> 4593.75 | BA48: =+AZ48 -> 4593.75 | BB48: =+BA48 -> 4593.75 | BC48: =+BB48 -> 4593.75 | BD48: =+BC48 -> 4593.75 | BE48: =+BD48 -> 4593.75 | ... BH48: =+BG48 -> 4593.75 | BI48: =BH48*(1+C$59) -> 4823.4375 | BJ48: =+BI48 -> 4823.4375 | BK48: =+BJ48 -> 4823.4375 | BL48: =+BK48 -> 4823.4375 | BM48: =+BL48 -> 4823.4375 | BN48: =+BM48 -> 4823.4375 | BO48: =+BN48 -> 4823.4375 | BP48: =+BO48 -> 4823.4375 | BQ48: =+BP48 -> 4823.4375 | ... BT48: =+BS48 -> 4823.4375
B49: AI Engineer Intern (Summer) | C49: 48000 | M49: 0 | N49: 0 | O49: 0 | P49: 0 | Q49: 0 | R49: 0 | S49: 0 | T49: 0 | U49: 0 | V49: 0 | W49: 0 | X49: 0 | Y49: 0 | Z49: 0 | AA49: 0 | AB49: 0 | AC49: 0 | AD49: 0 | AE49: =+AD49 -> 0 | AF49: =+AE49 -> 0 | AG49: =+AF49 -> 0 | AH49: =+AG49 -> 0 | AI49: =+AH49 -> 0 | AJ49: =+AI49 -> 0 | AK49: 0 | AL49: =+AK49 -> 0 | AM49: =+AL49 -> 0 | AN49: =+AM49 -> 0 | AO49: =C49/12 -> 4000 | AP49: =+AO49 -> 4000 | AQ49: =+AP49 -> 4000 | AR49: =+AQ49 -> 4000 | AS49: =+AR49 -> 4000 | AT49: 0 | AU49: =+AT49 -> 0 | AV49: =+AU49 -> 0 | AW49: 0 | AX49: 0 | AY49: 0 | AZ49: 0 | BA49: 0 | BB49: 0 | BC49: 0 | BD49: 0 | BE49: 0 | BF49: 0 | BG49: 0 | BH49: 0 | BI49: 0 | BJ49: 0 | BK49: 0 | BL49: 0 | BM49: 0 | BN49: 0 | BO49: 0 | BP49: 0 | BQ49: 0 | BR49: 0 | BS49: 0 | BT49: 0
B50: Data Engineer | C50: 130000 | M50: 0 | N50: 0 | O50: 0 | P50: 0 | Q50: 0 | R50: 0 | S50: 0 | T50: 0 | U50: 0 | V50: 0 | W50: 0 | X50: 0 | Y50: 0 | Z50: 0 | AA50: 0 | AB50: 0 | AC50: 0 | AD50: 0 | AE50: 0 | AF50: 0 | AG50: 0 | AH50: 0 | AI50: 0 | AJ50: 0 | AK50: 0 | AL50: 0 | AM50: 0 | AN50: 0 | AO50: 0 | AP50: 0 | AQ50: 0 | AR50: 0 | AS50: 0 | AT50: 0 | AU50: 0 | AV50: 0 | AW50: 0 | AX50: =+AW50 -> 0 | AY50: =+AX50 -> 0 | AZ50: =+AY50 -> 0 | BA50: =C50/12 -> 10833.333 | BB50: =+BA50 -> 10833.333 | BC50: =+BB50 -> 10833.333 | BD50: =+BC50 -> 10833.333 | BE50: =+BD50 -> 10833.333 | BF50: =+BE50 -> 10833.333 | BG50: =+BF50 -> 10833.333 | BH50: =+BG50 -> 10833.333 | BI50: =BH50*(1+$C$59) -> 11375 | BJ50: =+BI50 -> 11375 | BK50: =+BJ50 -> 11375 | BL50: =+BK50 -> 11375 | BM50: =+BL50 -> 11375 | BN50: =+BM50 -> 11375 | BO50: =+BN50 -> 11375 | BP50: =+BO50 -> 11375 | BQ50: =+BP50 -> 11375 | ... BT50: =+BS50 -> 11375
B51: Customer Success Engineer | C51: 75000 | M51: 0 | N51: 0 | O51: 0 | P51: 0 | Q51: 0 | R51: 0 | S51: 0 | T51: 0 | U51: 0 | V51: 0 | W51: 0 | X51: 0 | Y51: 0 | Z51: 0 | AA51: 0 | AB51: 0 | AC51: 0 | AD51: 0 | AE51: 0 | AF51: 0 | AG51: 0 | AH51: 0 | AI51: 0 | AJ51: 0 | AK51: 0 | AL51: 0 | AM51: 0 | AN51: 0 | AO51: 0 | AP51: 0 | AQ51: 0 | AR51: 0 | AS51: =C51/12 -> 6250 | AT51: =+AS51 -> 6250 | AU51: =+AT51 -> 6250 | AV51: =+AU51 -> 6250 | AW51: =AV51*(1+$C$59) -> 6562.5 | AX51: =+AW51 -> 6562.5 | AY51: =+AX51 -> 6562.5 | AZ51: =+AY51 -> 6562.5 | BA51: =+AZ51 -> 6562.5 | BB51: =+BA51 -> 6562.5 | BC51: =+BB51 -> 6562.5 | BD51: =+BC51 -> 6562.5 | BE51: =+BD51 -> 6562.5 | ... BH51: =+BG51 -> 6562.5 | BI51: =BH51*(1+$C$59) -> 6890.625 | BJ51: =+BI51 -> 6890.625 | BK51: =+BJ51 -> 6890.625 | BL51: =+BK51 -> 6890.625 | BM51: =+BL51 -> 6890.625 | BN51: =+BM51 -> 6890.625 | BO51: =+BN51 -> 6890.625 | BP51: =+BO51 -> 6890.625 | BQ51: =+BP51 -> 6890.625 | ... BT51: =+BS51 -> 6890.625
B52: Project Manager | C52: 150000 | M52: 0 | N52: 0 | O52: 0 | P52: 0 | Q52: 0 | R52: 0 | S52: 0 | T52: 0 | U52: 0 | V52: 0 | W52: 0 | X52: 0 | Y52: 0 | Z52: 0 | AA52: 0 | AB52: 0 | AC52: 0 | AD52: 0 | AE52: 0 | AF52: 0 | AG52: 0 | AH52: 0 | AI52: 0 | AJ52: 0 | AK52: 0 | AL52: 0 | AM52: 0 | AN52: 0 | AO52: 0 | AP52: =C52/12 -> 12500 | AQ52: =+AP52 -> 12500 | AR52: =+AQ52 -> 12500 | AS52: =+AR52 -> 12500 | AT52: =+AS52 -> 12500 | AU52: =+AT52 -> 12500 | AV52: =+AU52 -> 12500 | AW52: =AV52*(1+$C$59) -> 13125 | AX52: =+AW52 -> 13125 | AY52: =+AX52 -> 13125 | AZ52: =+AY52 -> 13125 | BA52: =+AZ52 -> 13125 | BB52: =+BA52 -> 13125 | BC52: =+BB52 -> 13125 | BD52: =+BC52 -> 13125 | BE52: =+BD52 -> 13125 | ... BH52: =+BG52 -> 13125 | BI52: =BH52*(1+$C$59) -> 13781.25 | BJ52: =+BI52 -> 13781.25 | BK52: =+BJ52 -> 13781.25 | BL52: =+BK52 -> 13781.25 | BM52: =+BL52 -> 13781.25 | BN52: =+BM52 -> 13781.25 | BO52: =+BN52 -> 13781.25 | BP52: =+BO52 -> 13781.25 | BQ52: =+BP52 -> 13781.25 | ... BT52: =+BS52 -> 13781.25
B53: Project Manager | C53: 150000 | M53: =0 -> 0 | N53: =+M53 -> 0 | O53: =+N53 -> 0 | P53: =+O53 -> 0 | Q53: =+P53 -> 0 | R53: =+Q53 -> 0 | S53: =+R53 -> 0 | T53: =+S53 -> 0 | U53: =+T53 -> 0 | ... X53: =+W53 -> 0 | Y53: =X53*(1+C$59) -> 0 | Z53: =+Y53 -> 0 | AA53: =+Z53 -> 0 | AB53: =+AA53 -> 0 | AC53: =+AB53 -> 0 | AD53: =+AC53 -> 0 | AE53: =+AD53 -> 0 | AF53: =+AE53 -> 0 | AG53: =+AF53 -> 0 | ... AJ53: =+AI53 -> 0 | AK53: 0 | AL53: =+AK53 -> 0 | AM53: =+AL53 -> 0 | AN53: =+AM53 -> 0 | AO53: =+AN53 -> 0 | AP53: =+AO53 -> 0 | AQ53: =+AP53 -> 0 | AR53: =+AQ53 -> 0 | AS53: 0 | AT53: =C53/12 -> 12500 | AU53: =+AT53 -> 12500 | AV53: =+AU53 -> 12500 | AW53: =AV53*(1+$C$59) -> 13125 | AX53: =+AW53 -> 13125 | AY53: =+AX53 -> 13125 | AZ53: =+AY53 -> 13125 | BA53: =+AZ53 -> 13125 | BB53: =+BA53 -> 13125 | BC53: =+BB53 -> 13125 | BD53: =+BC53 -> 13125 | BE53: =+BD53 -> 13125 | ... BH53: =+BG53 -> 13125 | BI53: =BH53*(1+C$59) -> 13781.25 | BJ53: =+BI53 -> 13781.25 | BK53: =+BJ53 -> 13781.25 | BL53: =+BK53 -> 13781.25 | BM53: =+BL53 -> 13781.25 | BN53: =+BM53 -> 13781.25 | BO53: =+BN53 -> 13781.25 | BP53: =+BO53 -> 13781.25 | BQ53: =+BP53 -> 13781.25 | ... BT53: =+BS53 -> 13781.25
B54: Cloud Architect | C54: 140000 | M54: 0 | N54: 0 | O54: 0 | P54: 0 | Q54: 0 | R54: 0 | S54: 0 | T54: 0 | U54: 0 | V54: 0 | W54: 0 | X54: 0 | Y54: 0 | Z54: 0 | AA54: 0 | AB54: 0 | AC54: 0 | AD54: 0 | AE54: 0 | AF54: 0 | AG54: 0 | AH54: 0 | AI54: 0 | AJ54: 0 | AK54: 0 | AL54: 0 | AM54: 0 | AN54: 0 | AO54: 0 | AP54: 0 | AQ54: 0 | AR54: 0 | AS54: 0 | AT54: 0 | AU54: 0 | AV54: 0 | AW54: 0 | AX54: =+AW54 -> 0 | AY54: =+AX54 -> 0 | AZ54: =+AY54 -> 0 | BA54: =+AZ54 -> 0 | BB54: =+BA54 -> 0 | BC54: =+BB54 -> 0 | BD54: =C54/12 -> 11666.667 | BE54: =+BD54 -> 11666.667 | BF54: =+BE54 -> 11666.667 | BG54: =+BF54 -> 11666.667 | BH54: =+BG54 -> 11666.667 | BI54: =BH54*(1+$C$59) -> 12250 | BJ54: =+BI54 -> 12250 | BK54: =+BJ54 -> 12250 | BL54: =+BK54 -> 12250 | BM54: =+BL54 -> 12250 | BN54: =+BM54 -> 12250 | BO54: =+BN54 -> 12250 | BP54: =+BO54 -> 12250 | BQ54: =+BP54 -> 12250 | ... BT54: =+BS54 -> 12250
B57: Total Salaries | M57: =SUM(M31:M54) -> 10833.333 | N57: =SUM(N31:N54) -> 10833.333 | O57: =SUM(O31:O54) -> 10833.333 | P57: =SUM(P31:P54) -> 21666.667 | Q57: =SUM(Q31:Q54) -> 21666.667 | R57: =SUM(R31:R54) -> 32500 | S57: =SUM(S31:S54) -> 32500 | T57: =SUM(T31:T54) -> 32500 | ... BT57: =SUM(BT31:BT54) -> 259271.8
A59: Annual Raises | C59: 0.05

Sheet G&A
A1: G&A
M3: Year 1 | N3: Year 1 | O3: Year 1 | P3: Year 1 | Q3: Year 1 | R3: Year 1 | S3: Year 1 | T3: Year 1 | U3: Year 1 | V3: Year 1 | W3: Year 1 | X3: Year 1 | Y3: Year 2 | Z3: Year 2 | AA3: Year 2 | AB3: Year 2 | AC3: Year 2 | AD3: Year 2 | AE3: Year 2 | AF3: Year 2 | AG3: Year 2 | AH3: Year 2 | AI3: Year 2 | AJ3: Year 2 | AK3: Year 3 | AL3: Year 3 | AM3: Year 3 | AN3: Year 3 | AO3: Year 3 | AP3: Year 3 | AQ3: Year 3 | AR3: Year 3 | AS3: Year 3 | AT3: Year 3 | AU3: Year 3 | AV3: Year 3 | AW3: Year 4 | AX3: Year 4 | AY3: Year 4 | AZ3: Year 4 | BA3: Year 4 | BB3: Year 4 | BC3: Year 4 | BD3: Year 4 | BE3: Year 4 | BF3: Year 4 | BG3: Year 4 | BH3: Year 4 | BI3: Year 5 | BJ3: Year 5 | BK3: Year 5 | BL3: Year 5 | BM3: Year 5 | BN3: Year 5 | BO3: Year 5 | BP3: Year 5 | BQ3: Year 5 | BR3: Year 5 | BS3: Year 5 | BT3: Year 5
M4: Jan | N4: Feb | O4: Mar | P4: Apr | Q4: May | R4: Jun | S4: Jul | T4: Aug | U4: Sep | V4: Oct | W4: Nov | X4: Dec | Y4: Jan | Z4: Feb | AA4: Mar | AB4: Apr | AC4: May | AD4: Jun | AE4: Jul | AF4: Aug | AG4: Sep | AH4: Oct | AI4: Nov | AJ4: Dec | AK4: Jan | AL4: Feb | AM4: Mar | AN4: Apr | AO4: May | AP4: Jun | AQ4: Jul | AR4: Aug | AS4: Sep | AT4: Oct | AU4: Nov | AV4: Dec | AW4: Jan | AX4: Feb | AY4: Mar | AZ4: Apr | BA4: May | BB4: Jun | BC4: Jul | BD4: Aug | BE4: Sep | BF4: Oct | BG4: Nov | BH4: Dec | BI4: Jan | BJ4: Feb | BK4: Mar | BL4: Apr | BM4: May | BN4: Jun | BO4: Jul | BP4: Aug | BQ4: Sep | BR4: Oct | BS4: Nov | BT4: Dec
A6: WAGES | M6: =M54 -> 43750 | N6: =N54 -> 43750 | O6: =O54 -> 43750 | P6: =P54 -> 43750 | Q6: =Q54 -> 43750 | R6: =R54 -> 43750 | S6: =S54 -> 43750 | T6: =T54 -> 43750 | ... BT6: =BT54 -> 132250
A7: Deferred Compensation Earned | M7: =M62 -> 28750 | N7: =N62 -> 28750 | O7: =O62 -> 28750 | P7: =P62 -> 28750 | Q7: =Q62 -> 28750 | R7: =R62 -> 28750 | S7: =S62 -> 28750 | T7: =T62 -> 28750 | ... BT7: =BT62 -> 0
A8: Benefits 22% | B8: 0.22 | M8: =M6*$B8 -> 9625 | N8: =N6*$B8 -> 9625 | O8: =O6*$B8 -> 9625 | P8: =P6*$B8 -> 9625 | Q8: =Q6*$B8 -> 9625 | R8: =R6*$B8 -> 9625 | S8: =S6*$B8 -> 9625 | T8: =T6*$B8 -> 9625 | ... BT8: =BT6*$B8 -> 29095
A10: T&E | M10: 2000 | N10: 2000 | O10: 2000 | P10: 2000 | Q10: 2000 | R10: 2000 | S10: 2000 | T10: 2000 | U10: 2000 | V10: 2000 | W10: 2000 | X10: 2000 | Y10: 2000 | Z10: 2000 | AA10: 2000 | AB10: 2000 | AC10: 5000 | AD10: 5000 | AE10: 5000 | AF10: 5000 | AG10: 5000 | AH10: 5000 | AI10: 10000 | AJ10: 10000 | AK10: 10000 | AL10: 10000 | AM10: 10000 | AN10: 10000 | AO10: 15000 | AP10: 15000 | AQ10: 15000 | AR10: 15000 | AS10: 15000 | AT10: 15000 | AU10: 15000 | AV10: 15000 | AW10: 15000 | AX10: 15000 | AY10: 15000 | AZ10: 15000 | BA10: 15000 | BB10: 15000 | BC10: 20000 | BD10: 20000 | BE10: 20000 | BF10: 20000 | BG10: 20000 | BH10: 20000 | BI10: 20000 | BJ10: 20000 | BK10: 20000 | BL10: 20000 | BM10: 20000 | BN10: 20000 | BO10: 20000 | BP10: 20000 | BQ10: 20000 | BR10: 20000 | BS10: 20000 | BT10: 20000
A12: HR consultant | M12: 2000 | N12: 2000 | O12: 2000 | P12: 2000 | Q12: 2000 | R12: 2000 | S12: 2000 | T12: 2000 | U12: 2000 | V12: 2000 | W12: 2000 | X12: 2000 | Y12: 4000 | Z12: 4000
A14: Office Rent | M14: =100000/12 -> 8333.3333 | N14: =100000/12 -> 8333.3333 | O14: =100000/12 -> 8333.3333 | P14: =100000/12 -> 8333.3333 | Q14: =100000/12 -> 8333.3333 | R14: =100000/12 -> 8333.3333 | S14: =100000/12 -> 8333.3333 | T14: =100000/12 -> 8333.3333 | ... X14: =100000/12 -> 8333.3333 | Y14: =200000/12 -> 16666.667 | Z14: =200000/12 -> 16666.667 | AA14: =200000/12 -> 16666.667 | AB14: =200000/12 -> 16666.667 | AC14: =200000/12 -> 16666.667 | AD14: =200000/12 -> 16666.667 | AE14: =200000/12 -> 16666.667 | AF14: =200000/12 -> 16666.667 | ... AV14: =200000/12 -> 16666.667 | AW14: =500000/12 -> 41666.667 | AX14: =500000/12 -> 41666.667 | AY14: =500000/12 -> 41666.667 | AZ14: =500000/12 -> 41666.667 | BA14: =500000/12 -> 41666.667 | BB14: =500000/12 -> 41666.667 | BC14: =500000/12 -> 41666.667 | BD14: =500000/12 -> 41666.667 | ... BT14: =500000/12 -> 41666.667
A16: Insurance | M16: =7000/12 -> 583.33333 | N16: =7000/12 -> 583.33333 | O16: =7000/12 -> 583.33333 | P16: =7000/12 -> 583.33333 | Q16: =7000/12 -> 583.33333 | R16: =7000/12 -> 583.33333 | S16: =7000/12 -> 583.33333 | T16: =7000/12 -> 583.33333 | ... W16: =7000/12 -> 583.33333 | X16: =20000/12 -> 1666.6667 | Y16: =20000/12 -> 1666.6667 | Z16: =20000/12 -> 1666.6667 | AA16: =20000/12 -> 1666.6667 | AB16: =20000/12 -> 1666.6667 | AC16: =20000/12 -> 1666.6667 | AD16: =20000/12 -> 1666.6667 | AE16: =20000/12 -> 1666.6667 | ... AV16: =20000/12 -> 1666.6667 | AW16: =40000/12 -> 3333.3333 | AX16: =40000/12 -> 3333.3333 | AY16: =40000/12 -> 3333.3333 | AZ16: =40000/12 -> 3333.3333 | BA16: =40000/12 -> 3333.3333 | BB16: =40000/12 -> 3333.3333 | BC16: =40000/12 -> 3333.3333 | BD16: =40000/12 -> 3333.3333 | ... BT16: =40000/12 -> 3333.3333
A18: Legal counsel (outsourced) | M18: 2500 | N18: 2500 | O18: 2500 | P18: 2500 | Q18: 2500 | R18: 2500 | S18: 2500 | T18: 2500 | U18: 2500 | V18: 2500 | W18: 2500 | X18: 5000 | Y18: 5000 | Z18: 5000 | AA18: 5000 | AB18: 5000 | AC18: 5000 | AD18: 5000 | AE18: 5000 | AF18: 5000 | AG18: 5000 | AH18: 5000 | AI18: 5000 | AJ18: 10000 | AK18: 10000 | AL18: 10000 | AM18: 10000 | AN18: 10000 | AO18: 10000 | AP18: 10000 | AQ18: 10000 | AR18: 10000 | AS18: 10000 | AT18: 10000 | AU18: 10000 | AV18: 10000
A20: Office Supplies | M20: 200 | N20: 200 | O20: 200 | P20: 200 | Q20: 200 | R20: 200 | S20: 200 | T20: 200 | U20: 200 | V20: 200 | W20: 200 | X20: 200 | Y20: 200 | Z20: 200 | AA20: 200 | AB20: 200 | AC20: 200 | AD20: 200 | AE20: 200 | AF20: 200 | AG20: 200 | AH20: 200 | AI20: 200 | AJ20: 200 | AK20: 200 | AL20: 200 | AM20: 200 | AN20: 200 | AO20: 200 | AP20: 200 | AQ20: 200 | AR20: 200 | AS20: 200 | AT20: 200 | AU20: 200 | AV20: 200 | AW20: 200 | AX20: 200 | AY20: 200 | AZ20: 200 | BA20: 200 | BB20: 200 | BC20: 200 | BD20: 200 | BE20: 200 | BF20: 200 | BG20: 200 | BH20: 200 | BI20: 200 | BJ20: 200 | BK20: 200 | BL20: 200 | BM20: 200 | BN20: 200 | BO20: 200 | BP20: 200 | BQ20: 200 | BR20: 200 | BS20: 200 | BT20: 200
A21: Snacks | M21: 500 | N21: 500 | O21: 500 | P21: 500 | Q21: 500 | R21: 500 | S21: 500 | T21: 500 | U21: 500 | V21: 500 | W21: 500 | X21: 500 | Y21: 500 | Z21: 500 | AA21: 500 | AB21: 500 | AC21: 500 | AD21: 500 | AE21: 500 | AF21: 500 | AG21: 500 | AH21: 500 | AI21: 500 | AJ21: 500 | AK21: 500 | AL21: 500 | AM21: 500 | AN21: 500 | AO21: 500 | AP21: 500 | AQ21: 500 | AR21: 500 | AS21: 500 | AT21: 500 | AU21: 500 | AV21: 500 | AW21: 500 | AX21: 500 | AY21: 500 | AZ21: 500 | BA21: 500 | BB21: 500 | BC21: 500 | BD21: 500 | BE21: 500 | BF21: 500 | BG21: 500 | BH21: 500 | BI21: 500 | BJ21: 500 | BK21: 500 | BL21: 500 | BM21: 500 | BN21: 500 | BO21: 500 | BP21: 500 | BQ21: 500 | BR21: 500 | BS21: 500 | BT21: 500
A22: Misc | M22: 500 | N22: 500 | O22: 500 | P22: 500 | Q22: 500 | R22: 500 | S22: 500 | T22: 500 | U22: 500 | V22: 500 | W22: 500 | X22: 500 | Y22: 500 | Z22: 500 | AA22: 500 | AB22: 500 | AC22: 500 | AD22: 500 | AE22: 500 | AF22: 500 | AG22: 500 | AH22: 500 | AI22: 500 | AJ22: 500 | AK22: 500 | AL22: 500 | AM22: 500 | AN22: 500 | AO22: 500 | AP22: 500 | AQ22: 500 | AR22: 500 | AS22: 500 | AT22: 500 | AU22: 500 | AV22: 500 | AW22: 500 | AX22: 500 | AY22: 500 | AZ22: 500 | BA22: 500 | BB22: 500 | BC22: 500 | BD22: 500 | BE22: 500 | BF22: 500 | BG22: 500 | BH22: 500 | BI22: 500 | BJ22: 500 | BK22: 500 | BL22: 500 | BM22: 500 | BN22: 500 | BO22: 500 | BP22: 500 | BQ22: 500 | BR22: 500 | BS22: 500 | BT22: 500
A25: Total | M25: =SUM(M6:M29) -> 98741.667 | N25: =SUM(N6:N29) -> 98741.667 | O25: =SUM(O6:O29) -> 98741.667 | P25: =SUM(P6:P29) -> 98741.667 | Q25: =SUM(Q6:Q29) -> 98741.667 | R25: =SUM(R6:R29) -> 98741.667 | S25: =SUM(S6:S29) -> 98741.667 | T25: =SUM(T6:T29) -> 98741.667 | ... BT25: =SUM(BT6:BT29) -> 227545
A29: Deffered payment repayed | AG29: 28000 | AH29: 28000 | AI29: 28000 | AJ29: 28000 | AK29: 28000 | AL29: 28000 | AM29: 28000 | AN29: 28000 | AO29: 28000 | AP29: 28000 | AQ29: 28000 | AR29: 28000 | AS29: 28000 | AT29: 28000 | AU29: 28000 | AV29: 28000 | AW29: 28000 | AX29: 28000 | AY29: 28000 | AZ29: 28000 | BA29: 15000
A30: total repayed | M30: =M29+G30 -> 0 | N30: =N29+H30 -> 0 | O30: =O29+I30 -> 0 | P30: =P29+J30 -> 0 | Q30: =Q29+K30 -> 0 | R30: =R29+L30 -> 0 | S30: =S29+M30 -> 0 | T30: =T29+N30 -> 0 | ... BT30: =BT29+BN30 -> 84000
B36: Salaries | C36: Hiring year | D36: Hiring month
A38: CEO | B38: 175000 | C38: Year 1 | D38: Jan | M38: =$B38/12 -> 14583.333 | N38: =$B$38/12 -> 14583.333 | O38: =$B$38/12 -> 14583.333 | P38: =$B$38/12 -> 14583.333 | Q38: =$B$38/12 -> 14583.333 | R38: =$B$38/12 -> 14583.333 | S38: =$B$38/12 -> 14583.333 | T38: =$B$38/12 -> 14583.333 | U38: =$B$38/12 -> 14583.333 | ... BT38: =$B$38/12 -> 14583.333
A39: COO | B39: 175000 | C39: Year 1 | D39: Jan | M39: =$B39/12 -> 14583.333 | N39: =$B39/12 -> 14583.333 | O39: =$B39/12 -> 14583.333 | P39: =$B39/12 -> 14583.333 | Q39: =$B39/12 -> 14583.333 | R39: =$B39/12 -> 14583.333 | S39: =$B39/12 -> 14583.333 | T39: =$B39/12 -> 14583.333 | ... BT39: =$B39/12 -> 14583.333
A40: CFO | B40: 175000 | C40: Year 1 | D40: Jan | M40: =$B40/12 -> 14583.333 | N40: =$B40/12 -> 14583.333 | O40: =$B40/12 -> 14583.333 | P40: =$B40/12 -> 14583.333 | Q40: =$B40/12 -> 14583.333 | R40: =$B40/12 -> 14583.333 | S40: =$B40/12 -> 14583.333 | T40: =$B40/12 -> 14583.333 | ... BT40: =$B40/12 -> 14583.333
A41: HR | B41: 110000 | C41: Year 2 | D41: Mar | M41: 0 | N41: 0 | O41: 0 | P41: 0 | Q41: 0 | R41: 0 | S41: 0 | T41: 0 | U41: 0 | V41: 0 | W41: 0 | X41: 0 | Y41: 0 | Z41: 0 | AA41: =$B41/12 -> 9166.6667 | AB41: =$B41/12 -> 9166.6667 | AC41: =$B41/12 -> 9166.6667 | AD41: =$B41/12 -> 9166.6667 | AE41: =$B41/12 -> 9166.6667 | AF41: =$B41/12 -> 9166.6667 | AG41: =$B41/12 -> 9166.6667 | AH41: =$B41/12 -> 9166.6667 | ... BT41: =$B41/12 -> 9166.6667
A42: HR | B42: 95000 | C42: Year 3 | D42: Jan | M42: 0 | N42: 0 | O42: 0 | P42: 0 | Q42: 0 | R42: 0 | S42: 0 | T42: 0 | U42: 0 | V42: 0 | W42: 0 | X42: 0 | Y42: 0 | Z42: 0 | AA42: 0 | AB42: 0 | AC42: 0 | AD42: 0 | AE42: 0 | AF42: 0 | AG42: 0 | AH42: 0 | AI42: 0 | AJ42: 0 | AK42: =$B42/12 -> 7916.6667 | AL42: =$B42/12 -> 7916.6667 | AM42: =$B42/12 -> 7916.6667 | AN42: =$B42/12 -> 7916.6667 | AO42: =$B42/12 -> 7916.6667 | AP42: =$B42/12 -> 7916.6667 | AQ42: =$B42/12 -> 7916.6667 | AR42: =$B42/12 -> 7916.6667 | ... BT42: =$B42/12 -> 7916.6667
A43: Senior accountant | B43: 95000 | C43: Year 2 | D43: Jan | M43: 0 | N43: 0 | O43: 0 | P43: 0 | Q43: 0 | R43: 0 | S43: 0 | T43: 0 | U43: 0 | V43: 0 | W43: 0 | X43: 0 | Y43: =$B43/12 -> 7916.6667 | Z43: =$B43/12 -> 7916.6667 | AA43: =$B43/12 -> 7916.6667 | AB43: =$B43/12 -> 7916.6667 | AC43: =$B43/12 -> 7916.6667 | AD43: =$B43/12 -> 7916.6667 | AE43: =$B43/12 -> 7916.6667 | AF43: =$B43/12 -> 7916.6667 | ... BT43: =$B43/12 -> 7916.6667
A44: Recruiter | B44: 85000 | C44: Year 3 | D44: Apr | M44: 0 | N44: 0 | O44: 0 | P44: 0 | Q44: 0 | R44: 0 | S44: 0 | T44: 0 | U44: 0 | V44: 0 | W44: 0 | X44: 0 | Y44: 0 | Z44: 0 | AA44: 0 | AB44: =$B44/12 -> 7083.3333 | AC44: =$B44/12 -> 7083.3333 | AD44: =$B44/12 -> 7083.3333 | AE44: =$B44/12 -> 7083.3333 | AF44: =$B44/12 -> 7083.3333 | AG44: =$B44/12 -> 7083.3333 | AH44: =$B44/12 -> 7083.3333 | AI44: =$B44/12 -> 7083.3333 | ... BT44: =$B44/12 -> 7083.3333
A45: Recruiter | B45: 85000 | C45: Year 3 | D45: Apr | M45: 0 | N45: 0 | O45: 0 | P45: 0 | Q45: 0 | R45: 0 | S45: 0 | T45: 0 | U45: 0 | V45: 0 | W45: 0 | X45: 0 | Y45: 0 | Z45: 0 | AA45: 0 | AB45: =$B45/12 -> 7083.3333 | AC45: =$B45/12 -> 7083.3333 | AD45: =$B45/12 -> 7083.3333 | AE45: =$B45/12 -> 7083.3333 | AF45: =$B45/12 -> 7083.3333 | AG45: =$B45/12 -> 7083.3333 | AH45: =$B45/12 -> 7083.3333 | AI45: =$B45/12 -> 7083.3333 | ... BT45: =$B45/12 -> 7083.3333
A46: Admin | B46: 65000 | C46: Year 3 | D46: Apr | M46: 0 | N46: 0 | O46: 0 | P46: 0 | Q46: 0 | R46: 0 | S46: 0 | T46: 0 | U46: 0 | V46: 0 | W46: 0 | X46: 0 | Y46: 0 | Z46: 0 | AA46: 0 | AB46: =$B46/12 -> 5416.6667 | AC46: =$B46/12 -> 5416.6667 | AD46: =$B46/12 -> 5416.6667 | AE46: =$B46/12 -> 5416.6667 | AF46: =$B46/12 -> 5416.6667 | AG46: =$B46/12 -> 5416.6667 | AH46: =$B46/12 -> 5416.6667 | AI46: =$B46/12 -> 5416.6667 | ... BT46: =$B46/12 -> 5416.6667
A47: Admin | B47: 65000 | C47: Year 4 | D47: Jan | M47: 0 | N47: 0 | O47: 0 | P47: 0 | Q47: 0 | R47: 0 | S47: 0 | T47: 0 | U47: 0 | V47: 0 | W47: 0 | X47: 0 | Y47: 0 | Z47: 0 | AA47: 0 | AB47: 0 | AC47: 0 | AD47: 0 | AE47: 0 | AF47: 0 | AG47: 0 | AH47: 0 | AI47: 0 | AJ47: 0 | AK47: 0 | AL47: 0 | AM47: 0 | AN47: 0 | AO47: 0 | AP47: 0 | AQ47: 0 | AR47: 0 | AS47: 0 | AT47: 0 | AU47: 0 | AV47: 0 | AW47: =$B47/12 -> 5416.6667 | AX47: =$B47/12 -> 5416.6667 | AY47: =$B47/12 -> 5416.6667 | AZ47: =$B47/12 -> 5416.6667 | BA47: =$B47/12 -> 5416.6667 | BB47: =$B47/12 -> 5416.6667 | BC47: =$B47/12 -> 5416.6667 | BD47: =$B47/12 -> 5416.6667 | ... BT47: =$B47/12 -> 5416.6667
A48: Controller | B48: 140000 | C48: Year 4 | D48: Jan | M48: 0 | N48: 0 | O48: 0 | P48: 0 | Q48: 0 | R48: 0 | S48: 0 | T48: 0 | U48: 0 | V48: 0 | W48: 0 | X48: 0 | Y48: 0 | Z48: 0 | AA48: 0 | AB48: 0 | AC48: 0 | AD48: 0 | AE48: 0 | AF48: 0 | AG48: 0 | AH48: 0 | AI48: 0 | AJ48: 0 | AK48: 0 | AL48: 0 | AM48: 0 | AN48: 0 | AO48: 0 | AP48: 0 | AQ48: 0 | AR48: 0 | AS48: 0 | AT48: 0 | AU48: 0 | AV48: 0 | AW48: =$B48/12 -> 11666.667 | AX48: =$B48/12 -> 11666.667 | AY48: =$B48/12 -> 11666.667 | AZ48: =$B48/12 -> 11666.667 | BA48: =$B48/12 -> 11666.667 | BB48: =$B48/12 -> 11666.667 | BC48: =$B48/12 -> 11666.667 | BD48: =$B48/12 -> 11666.667 | ... BT48: =$B48/12 -> 11666.667
A49: Legal counsel | B49: 190000 | C49: Year 4 | D49: Jan | M49: 0 | N49: 0 | O49: 0 | P49: 0 | Q49: 0 | R49: 0 | S49: 0 | T49: 0 | U49: 0 | V49: 0 | W49: 0 | X49: 0 | Y49: 0 | Z49: 0 | AA49: 0 | AB49: 0 | AC49: 0 | AD49: 0 | AE49: 0 | AF49: 0 | AG49: 0 | AH49: 0 | AI49: 0 | AJ49: 0 | AK49: 0 | AL49: 0 | AM49: 0 | AN49: 0 | AO49: 0 | AP49: 0 | AQ49: 0 | AR49: 0 | AS49: 0 | AT49: 0 | AU49: 0 | AV49: 0 | AW49: =$B49/12 -> 15833.333 | AX49: =$B49/12 -> 15833.333 | AY49: =$B49/12 -> 15833.333 | AZ49: =$B49/12 -> 15833.333 | BA49: =$B49/12 -> 15833.333 | BB49: =$B49/12 -> 15833.333 | BC49: =$B49/12 -> 15833.333 | BD49: =$B49/12 -> 15833.333 | ... BT49: =$B49/12 -> 15833.333
A50: assistant | B50: 44000 | C50: Year 1 | D50: Sept | U50: =$B50/12 -> 3666.6667 | V50: =$B50/12 -> 3666.6667 | W50: =$B50/12 -> 3666.6667 | X50: =$B50/12 -> 3666.6667 | Y50: =$B50/12 -> 3666.6667 | Z50: =$B50/12 -> 3666.6667 | AA50: =$B50/12 -> 3666.6667 | AB50: =$B50/12 -> 3666.6667 | ... BT50: =$B50/12 -> 3666.6667
A51: assistant | B51: 44000 | C51: Year 2 | D51: Jan | Y51: =$B51/12 -> 3666.6667 | Z51: =$B51/12 -> 3666.6667 | AA51: =$B51/12 -> 3666.6667 | AB51: =$B51/12 -> 3666.6667 | AC51: =$B51/12 -> 3666.6667 | AD51: =$B51/12 -> 3666.6667 | AE51: =$B51/12 -> 3666.6667 | AF51: =$B51/12 -> 3666.6667 | ... BT51: =$B51/12 -> 3666.6667
A52: assistant | B52: 44000 | C52: Year 3 | D52: Jan | AK52: =$B52/12 -> 3666.6667 | AL52: =$B52/12 -> 3666.6667 | AM52: =$B52/12 -> 3666.6667 | AN52: =$B52/12 -> 3666.6667 | AO52: =$B52/12 -> 3666.6667 | AP52: =$B52/12 -> 3666.6667 | AQ52: =$B52/12 -> 3666.6667 | AR52: =$B52/12 -> 3666.6667 | ... BT52: =$B52/12 -> 3666.6667
B54: Total Wages | M54: =SUM(M38:M53) -> 43750 | N54: =SUM(N38:N53) -> 43750 | O54: =SUM(O38:O53) -> 43750 | P54: =SUM(P38:P53) -> 43750 | Q54: =SUM(Q38:Q53) -> 43750 | R54: =SUM(R38:R53) -> 43750 | S54: =SUM(S38:S53) -> 43750 | T54: =SUM(T38:T53) -> 43750 | ... BT54: =SUM(BT38:BT53) -> 132250
B57: Defered Expenses | F57: paid salary
B58: CEO | C58: =B38 -> 175000 | D58: Year1 | E58: Jan | F58: 60000 | M58: =($C58-$F58)/12 -> 9583.3333 | N58: =($C58-$F58)/12 -> 9583.3333 | O58: =($C58-$F58)/12 -> 9583.3333 | P58: =($C58-$F58)/12 -> 9583.3333 | Q58: =($C58-$F58)/12 -> 9583.3333 | R58: =($C58-$F58)/12 -> 9583.3333 | S58: =($C58-$F58)/12 -> 9583.3333 | T58: =($C58-$F58)/12 -> 9583.3333 | ... AF58: =($C58-$F58)/12 -> 9583.3333
B59: COO | C59: =B39 -> 175000 | D59: Year1 | E59: Jan | F59: 60000 | M59: =($C59-$F59)/12 -> 9583.3333 | N59: =($C59-$F59)/12 -> 9583.3333 | O59: =($C59-$F59)/12 -> 9583.3333 | P59: =($C59-$F59)/12 -> 9583.3333 | Q59: =($C59-$F59)/12 -> 9583.3333 | R59: =($C59-$F59)/12 -> 9583.3333 | S59: =($C59-$F59)/12 -> 9583.3333 | T59: =($C59-$F59)/12 -> 9583.3333 | ... AF59: =($C59-$F59)/12 -> 9583.3333
B60: CFO | C60: =B40 -> 175000 | D60: Year1 | E60: Jan | F60: 60000 | M60: =($C60-$F60)/12 -> 9583.3333 | N60: =($C60-$F60)/12 -> 9583.3333 | O60: =($C60-$F60)/12 -> 9583.3333 | P60: =($C60-$F60)/12 -> 9583.3333 | Q60: =($C60-$F60)/12 -> 9583.3333 | R60: =($C60-$F60)/12 -> 9583.3333 | S60: =($C60-$F60)/12 -> 9583.3333 | T60: =($C60-$F60)/12 -> 9583.3333 | ... AF60: =($C60-$F60)/12 -> 9583.3333
B62: Total deferred | M62: =SUM(M58:M61) -> 28750 | N62: =SUM(N58:N61) -> 28750 | O62: =SUM(O58:O61) -> 28750 | P62: =SUM(P58:P61) -> 28750 | Q62: =SUM(Q58:Q61) -> 28750 | R62: =SUM(R58:R61) -> 28750 | S62: =SUM(S58:S61) -> 28750 | T62: =SUM(T58:T61) -> 28750 | ... BT62: =SUM(BT58:BT61) -> 0
E64: AP | M64: ='G&A'!M62 -> 28750 | N64: ='G&A'!N62+M64 -> 57500 | O64: ='G&A'!O62+N64 -> 86250 | P64: ='G&A'!P62+O64 -> 115000 | Q64: ='G&A'!Q62+P64 -> 143750 | R64: ='G&A'!R62+Q64 -> 172500 | S64: ='G&A'!S62+R64 -> 201250 | T64: ='G&A'!T62+S64 -> 230000 | U64: ='G&A'!U62+T64 -> 258750 | ... AF64: ='G&A'!AF62+AE64 -> 575000 | AG64: ='G&A'!AG62+AF64-AG29 -> 547000 | AH64: ='G&A'!AH62+AG64-AH29 -> 519000 | AI64: ='G&A'!AI62+AH64-AI29 -> 491000 | AJ64: ='G&A'!AJ62+AI64-AJ29 -> 463000 | AK64: ='G&A'!AK62+AJ64-AK29 -> 435000 | AL64: ='G&A'!AL62+AK64-AL29 -> 407000 | AM64: ='G&A'!AM62+AL64-AM29 -> 379000 | AN64: ='G&A'!AN62+AM64-AN29 -> 351000 | ... BT64: ='G&A'!BT62+BS64-BT29 -> 0
B71: Repayment start date | C71: Year 3
A75: office rent | B75: year | C75: avg Yearly rent | D75: Size (sqft)
B76: 1 | C76: 100000 | D76: 2000
B77: 2 | C77: 200000 | D77: 5000
B78: 3 | C78: 200000 | D78: 5000
B79: 4 | C79: 500000 | D79: 10000
B80: 5 | C80: 500000 | D80: 10000

Sheet Sales & Marketing
A1: Sales & Marketing
B2: Marketing | M2: Year 1 | N2: Year 1 | O2: Year 1 | P2: Year 1 | Q2: Year 1 | R2: Year 1 | S2: Year 1 | T2: Year 1 | U2: Year 1 | V2: Year 1 | W2: Year 1 | X2: Year 1 | Y2: Year 2 | Z2: Year 2 | AA2: Year 2 | AB2: Year 2 | AC2: Year 2 | AD2: Year 2 | AE2: Year 2 | AF2: Year 2 | AG2: Year 2 | AH2: Year 2 | AI2: Year 2 | AJ2: Year 2 | AK2: Year 3 | AL2: Year 3 | AM2: Year 3 | AN2: Year 3 | AO2: Year 3 | AP2: Year 3 | AQ2: Year 3 | AR2: Year 3 | AS2: Year 3 | AT2: Year 3 | AU2: Year 3 | AV2: Year 3 | AW2: Year 4 | AX2: Year 4 | AY2: Year 4 | AZ2: Year 4 | BA2: Year 4 | BB2: Year 4 | BC2: Year 4 | BD2: Year 4 | BE2: Year 4 | BF2: Year 4 | BG2: Year 4 | BH2: Year 4 | BI2: Year 5 | BJ2: Year 5 | BK2: Year 5 | BL2: Year 5 | BM2: Year 5 | BN2: Year 5 | BO2: Year 5 | BP2: Year 5 | BQ2: Year 5 | BR2: Year 5 | BS2: Year 5 | BT2: Year 5
B3: Year | C3: 1 | D3: 2 | E3: 3 | F3: 4 | G3: 5 | M3: Jan | N3: Feb | O3: Mar | P3: Apr | Q3: May | R3: Jun | S3: Jul | T3: Aug | U3: Sep | V3: Oct | W3: Nov | X3: Dec | Y3: Jan | Z3: Feb | AA3: Mar | AB3: Apr | AC3: May | AD3: Jun | AE3: Jul | AF3: Aug | AG3: Sep | AH3: Oct | AI3: Nov | AJ3: Dec | AK3: Jan | AL3: Feb | AM3: Mar | AN3: Apr | AO3: May | AP3: Jun | AQ3: Jul | AR3: Aug | AS3: Sep | AT3: Oct | AU3: Nov | AV3: Dec | AW3: Jan | AX3: Feb | AY3: Mar | AZ3: Apr | BA3: May | BB3: Jun | BC3: Jul | BD3: Aug | BE3: Sep | BF3: Oct | BG3: Nov | BH3: Dec | BI3: Jan | BJ3: Feb | BK3: Mar | BL3: Apr | BM3: May | BN3: Jun | BO3: Jul | BP3: Aug | BQ3: Sep | BR3: Oct | BS3: Nov | BT3: Dec
B4: Advertising and Media Spend | C4: 15000 | D4: 30000 | E4: 70000 | F4: 90000 | G4: 125000
B5: Content Creation | C5: 6000 | D5: 12000 | E5: 15000 | F5: 18000 | G5: 21000 | K5: {=B4:B6} -> Advertising and Media Spend | M5: =_xlfn.XLOOKUP(_xlfn.NUMBERVALUE(RIGHT(M$2,1)),$C$3:$G$3,$C4:$G4)/12 -> 1250 | N5: =_xlfn.XLOOKUP(_xlfn.NUMBERVALUE(RIGHT(N$2,1)),$C$3:$G$3,$C4:$G4)/12 -> 1250 | O5: =_xlfn.XLOOKUP(_xlfn.NUMBERVALUE(RIGHT(O$2,1)),$C$3:$G$3,$C4:$G4)/12 -> 1250 | P5: =_xlfn.XLOOKUP(_xlfn.NUMBERVALUE(RIGHT(P$2,1)),$C$3:$G$3,$C4:$G4)/12 -> 1250 | Q5: =_xlfn.XLOOKUP(_xlfn.NUMBERVALUE(RIGHT(Q$2,1)),$C$3:$G$3,$C4:$G4)/12 -> 1250 | R5: =_xlfn.XLOOKUP(_xlfn.NUMBERVALUE(RIGHT(R$2,1)),$C$3:$G$3,$C4:$G4)/12 -> 1250 | S5: =_xlfn.XLOOKUP(_xlfn.NUMBERVALUE(RIGHT(S$2,1)),$C$3:$G$3,$C4:$G4)/12 -> 1250 | T5: =_xlfn.XLOOKUP(_xlfn.NUMBERVALUE(RIGHT(T$2,1)),$C$3:$G$3,$C4:$G4)/12 -> 1250 | ... BT5: =_xlfn.XLOOKUP(_xlfn.NUMBERVALUE(RIGHT(BT$2,1)),$C$3:$G$3,$C4:$G4)/12 -> 10416.667
B6: SEO | C6: 6000 | D6: 9000 | E6: 12000 | F6: 18000 | G6: 21000 | K6: Content Creation | M6: =_xlfn.XLOOKUP(_xlfn.NUMBERVALUE(RIGHT(M$2,1)),$C$3:$G$3,$C9:$G9)/12 -> 500 | N6: =_xlfn.XLOOKUP(_xlfn.NUMBERVALUE(RIGHT(N$2,1)),$C$3:$G$3,$C9:$G9)/12 -> 500 | O6: =_xlfn.XLOOKUP(_xlfn.NUMBERVALUE(RIGHT(O$2,1)),$C$3:$G$3,$C9:$G9)/12 -> 500 | P6: =_xlfn.XLOOKUP(_xlfn.NUMBERVALUE(RIGHT(P$2,1)),$C$3:$G$3,$C9:$G9)/12 -> 500 | Q6: =_xlfn.XLOOKUP(_xlfn.NUMBERVALUE(RIGHT(Q$2,1)),$C$3:$G$3,$C9:$G9)/12 -> 500 | R6: =_xlfn.XLOOKUP(_xlfn.NUMBERVALUE(RIGHT(R$2,1)),$C$3:$G$3,$C9:$G9)/12 -> 500 | S6: =_xlfn.XLOOKUP(_xlfn.NUMBERVALUE(RIGHT(S$2,1)),$C$3:$G$3,$C9:$G9)/12 -> 500 | T6: =_xlfn.XLOOKUP(_xlfn.NUMBERVALUE(RIGHT(T$2,1)),$C$3:$G$3,$C9:$G9)/12 -> 500 | ... BT6: =_xlfn.XLOOKUP(_xlfn.NUMBERVALUE(RIGHT(BT$2,1)),$C$3:$G$3,$C9:$G9)/12 -> 5833.3333
K7: SEO | M7: =_xlfn.XLOOKUP(_xlfn.NUMBERVALUE(RIGHT(M$2,1)),$C$3:$G$3,$C5:$G5)/12 -> 500 | N7: =_xlfn.XLOOKUP(_xlfn.NUMBERVALUE(RIGHT(N$2,1)),$C$3:$G$3,$C5:$G5)/12 -> 500 | O7: =_xlfn.XLOOKUP(_xlfn.NUMBERVALUE(RIGHT(O$2,1)),$C$3:$G$3,$C5:$G5)/12 -> 500 | P7: =_xlfn.XLOOKUP(_xlfn.NUMBERVALUE(RIGHT(P$2,1)),$C$3:$G$3,$C5:$G5)/12 -> 500 | Q7: =_xlfn.XLOOKUP(_xlfn.NUMBERVALUE(RIGHT(Q$2,1)),$C$3:$G$3,$C5:$G5)/12 -> 500 | R7: =_xlfn.XLOOKUP(_xlfn.NUMBERVALUE(RIGHT(R$2,1)),$C$3:$G$3,$C5:$G5)/12 -> 500 | S7: =_xlfn.XLOOKUP(_xlfn.NUMBERVALUE(RIGHT(S$2,1)),$C$3:$G$3,$C5:$G5)/12 -> 500 | T7: =_xlfn.XLOOKUP(_xlfn.NUMBERVALUE(RIGHT(T$2,1)),$C$3:$G$3,$C5:$G5)/12 -> 500 | ... BT7: =_xlfn.XLOOKUP(_xlfn.NUMBERVALUE(RIGHT(BT$2,1)),$C$3:$G$3,$C5:$G5)/12 -> 1750
B8: Sales
B9: Sales Lead Gen | C9: 6000 | D9: 12000 | E9: 30000 | F9: 60000 | G9: 70000
K10: Marketing Wages | M10: =M17 -> 10500 | N10: =N17 -> 10500 | O10: =O17 -> 10500 | P10: =P17 -> 10500 | Q10: =Q17 -> 10500 | R10: =R17 -> 10500 | S10: =S17 -> 10500 | T10: =T17 -> 10500 | ... BT10: =BT17 -> 20650
C12: Estimated Salary w/o commission | D12: Starting Year | E12: Benefits % | F12: T&E % | G12: Other % | H12: Total Yearly Salary | K12: Total Marketing Expense | M12: =SUM(M5:M10) -> 12750 | N12: =SUM(N5:N10) -> 12750 | O12: =SUM(O5:O10) -> 12750 | P12: =SUM(P5:P10) -> 12750 | Q12: =SUM(Q5:Q10) -> 12750 | R12: =SUM(R5:R10) -> 12750 | S12: =SUM(S5:S10) -> 12750 | T12: =SUM(T5:T10) -> 12750 | ... BT12: =SUM(BT5:BT10) -> 38650
B13: Sales VP | C13: 75000 | D13: 2 | E13: 0.3 | F13: 0.07 | G13: 0.12 | H13: =C13*E13+C13*F13+C13*G13+C13 -> 111750
B14: Sales rep | C14: 52500 | D14: 2 | E14: 0.25 | F14: 0.05 | G14: 0.1 | H14: =C14*E14+C14*F14+C14*G14+C14 -> 73500 | K14: Marketing Manager | M14: =IF(_xlfn.NUMBERVALUE(RIGHT(M$2,1))>=$D22,$H22/12,0)*IF(_xlfn.NUMBERVALUE(RIGHT(M$2,1))-$D22>=1,1+((_xlfn.NUMBERVALUE(RIGHT(M$2,1))-$D22)*$H$25),1) -> 10500 | N14: =IF(_xlfn.NUMBERVALUE(RIGHT(N$2,1))>=$D22,$H22/12,0)*IF(_xlfn.NUMBERVALUE(RIGHT(N$2,1))-$D22>=1,1+((_xlfn.NUMBERVALUE(RIGHT(N$2,1))-$D22)*$H$25),1) -> 10500 | O14: =IF(_xlfn.NUMBERVALUE(RIGHT(O$2,1))>=$D22,$H22/12,0)*IF(_xlfn.NUMBERVALUE(RIGHT(O$2,1))-$D22>=1,1+((_xlfn.NUMBERVALUE(RIGHT(O$2,1))-$D22)*$H$25),1) -> 10500 | P14: =IF(_xlfn.NUMBERVALUE(RIGHT(P$2,1))>=$D22,$H22/12,0)*IF(_xlfn.NUMBERVALUE(RIGHT(P$2,1))-$D22>=1,1+((_xlfn.NUMBERVALUE(RIGHT(P$2,1))-$D22)*$H$25),1) -> 10500 | Q14: =IF(_xlfn.NUMBERVALUE(RIGHT(Q$2,1))>=$D22,$H22/12,0)*IF(_xlfn.NUMBERVALUE(RIGHT(Q$2,1))-$D22>=1,1+((_xlfn.NUMBERVALUE(RIGHT(Q$2,1))-$D22)*$H$25),1) -> 10500 | R14: =IF(_xlfn.NUMBERVALUE(RIGHT(R$2,1))>=$D22,$H22/12,0)*IF(_xlfn.NUMBERVALUE(RIGHT(R$2,1))-$D22>=1,1+((_xlfn.NUMBERVALUE(RIGHT(R$2,1))-$D22)*$H$25),1) -> 10500 | S14: =IF(_xlfn.NUMBERVALUE(RIGHT(S$2,1))>=$D22,$H22/12,0)*IF(_xlfn.NUMBERVALUE(RIGHT(S$2,1))-$D22>=1,1+((_xlfn.NUMBERVALUE(RIGHT(S$2,1))-$D22)*$H$25),1) -> 10500 | T14: =IF(_xlfn.NUMBERVALUE(RIGHT(T$2,1))>=$D22,$H22/12,0)*IF(_xlfn.NUMBERVALUE(RIGHT(T$2,1))-$D22>=1,1+((_xlfn.NUMBERVALUE(RIGHT(T$2,1))-$D22)*$H$25),1) -> 10500 | ... BT14: =IF(_xlfn.NUMBERVALUE(RIGHT(BT$2,1))>=$D22,$H22/12,0)*IF(_xlfn.NUMBERVALUE(RIGHT(BT$2,1))-$D22>=1,1+((_xlfn.NUMBERVALUE(RIGHT(BT$2,1))-$D22)*$H$25),1) -> 12600
B15: Sales rep | C15: 52500 | D15: 2 | E15: 0.25 | F15: 0.05 | G15: 0.1 | H15: =C15*E15+C15*F15+C15*G15+C15 -> 73500 | K15: Digital Marketing Specialist | M15: =IF(_xlfn.NUMBERVALUE(RIGHT(M$2,1))>=$D23,$H23/12,0)*IF(_xlfn.NUMBERVALUE(RIGHT(M$2,1))-$D23>=1,1+((_xlfn.NUMBERVALUE(RIGHT(M$2,1))-$D23)*$H$25),1) -> 0 | N15: =IF(_xlfn.NUMBERVALUE(RIGHT(N$2,1))>=$D23,$H23/12,0)*IF(_xlfn.NUMBERVALUE(RIGHT(N$2,1))-$D23>=1,1+((_xlfn.NUMBERVALUE(RIGHT(N$2,1))-$D23)*$H$25),1) -> 0 | O15: =IF(_xlfn.NUMBERVALUE(RIGHT(O$2,1))>=$D23,$H23/12,0)*IF(_xlfn.NUMBERVALUE(RIGHT(O$2,1))-$D23>=1,1+((_xlfn.NUMBERVALUE(RIGHT(O$2,1))-$D23)*$H$25),1) -> 0 | P15: =IF(_xlfn.NUMBERVALUE(RIGHT(P$2,1))>=$D23,$H23/12,0)*IF(_xlfn.NUMBERVALUE(RIGHT(P$2,1))-$D23>=1,1+((_xlfn.NUMBERVALUE(RIGHT(P$2,1))-$D23)*$H$25),1) -> 0 | Q15: =IF(_xlfn.NUMBERVALUE(RIGHT(Q$2,1))>=$D23,$H23/12,0)*IF(_xlfn.NUMBERVALUE(RIGHT(Q$2,1))-$D23>=1,1+((_xlfn.NUMBERVALUE(RIGHT(Q$2,1))-$D23)*$H$25),1) -> 0 | R15: =IF(_xlfn.NUMBERVALUE(RIGHT(R$2,1))>=$D23,$H23/12,0)*IF(_xlfn.NUMBERVALUE(RIGHT(R$2,1))-$D23>=1,1+((_xlfn.NUMBERVALUE(RIGHT(R$2,1))-$D23)*$H$25),1) -> 0 | S15: =IF(_xlfn.NUMBERVALUE(RIGHT(S$2,1))>=$D23,$H23/12,0)*IF(_xlfn.NUMBERVALUE(RIGHT(S$2,1))-$D23>=1,1+((_xlfn.NUMBERVALUE(RIGHT(S$2,1))-$D23)*$H$25),1) -> 0 | T15: =IF(_xlfn.NUMBERVALUE(RIGHT(T$2,1))>=$D23,$H23/12,0)*IF(_xlfn.NUMBERVALUE(RIGHT(T$2,1))-$D23>=1,1+((_xlfn.NUMBERVALUE(RIGHT(T$2,1))-$D23)*$H$25),1) -> 0 | ... BT15: =IF(_xlfn.NUMBERVALUE(RIGHT(BT$2,1))>=$D23,$H23/12,0)*IF(_xlfn.NUMBERVALUE(RIGHT(BT$2,1))-$D23>=1,1+((_xlfn.NUMBERVALUE(RIGHT(BT$2,1))-$D23)*$H$25),1) -> 8050
B16: Senior Sales Rep | C16: 67500 | D16: 3 | E16: 0.25 | F16: 0.05 | G16: 0.1 | H16: =C16*E16+C16*F16+C16*G16+C16 -> 94500
B17: Additional Sales Rep | C17: 52500 | D17: 5 | E17: 0.25 | F17: 0.05 | G17: 0.1 | H17: =C17*E17+C17*F17+C17*G17+C17 -> 73500 | K17: Total Marketing Wages | M17: =SUM(M14:M15) -> 10500 | N17: =SUM(N14:N15) -> 10500 | O17: =SUM(O14:O15) -> 10500 | P17: =SUM(P14:P15) -> 10500 | Q17: =SUM(Q14:Q15) -> 10500 | R17: =SUM(R14:R15) -> 10500 | S17: =SUM(S14:S15) -> 10500 | T17: =SUM(T14:T15) -> 10500 | ... BT17: =SUM(BT14:BT15) -> 20650
B18: Regional Sales Manager | C18: 75000 | D18: 4 | E18: 0.27 | F18: 0.06 | G18: 0.11 | H18: =C18*E18+C18*F18+C18*G18+C18 -> 108000
B19: Customer Success Manager | C19: 52500 | D19: 4 | E19: 0.25 | F19: 0.05 | G19: 0.1 | H19: =C19*E19+C19*F19+C19*G19+C19 -> 73500 | K19: Sales VP | M19: =IF(_xlfn.NUMBERVALUE(RIGHT(M$2,1))>=$D13,$H13/12,0)*IF(_xlfn.NUMBERVALUE(RIGHT(M$2,1))-$D13>=1,1+((_xlfn.NUMBERVALUE(RIGHT(M$2,1))-$D13)*$H$25),1) -> 0 | N19: =IF(_xlfn.NUMBERVALUE(RIGHT(N$2,1))>=$D13,$H13/12,0)*IF(_xlfn.NUMBERVALUE(RIGHT(N$2,1))-$D13>=1,1+((_xlfn.NUMBERVALUE(RIGHT(N$2,1))-$D13)*$H$25),1) -> 0 | O19: =IF(_xlfn.NUMBERVALUE(RIGHT(O$2,1))>=$D13,$H13/12,0)*IF(_xlfn.NUMBERVALUE(RIGHT(O$2,1))-$D13>=1,1+((_xlfn.NUMBERVALUE(RIGHT(O$2,1))-$D13)*$H$25),1) -> 0 | P19: =IF(_xlfn.NUMBERVALUE(RIGHT(P$2,1))>=$D13,$H13/12,0)*IF(_xlfn.NUMBERVALUE(RIGHT(P$2,1))-$D13>=1,1+((_xlfn.NUMBERVALUE(RIGHT(P$2,1))-$D13)*$H$25),1) -> 0 | Q19: =IF(_xlfn.NUMBERVALUE(RIGHT(Q$2,1))>=$D13,$H13/12,0)*IF(_xlfn.NUMBERVALUE(RIGHT(Q$2,1))-$D13>=1,1+((_xlfn.NUMBERVALUE(RIGHT(Q$2,1))-$D13)*$H$25),1) -> 0 | R19: =IF(_xlfn.NUMBERVALUE(RIGHT(R$2,1))>=$D13,$H13/12,0)*IF(_xlfn.NUMBERVALUE(RIGHT(R$2,1))-$D13>=1,1+((_xlfn.NUMBERVALUE(RIGHT(R$2,1))-$D13)*$H$25),1) -> 0 | S19: =IF(_xlfn.NUMBERVALUE(RIGHT(S$2,1))>=$D13,$H13/12,0)*IF(_xlfn.NUMBERVALUE(RIGHT(S$2,1))-$D13>=1,1+((_xlfn.NUMBERVALUE(RIGHT(S$2,1))-$D13)*$H$25),1) -> 0 | T19: =IF(_xlfn.NUMBERVALUE(RIGHT(T$2,1))>=$D13,$H13/12,0)*IF(_xlfn.NUMBERVALUE(RIGHT(T$2,1))-$D13>=1,1+((_xlfn.NUMBERVALUE(RIGHT(T$2,1))-$D13)*$H$25),1) -> 0 | ... BT19: =IF(_xlfn.NUMBERVALUE(RIGHT(BT$2,1))>=$D13,$H13/12,0)*IF(_xlfn.NUMBERVALUE(RIGHT(BT$2,1))-$D13>=1,1+((_xlfn.NUMBERVALUE(RIGHT(BT$2,1))-$D13)*$H$25),1) -> 10709.375 | BU19: =IF(_xlfn.NUMBERVALUE(RIGHT(BU$2,1))>=$D13,$H13/12,0)*IF(_xlfn.NUMBERVALUE(RIGHT(BU$2,1))-$D13>1,_xlfn.NUMBERVALUE(RIGHT(BU$2,1))-$D13*$H$25,1) -> 0 | BV19: =IF(_xlfn.NUMBERVALUE(RIGHT(BV$2,1))>=$D13,$H13/12,0)*IF(_xlfn.NUMBERVALUE(RIGHT(BV$2,1))-$D13>1,_xlfn.NUMBERVALUE(RIGHT(BV$2,1))-$D13*$H$25,1) -> 0 | BW19: =IF(_xlfn.NUMBERVALUE(RIGHT(BW$2,1))>=$D13,$H13/12,0)*IF(_xlfn.NUMBERVALUE(RIGHT(BW$2,1))-$D13>1,_xlfn.NUMBERVALUE(RIGHT(BW$2,1))-$D13*$H$25,1) -> 0
K20: Sales rep | M20: =IF(_xlfn.NUMBERVALUE(RIGHT(M$2,1))>=$D14,$H14/12,0)*IF(_xlfn.NUMBERVALUE(RIGHT(M$2,1))-$D14>=1,1+((_xlfn.NUMBERVALUE(RIGHT(M$2,1))-$D14)*$H$25),1) -> 0 | N20: =IF(_xlfn.NUMBERVALUE(RIGHT(N$2,1))>=$D14,$H14/12,0)*IF(_xlfn.NUMBERVALUE(RIGHT(N$2,1))-$D14>=1,1+((_xlfn.NUMBERVALUE(RIGHT(N$2,1))-$D14)*$H$25),1) -> 0 | O20: =IF(_xlfn.NUMBERVALUE(RIGHT(O$2,1))>=$D14,$H14/12,0)*IF(_xlfn.NUMBERVALUE(RIGHT(O$2,1))-$D14>=1,1+((_xlfn.NUMBERVALUE(RIGHT(O$2,1))-$D14)*$H$25),1) -> 0 | P20: =IF(_xlfn.NUMBERVALUE(RIGHT(P$2,1))>=$D14,$H14/12,0)*IF(_xlfn.NUMBERVALUE(RIGHT(P$2,1))-$D14>=1,1+((_xlfn.NUMBERVALUE(RIGHT(P$2,1))-$D14)*$H$25),1) -> 0 | Q20: =IF(_xlfn.NUMBERVALUE(RIGHT(Q$2,1))>=$D14,$H14/12,0)*IF(_xlfn.NUMBERVALUE(RIGHT(Q$2,1))-$D14>=1,1+((_xlfn.NUMBERVALUE(RIGHT(Q$2,1))-$D14)*$H$25),1) -> 0 | R20: =IF(_xlfn.NUMBERVALUE(RIGHT(R$2,1))>=$D14,$H14/12,0)*IF(_xlfn.NUMBERVALUE(RIGHT(R$2,1))-$D14>=1,1+((_xlfn.NUMBERVALUE(RIGHT(R$2,1))-$D14)*$H$25),1) -> 0 | S20: =IF(_xlfn.NUMBERVALUE(RIGHT(S$2,1))>=$D14,$H14/12,0)*IF(_xlfn.NUMBERVALUE(RIGHT(S$2,1))-$D14>=1,1+((_xlfn.NUMBERVALUE(RIGHT(S$2,1))-$D14)*$H$25),1) -> 0 | T20: =IF(_xlfn.NUMBERVALUE(RIGHT(T$2,1))>=$D14,$H14/12,0)*IF(_xlfn.NUMBERVALUE(RIGHT(T$2,1))-$D14>=1,1+((_xlfn.NUMBERVALUE(RIGHT(T$2,1))-$D14)*$H$25),1) -> 0 | ... BT20: =IF(_xlfn.NUMBERVALUE(RIGHT(BT$2,1))>=$D14,$H14/12,0)*IF(_xlfn.NUMBERVALUE(RIGHT(BT$2,1))-$D14>=1,1+((_xlfn.NUMBERVALUE(RIGHT(BT$2,1))-$D14)*$H$25),1) -> 7043.75
K21: Sales rep | M21: =IF(_xlfn.NUMBERVALUE(RIGHT(M$2,1))>=$D15,$H15/12,0)*IF(_xlfn.NUMBERVALUE(RIGHT(M$2,1))-$D15>=1,1+((_xlfn.NUMBERVALUE(RIGHT(M$2,1))-$D15)*$H$25),1) -> 0 | N21: =IF(_xlfn.NUMBERVALUE(RIGHT(N$2,1))>=$D15,$H15/12,0)*IF(_xlfn.NUMBERVALUE(RIGHT(N$2,1))-$D15>=1,1+((_xlfn.NUMBERVALUE(RIGHT(N$2,1))-$D15)*$H$25),1) -> 0 | O21: =IF(_xlfn.NUMBERVALUE(RIGHT(O$2,1))>=$D15,$H15/12,0)*IF(_xlfn.NUMBERVALUE(RIGHT(O$2,1))-$D15>=1,1+((_xlfn.NUMBERVALUE(RIGHT(O$2,1))-$D15)*$H$25),1) -> 0 | P21: =IF(_xlfn.NUMBERVALUE(RIGHT(P$2,1))>=$D15,$H15/12,0)*IF(_xlfn.NUMBERVALUE(RIGHT(P$2,1))-$D15>=1,1+((_xlfn.NUMBERVALUE(RIGHT(P$2,1))-$D15)*$H$25),1) -> 0 | Q21: =IF(_xlfn.NUMBERVALUE(RIGHT(Q$2,1))>=$D15,$H15/12,0)*IF(_xlfn.NUMBERVALUE(RIGHT(Q$2,1))-$D15>=1,1+((_xlfn.NUMBERVALUE(RIGHT(Q$2,1))-$D15)*$H$25),1) -> 0 | R21: =IF(_xlfn.NUMBERVALUE(RIGHT(R$2,1))>=$D15,$H15/12,0)*IF(_xlfn.NUMBERVALUE(RIGHT(R$2,1))-$D15>=1,1+((_xlfn.NUMBERVALUE(RIGHT(R$2,1))-$D15)*$H$25),1) -> 0 | S21: =IF(_xlfn.NUMBERVALUE(RIGHT(S$2,1))>=$D15,$H15/12,0)*IF(_xlfn.NUMBERVALUE(RIGHT(S$2,1))-$D15>=1,1+((_xlfn.NUMBERVALUE(RIGHT(S$2,1))-$D15)*$H$25),1) -> 0 | T21: =IF(_xlfn.NUMBERVALUE(RIGHT(T$2,1))>=$D15,$H15/12,0)*IF(_xlfn.NUMBERVALUE(RIGHT(T$2,1))-$D15>=1,1+((_xlfn.NUMBERVALUE(RIGHT(T$2,1))-$D15)*$H$25),1) -> 0 | ... BT21: =IF(_xlfn.NUMBERVALUE(RIGHT(BT$2,1))>=$D15,$H15/12,0)*IF(_xlfn.NUMBERVALUE(RIGHT(BT$2,1))-$D15>=1,1+((_xlfn.NUMBERVALUE(RIGHT(BT$2,1))-$D15)*$H$25),1) -> 7043.75
B22: Marketing Manager | C22: 90000 | D22: 1 | E22: 0.25 | F22: 0.05 | G22: 0.1 | H22: =C22*E22+C22*F22+C22*G22+C22 -> 126000 | K22: Senior Sales Rep | M22: =IF(_xlfn.NUMBERVALUE(RIGHT(M$2,1))>=$D16,$H16/12,0)*IF(_xlfn.NUMBERVALUE(RIGHT(M$2,1))-$D16>=1,1+((_xlfn.NUMBERVALUE(RIGHT(M$2,1))-$D16)*$H$25),1) -> 0 | N22: =IF(_xlfn.NUMBERVALUE(RIGHT(N$2,1))>=$D16,$H16/12,0)*IF(_xlfn.NUMBERVALUE(RIGHT(N$2,1))-$D16>=1,1+((_xlfn.NUMBERVALUE(RIGHT(N$2,1))-$D16)*$H$25),1) -> 0 | O22: =IF(_xlfn.NUMBERVALUE(RIGHT(O$2,1))>=$D16,$H16/12,0)*IF(_xlfn.NUMBERVALUE(RIGHT(O$2,1))-$D16>=1,1+((_xlfn.NUMBERVALUE(RIGHT(O$2,1))-$D16)*$H$25),1) -> 0 | P22: =IF(_xlfn.NUMBERVALUE(RIGHT(P$2,1))>=$D16,$H16/12,0)*IF(_xlfn.NUMBERVALUE(RIGHT(P$2,1))-$D16>=1,1+((_xlfn.NUMBERVALUE(RIGHT(P$2,1))-$D16)*$H$25),1) -> 0 | Q22: =IF(_xlfn.NUMBERVALUE(RIGHT(Q$2,1))>=$D16,$H16/12,0)*IF(_xlfn.NUMBERVALUE(RIGHT(Q$2,1))-$D16>=1,1+((_xlfn.NUMBERVALUE(RIGHT(Q$2,1))-$D16)*$H$25),1) -> 0 | R22: =IF(_xlfn.NUMBERVALUE(RIGHT(R$2,1))>=$D16,$H16/12,0)*IF(_xlfn.NUMBERVALUE(RIGHT(R$2,1))-$D16>=1,1+((_xlfn.NUMBERVALUE(RIGHT(R$2,1))-$D16)*$H$25),1) -> 0 | S22: =IF(_xlfn.NUMBERVALUE(RIGHT(S$2,1))>=$D16,$H16/12,0)*IF(_xlfn.NUMBERVALUE(RIGHT(S$2,1))-$D16>=1,1+((_xlfn.NUMBERVALUE(RIGHT(S$2,1))-$D16)*$H$25),1) -> 0 | T22: =IF(_xlfn.NUMBERVALUE(RIGHT(T$2,1))>=$D16,$H16/12,0)*IF(_xlfn.NUMBERVALUE(RIGHT(T$2,1))-$D16>=1,1+((_xlfn.NUMBERVALUE(RIGHT(T$2,1))-$D16)*$H$25),1) -> 0 | ... BT22: =IF(_xlfn.NUMBERVALUE(RIGHT(BT$2,1))>=$D16,$H16/12,0)*IF(_xlfn.NUMBERVALUE(RIGHT(BT$2,1))-$D16>=1,1+((_xlfn.NUMBERVALUE(RIGHT(BT$2,1))-$D16)*$H$25),1) -> 8662.5
B23: Digital Marketing Specialist | C23: 60000 | D23: 2 | E23: 0.25 | F23: 0.05 | G23: 0.1 | H23: =C23*E23+C23*F23+C23*G23+C23 -> 84000 | K23: Additional Sales Rep | M23: =IF(_xlfn.NUMBERVALUE(RIGHT(M$2,1))>=$D17,$H17/12,0)*IF(_xlfn.NUMBERVALUE(RIGHT(M$2,1))-$D17>=1,1+((_xlfn.NUMBERVALUE(RIGHT(M$2,1))-$D17)*$H$25),1) -> 0 | N23: =IF(_xlfn.NUMBERVALUE(RIGHT(N$2,1))>=$D17,$H17/12,0)*IF(_xlfn.NUMBERVALUE(RIGHT(N$2,1))-$D17>=1,1+((_xlfn.NUMBERVALUE(RIGHT(N$2,1))-$D17)*$H$25),1) -> 0 | O23: =IF(_xlfn.NUMBERVALUE(RIGHT(O$2,1))>=$D17,$H17/12,0)*IF(_xlfn.NUMBERVALUE(RIGHT(O$2,1))-$D17>=1,1+((_xlfn.NUMBERVALUE(RIGHT(O$2,1))-$D17)*$H$25),1) -> 0 | P23: =IF(_xlfn.NUMBERVALUE(RIGHT(P$2,1))>=$D17,$H17/12,0)*IF(_xlfn.NUMBERVALUE(RIGHT(P$2,1))-$D17>=1,1+((_xlfn.NUMBERVALUE(RIGHT(P$2,1))-$D17)*$H$25),1) -> 0 | Q23: =IF(_xlfn.NUMBERVALUE(RIGHT(Q$2,1))>=$D17,$H17/12,0)*IF(_xlfn.NUMBERVALUE(RIGHT(Q$2,1))-$D17>=1,1+((_xlfn.NUMBERVALUE(RIGHT(Q$2,1))-$D17)*$H$25),1) -> 0 | R23: =IF(_xlfn.NUMBERVALUE(RIGHT(R$2,1))>=$D17,$H17/12,0)*IF(_xlfn.NUMBERVALUE(RIGHT(R$2,1))-$D17>=1,1+((_xlfn.NUMBERVALUE(RIGHT(R$2,1))-$D17)*$H$25),1) -> 0 | S23: =IF(_xlfn.NUMBERVALUE(RIGHT(S$2,1))>=$D17,$H17/12,0)*IF(_xlfn.NUMBERVALUE(RIGHT(S$2,1))-$D17>=1,1+((_xlfn.NUMBERVALUE(RIGHT(S$2,1))-$D17)*$H$25),1) -> 0 | T23: =IF(_xlfn.NUMBERVALUE(RIGHT(T$2,1))>=$D17,$H17/12,0)*IF(_xlfn.NUMBERVALUE(RIGHT(T$2,1))-$D17>=1,1+((_xlfn.NUMBERVALUE(RIGHT(T$2,1))-$D17)*$H$25),1) -> 0 | ... BT23: =IF(_xlfn.NUMBERVALUE(RIGHT(BT$2,1))>=$D17,$H17/12,0)*IF(_xlfn.NUMBERVALUE(RIGHT(BT$2,1))-$D17>=1,1+((_xlfn.NUMBERVALUE(RIGHT(BT$2,1))-$D17)*$H$25),1) -> 6125
K24: Regional Sales Manager | M24: =IF(_xlfn.NUMBERVALUE(RIGHT(M$2,1))>=$D18,$H18/12,0)*IF(_xlfn.NUMBERVALUE(RIGHT(M$2,1))-$D18>=1,1+((_xlfn.NUMBERVALUE(RIGHT(M$2,1))-$D18)*$H$25),1) -> 0 | N24: =IF(_xlfn.NUMBERVALUE(RIGHT(N$2,1))>=$D18,$H18/12,0)*IF(_xlfn.NUMBERVALUE(RIGHT(N$2,1))-$D18>=1,1+((_xlfn.NUMBERVALUE(RIGHT(N$2,1))-$D18)*$H$25),1) -> 0 | O24: =IF(_xlfn.NUMBERVALUE(RIGHT(O$2,1))>=$D18,$H18/12,0)*IF(_xlfn.NUMBERVALUE(RIGHT(O$2,1))-$D18>=1,1+((_xlfn.NUMBERVALUE(RIGHT(O$2,1))-$D18)*$H$25),1) -> 0 | P24: =IF(_xlfn.NUMBERVALUE(RIGHT(P$2,1))>=$D18,$H18/12,0)*IF(_xlfn.NUMBERVALUE(RIGHT(P$2,1))-$D18>=1,1+((_xlfn.NUMBERVALUE(RIGHT(P$2,1))-$D18)*$H$25),1) -> 0 | Q24: =IF(_xlfn.NUMBERVALUE(RIGHT(Q$2,1))>=$D18,$H18/12,0)*IF(_xlfn.NUMBERVALUE(RIGHT(Q$2,1))-$D18>=1,1+((_xlfn.NUMBERVALUE(RIGHT(Q$2,1))-$D18)*$H$25),1) -> 0 | R24: =IF(_xlfn.NUMBERVALUE(RIGHT(R$2,1))>=$D18,$H18/12,0)*IF(_xlfn.NUMBERVALUE(RIGHT(R$2,1))-$D18>=1,1+((_xlfn.NUMBERVALUE(RIGHT(R$2,1))-$D18)*$H$25),1) -> 0 | S24: =IF(_xlfn.NUMBERVALUE(RIGHT(S$2,1))>=$D18,$H18/12,0)*IF(_xlfn.NUMBERVALUE(RIGHT(S$2,1))-$D18>=1,1+((_xlfn.NUMBERVALUE(RIGHT(S$2,1))-$D18)*$H$25),1) -> 0 | T24: =IF(_xlfn.NUMBERVALUE(RIGHT(T$2,1))>=$D18,$H18/12,0)*IF(_xlfn.NUMBERVALUE(RIGHT(T$2,1))-$D18>=1,1+((_xlfn.NUMBERVALUE(RIGHT(T$2,1))-$D18)*$H$25),1) -> 0 | ... BT24: =IF(_xlfn.NUMBERVALUE(RIGHT(BT$2,1))>=$D18,$H18/12,0)*IF(_xlfn.NUMBERVALUE(RIGHT(BT$2,1))-$D18>=1,1+((_xlfn.NUMBERVALUE(RIGHT(BT$2,1))-$D18)*$H$25),1) -> 9450
G25: Annual Raises | H25: 0.05 | K25: Customer Success Manager | M25: =IF(_xlfn.NUMBERVALUE(RIGHT(M$2,1))>=$D19,$H19/12,0)*IF(_xlfn.NUMBERVALUE(RIGHT(M$2,1))-$D19>=1,1+((_xlfn.NUMBERVALUE(RIGHT(M$2,1))-$D19)*$H$25),1) -> 0 | N25: =IF(_xlfn.NUMBERVALUE(RIGHT(N$2,1))>=$D19,$H19/12,0)*IF(_xlfn.NUMBERVALUE(RIGHT(N$2,1))-$D19>=1,1+((_xlfn.NUMBERVALUE(RIGHT(N$2,1))-$D19)*$H$25),1) -> 0 | O25: =IF(_xlfn.NUMBERVALUE(RIGHT(O$2,1))>=$D19,$H19/12,0)*IF(_xlfn.NUMBERVALUE(RIGHT(O$2,1))-$D19>=1,1+((_xlfn.NUMBERVALUE(RIGHT(O$2,1))-$D19)*$H$25),1) -> 0 | P25: =IF(_xlfn.NUMBERVALUE(RIGHT(P$2,1))>=$D19,$H19/12,0)*IF(_xlfn.NUMBERVALUE(RIGHT(P$2,1))-$D19>=1,1+((_xlfn.NUMBERVALUE(RIGHT(P$2,1))-$D19)*$H$25),1) -> 0 | Q25: =IF(_xlfn.NUMBERVALUE(RIGHT(Q$2,1))>=$D19,$H19/12,0)*IF(_xlfn.NUMBERVALUE(RIGHT(Q$2,1))-$D19>=1,1+((_xlfn.NUMBERVALUE(RIGHT(Q$2,1))-$D19)*$H$25),1) -> 0 | R25: =IF(_xlfn.NUMBERVALUE(RIGHT(R$2,1))>=$D19,$H19/12,0)*IF(_xlfn.NUMBERVALUE(RIGHT(R$2,1))-$D19>=1,1+((_xlfn.NUMBERVALUE(RIGHT(R$2,1))-$D19)*$H$25),1) -> 0 | S25: =IF(_xlfn.NUMBERVALUE(RIGHT(S$2,1))>=$D19,$H19/12,0)*IF(_xlfn.NUMBERVALUE(RIGHT(S$2,1))-$D19>=1,1+((_xlfn.NUMBERVALUE(RIGHT(S$2,1))-$D19)*$H$25),1) -> 0 | T25: =IF(_xlfn.NUMBERVALUE(RIGHT(T$2,1))>=$D19,$H19/12,0)*IF(_xlfn.NUMBERVALUE(RIGHT(T$2,1))-$D19>=1,1+((_xlfn.NUMBERVALUE(RIGHT(T$2,1))-$D19)*$H$25),1) -> 0 | ... BT25: =IF(_xlfn.NUMBERVALUE(RIGHT(BT$2,1))>=$D19,$H19/12,0)*IF(_xlfn.NUMBERVALUE(RIGHT(BT$2,1))-$D19>=1,1+((_xlfn.NUMBERVALUE(RIGHT(BT$2,1))-$D19)*$H$25),1) -> 6431.25
B27: Year | C27: 1 | D27: 2 | E27: 3 | F27: 4 | G27: 5 | K27: =B9 -> Sales Lead Gen | M27: =_xlfn.XLOOKUP(_xlfn.NUMBERVALUE(RIGHT(M$2,1)),$C$3:$G$3,$C6:$G6)/12 -> 500 | N27: =_xlfn.XLOOKUP(_xlfn.NUMBERVALUE(RIGHT(N$2,1)),$C$3:$G$3,$C6:$G6)/12 -> 500 | O27: =_xlfn.XLOOKUP(_xlfn.NUMBERVALUE(RIGHT(O$2,1)),$C$3:$G$3,$C6:$G6)/12 -> 500 | P27: =_xlfn.XLOOKUP(_xlfn.NUMBERVALUE(RIGHT(P$2,1)),$C$3:$G$3,$C6:$G6)/12 -> 500 | Q27: =_xlfn.XLOOKUP(_xlfn.NUMBERVALUE(RIGHT(Q$2,1)),$C$3:$G$3,$C6:$G6)/12 -> 500 | R27: =_xlfn.XLOOKUP(_xlfn.NUMBERVALUE(RIGHT(R$2,1)),$C$3:$G$3,$C6:$G6)/12 -> 500 | S27: =_xlfn.XLOOKUP(_xlfn.NUMBERVALUE(RIGHT(S$2,1)),$C$3:$G$3,$C6:$G6)/12 -> 500 | T27: =_xlfn.XLOOKUP(_xlfn.NUMBERVALUE(RIGHT(T$2,1)),$C$3:$G$3,$C6:$G6)/12 -> 500 | ... BT27: =_xlfn.XLOOKUP(_xlfn.NUMBERVALUE(RIGHT(BT$2,1)),$C$3:$G$3,$C6:$G6)/12 -> 1750
B28: Headcount | C28: =COUNTIF($D$13:$D$25,"<=1") -> 1 | D28: =COUNTIF($D$13:$D$25,"<=2") -> 5 | E28: =COUNTIF($D$13:$D$25,"<=3") -> 6 | F28: =COUNTIF($D$13:$D$25,"<=4") -> 8 | G28: =COUNTIF($D$13:$D$25,"<=5") -> 9 | J28: Comissions
K29: Sales VP | N29: ='Sales Rev'!M21 -> 0 | O29: ='Sales Rev'!N21 -> 0 | P29: ='Sales Rev'!O21 -> 0 | Q29: ='Sales Rev'!P21 -> 0 | R29: ='Sales Rev'!Q21 -> 0 | S29: ='Sales Rev'!R21 -> 0 | T29: ='Sales Rev'!S21 -> 0 | U29: ='Sales Rev'!T21 -> 0 | ... BT29: ='Sales Rev'!BS21 -> 4775.7946
K30: Sales rep | N30: ='Sales Rev'!M20 -> 0 | O30: ='Sales Rev'!N20 -> 0 | P30: ='Sales Rev'!O20 -> 0 | Q30: ='Sales Rev'!P20 -> 0 | R30: ='Sales Rev'!Q20 -> 0 | S30: ='Sales Rev'!R20 -> 0 | T30: ='Sales Rev'!S20 -> 0 | U30: ='Sales Rev'!T20 -> 0 | ... BT30: ='Sales Rev'!BS20 -> 5352.7474
K31: Sales rep | N31: ='Sales Rev'!M18 -> 0 | O31: ='Sales Rev'!N18 -> 0 | P31: ='Sales Rev'!O18 -> 0 | Q31: ='Sales Rev'!P18 -> 0 | R31: ='Sales Rev'!Q18 -> 0 | S31: ='Sales Rev'!R18 -> 0 | T31: ='Sales Rev'!S18 -> 0 | U31: ='Sales Rev'!T18 -> 0 | ... BT31: ='Sales Rev'!BS18 -> 5352.7474
K32: Senior Sales Rep | N32: ='Sales Rev'!M22 -> 0 | O32: ='Sales Rev'!N22 -> 0 | P32: ='Sales Rev'!O22 -> 0 | Q32: ='Sales Rev'!P22 -> 0 | R32: ='Sales Rev'!Q22 -> 0 | S32: ='Sales Rev'!R22 -> 0 | T32: ='Sales Rev'!S22 -> 0 | U32: ='Sales Rev'!T22 -> 0 | ... BT32: ='Sales Rev'!BS22 -> 2340.0243
K33: Additional Sales Rep | N33: ='Sales Rev'!M19 -> 0 | O33: ='Sales Rev'!N19 -> 0 | P33: ='Sales Rev'!O19 -> 0 | Q33: ='Sales Rev'!P19 -> 0 | R33: ='Sales Rev'!Q19 -> 0 | S33: ='Sales Rev'!R19 -> 0 | T33: ='Sales Rev'!S19 -> 0 | U33: ='Sales Rev'!T19 -> 0 | ... BT33: ='Sales Rev'!BS19 -> 825.30661
K34: Regional Sales Manager | N34: ='Sales Rev'!M17 -> 0 | O34: ='Sales Rev'!N17 -> 0 | P34: ='Sales Rev'!O17 -> 0 | Q34: ='Sales Rev'!P17 -> 0 | R34: ='Sales Rev'!Q17 -> 0 | S34: ='Sales Rev'!R17 -> 0 | T34: ='Sales Rev'!S17 -> 0 | U34: ='Sales Rev'!T17 -> 0 | ... BT34: ='Sales Rev'!BS17 -> 1718.9111
K35: Customer Success Manager | N35: ='Sales Rev'!M15 -> 0 | O35: ='Sales Rev'!N15 -> 0 | P35: ='Sales Rev'!O15 -> 0 | Q35: ='Sales Rev'!P15 -> 0 | R35: ='Sales Rev'!Q15 -> 0 | S35: ='Sales Rev'!R15 -> 0 | T35: ='Sales Rev'!S15 -> 0 | U35: ='Sales Rev'!T15 -> 0 | ... BT35: ='Sales Rev'!BS15 -> 732.95629
K37: Total Sales Expense | M37: =SUM(M19:M25,M27,M29:M35) -> 500 | N37: =SUM(N19:N25,N27,N29:N35) -> 500 | O37: =SUM(O19:O25,O27,O29:O35) -> 500 | P37: =SUM(P19:P25,P27,P29:P35) -> 500 | Q37: =SUM(Q19:Q25,Q27,Q29:Q35) -> 500 | R37: =SUM(R19:R25,R27,R29:R35) -> 500 | S37: =SUM(S19:S25,S27,S29:S35) -> 500 | T37: =SUM(T19:T25,T27,T29:T35) -> 500 | ... BT37: =SUM(BT19:BT25,BT27,BT29:BT35) -> 78314.113

Sheet CapEx
A1: Cap Ex DEPT
M2: Year 1 | N2: Year 1 | O2: Year 1 | P2: Year 1 | Q2: Year 1 | R2: Year 1 | S2: Year 1 | T2: Year 1 | U2: Year 1 | V2: Year 1 | W2: Year 1 | X2: Year 1 | Y2: Year 2 | Z2: Year 2 | AA2: Year 2 | AB2: Year 2 | AC2: Year 2 | AD2: Year 2 | AE2: Year 2 | AF2: Year 2 | AG2: Year 2 | AH2: Year 2 | AI2: Year 2 | AJ2: Year 2 | AK2: Year 3 | AL2: Year 3 | AM2: Year 3 | AN2: Year 3 | AO2: Year 3 | AP2: Year 3 | AQ2: Year 3 | AR2: Year 3 | AS2: Year 3 | AT2: Year 3 | AU2: Year 3 | AV2: Year 3 | AW2: Year 4 | AX2: Year 4 | AY2: Year 4 | AZ2: Year 4 | BA2: Year 4 | BB2: Year 4 | BC2: Year 4 | BD2: Year 4 | BE2: Year 4 | BF2: Year 4 | BG2: Year 4 | BH2: Year 4 | BI2: Year 5 | BJ2: Year 5 | BK2: Year 5 | BL2: Year 5 | BM2: Year 5 | BN2: Year 5 | BO2: Year 5 | BP2: Year 5 | BQ2: Year 5 | BR2: Year 5 | BS2: Year 5 | BT2: Year 5
A3: Capital Expenditures | D3: Price | E3: Useful Life | J3: Depreciation | M3: Jan | N3: Feb | O3: Mar | P3: Apr | Q3: May | R3: Jun | S3: Jul | T3: Aug | U3: Sep | V3: Oct | W3: Nov | X3: Dec | Y3: Jan | Z3: Feb | AA3: Mar | AB3: Apr | AC3: May | AD3: Jun | AE3: Jul | AF3: Aug | AG3: Sep | AH3: Oct | AI3: Nov | AJ3: Dec | AK3: Jan | AL3: Feb | AM3: Mar | AN3: Apr | AO3: May | AP3: Jun | AQ3: Jul | AR3: Aug | AS3: Sep | AT3: Oct | AU3: Nov | AV3: Dec | AW3: Jan | AX3: Feb | AY3: Mar | AZ3: Apr | BA3: May | BB3: Jun | BC3: Jul | BD3: Aug | BE3: Sep | BF3: Oct | BG3: Nov | BH3: Dec | BI3: Jan | BJ3: Feb | BK3: Mar | BL3: Apr | BM3: May | BN3: Jun | BO3: Jul | BP3: Aug | BQ3: Sep | BR3: Oct | BS3: Nov | BT3: Dec
C4: Developer Workstations / Laptops Per Employee | D4: 2000 | E4: 5 | K4: Developer Workstations / Laptops Per Employee | M4: =_xlfn.XLOOKUP(_xlfn.NUMBERVALUE(RIGHT(M$2,1)),$C$11:$G$11,$C28:$G28)*$D4/12/$E4 -> 100 | N4: =_xlfn.XLOOKUP(_xlfn.NUMBERVALUE(RIGHT(N$2,1)),$C$11:$G$11,$C28:$G28)*$D4/12/$E4 -> 100 | O4: =_xlfn.XLOOKUP(_xlfn.NUMBERVALUE(RIGHT(O$2,1)),$C$11:$G$11,$C28:$G28)*$D4/12/$E4 -> 100 | P4: =_xlfn.XLOOKUP(_xlfn.NUMBERVALUE(RIGHT(P$2,1)),$C$11:$G$11,$C28:$G28)*$D4/12/$E4 -> 100 | Q4: =_xlfn.XLOOKUP(_xlfn.NUMBERVALUE(RIGHT(Q$2,1)),$C$11:$G$11,$C28:$G28)*$D4/12/$E4 -> 100 | R4: =_xlfn.XLOOKUP(_xlfn.NUMBERVALUE(RIGHT(R$2,1)),$C$11:$G$11,$C28:$G28)*$D4/12/$E4 -> 100 | S4: =_xlfn.XLOOKUP(_xlfn.NUMBERVALUE(RIGHT(S$2,1)),$C$11:$G$11,$C28:$G28)*$D4/12/$E4 -> 100 | T4: =_xlfn.XLOOKUP(_xlfn.NUMBERVALUE(RIGHT(T$2,1)),$C$11:$G$11,$C28:$G28)*$D4/12/$E4 -> 100 | ... BT4: =_xlfn.XLOOKUP(_xlfn.NUMBERVALUE(RIGHT(BT$2,1)),$C$11:$G$11,$C28:$G28)*$D4/12/$E4 -> 766.66667
C5: Office Networking Gear | D5: 4000 | E5: 5 | K5: Office Networking Gear | M5: =_xlfn.XLOOKUP(_xlfn.NUMBERVALUE(RIGHT(M$2,1)),$C$11:$G$11,$C29:$G29)*$D5/12/$E5 -> 66.666667 | N5: =_xlfn.XLOOKUP(_xlfn.NUMBERVALUE(RIGHT(N$2,1)),$C$11:$G$11,$C29:$G29)*$D5/12/$E5 -> 66.666667 | O5: =_xlfn.XLOOKUP(_xlfn.NUMBERVALUE(RIGHT(O$2,1)),$C$11:$G$11,$C29:$G29)*$D5/12/$E5 -> 66.666667 | P5: =_xlfn.XLOOKUP(_xlfn.NUMBERVALUE(RIGHT(P$2,1)),$C$11:$G$11,$C29:$G29)*$D5/12/$E5 -> 66.666667 | Q5: =_xlfn.XLOOKUP(_xlfn.NUMBERVALUE(RIGHT(Q$2,1)),$C$11:$G$11,$C29:$G29)*$D5/12/$E5 -> 66.666667 | R5: =_xlfn.XLOOKUP(_xlfn.NUMBERVALUE(RIGHT(R$2,1)),$C$11:$G$11,$C29:$G29)*$D5/12/$E5 -> 66.666667 | S5: =_xlfn.XLOOKUP(_xlfn.NUMBERVALUE(RIGHT(S$2,1)),$C$11:$G$11,$C29:$G29)*$D5/12/$E5 -> 66.666667 | T5: =_xlfn.XLOOKUP(_xlfn.NUMBERVALUE(RIGHT(T$2,1)),$C$11:$G$11,$C29:$G29)*$D5/12/$E5 -> 66.666667 | ... BT5: =_xlfn.XLOOKUP(_xlfn.NUMBERVALUE(RIGHT(BT$2,1)),$C$11:$G$11,$C29:$G29)*$D5/12/$E5 -> 66.666667
